Workbook
Name FAPool: 'FA Pool'!$P$2:$P$741

Sheet My Roster
A1: Player | B1: NHL | C1: Pos | D1: Eligible | E1: Slot | F1: Status | G1: Age | H1: Salary | I1: FPts 25/26 | J1: FPts 25/26 per $M | K1: FP/G 25/26 | L1: FP/G 25/26 per $M | M1: Fantrax 26/27 | N1: A&G 26/27 | O1: Consensus 26/27 | P1: Change | Q1: Cons. per $M | R1: ADP | S1: · row | T1: SCENARIO 1 | W1: <name this plan> | AD1: SCENARIO 2 | AG1: <name this plan> | AN1: SCENARIO 3 | AQ1: <name this plan> | AX1: · drop order
T2: Player | U2: Pos | V2: Age | W2: Salary | X2: FPts 25/26 | Y2: Cons 26/27 | Z2: Cons/$M | AA2: ADP | AB2: Own | AD2: Player | AE2: Pos | AF2: Age | AG2: Salary | AH2: FPts 25/26 | AI2: Cons 26/27 | AJ2: Cons/$M | AK2: ADP | AL2: Own | AN2: Player | AO2: Pos | AP2: Age | AQ2: Salary | AR2: FPts 25/26 | AS2: Cons 26/27 | AT2: Cons/$M | AU2: ADP | AV2: Own
A3: ROSTER - counts toward the cap and scores | T3: ROSTER - counts toward the cap and scores | AD3: ROSTER - counts toward the cap and scores | AN3: ROSTER - counts toward the cap and scores
A4: =IFERROR(IF(INDEX(Rosters!$B$2:$B$516,$S4)="","",INDEX(Rosters!$B$2:$B$516,$S4)),"") | B4: =IFERROR(IF(INDEX(Rosters!$C$2:$C$516,$S4)="","",INDEX(Rosters!$C$2:$C$516,$S4)),"") | C4: =IFERROR(IF(INDEX(Rosters!$D$2:$D$516,$S4)="","",INDEX(Rosters!$D$2:$D$516,$S4)),"") | D4: =IFERROR(IF(INDEX(Rosters!$E$2:$E$516,$S4)="","",INDEX(Rosters!$E$2:$E$516,$S4)),"") | E4: =IFERROR(IF(INDEX(Rosters!$F$2:$F$516,$S4)="","",INDEX(Rosters!$F$2:$F$516,$S4)),"") | F4: =IFERROR(IF(INDEX(Rosters!$G$2:$G$516,$S4)="","",INDEX(Rosters!$G$2:$G$516,$S4)),"") | G4: =IFERROR(IF(INDEX(Rosters!$H$2:$H$516,$S4)="","",INDEX(Rosters!$H$2:$H$516,$S4)),"") | H4: =IFERROR(IF(INDEX(Rosters!$I$2:$I$516,$S4)="","",INDEX(Rosters!$I$2:$I$516,$S4)),"") | I4: =IFERROR(IF(INDEX(Rosters!$J$2:$J$516,$S4)="","",INDEX(Rosters!$J$2:$J$516,$S4)),"") | J4: =IFERROR(IF(INDEX(Rosters!$S$2:$S$516,$S4)="","",INDEX(Rosters!$S$2:$S$516,$S4)),"") | K4: =IFERROR(IF(INDEX(Rosters!$K$2:$K$516,$S4)="","",INDEX(Rosters!$K$2:$K$516,$S4)),"") | L4: =IFERROR(IF(INDEX(Rosters!$T$2:$T$516,$S4)="","",INDEX(Rosters!$T$2:$T$516,$S4)),"") | M4: =IFERROR(IF(INDEX(Rosters!$L$2:$L$516,$S4)="","",INDEX(Rosters!$L$2:$L$516,$S4)),"") | N4: =IFERROR(IF(INDEX(Rosters!$Q$2:$Q$516,$S4)="","",INDEX(Rosters!$Q$2:$Q$516,$S4)),"") | O4: =IFERROR(IF(INDEX(Rosters!$R$2:$R$516,$S4)="","",INDEX(Rosters!$R$2:$R$516,$S4)),"") | P4: =IFERROR(IF(INDEX(Rosters!$N$2:$N$516,$S4)="","",INDEX(Rosters!$N$2:$N$516,$S4)),"") | Q4: =IFERROR(IF(INDEX(Rosters!$O$2:$O$516,$S4)="","",INDEX(Rosters!$O$2:$O$516,$S4)),"") | R4: =IFERROR(IF(INDEX(Rosters!$P$2:$P$516,$S4)="","",INDEX(Rosters!$P$2:$P$516,$S4)),"") | S4: =IFERROR(MATCH('League Settings'!$B$2&"|ACTIVE|"&1,Rosters!$AD$2:$AD$516,0),"") | T4: Zach Werenski (CBJ D) | U4: =IFERROR(IF(INDEX('Player Pool'!$D$2:$D$8725,MATCH($T4,'Player Pool'!$Z$2:$Z$8725,0))="","",INDEX('Player Pool'!$D$2:$D$8725,MATCH($T4,'Player Pool'!$Z$2:$Z$8725,0))),"") | V4: =IFERROR(IF(INDEX('Player Pool'!$E$2:$E$8725,MATCH($T4,'Player Pool'!$Z$2:$Z$8725,0))="","",INDEX('Player Pool'!$E$2:$E$8725,MATCH($T4,'Player Pool'!$Z$2:$Z$8725,0))),"") | W4: =IFERROR(IF($T4="","",IF(ISNUMBER(IFERROR(INDEX(Rosters!$I$2:$I$516,MATCH(INDEX('Player Pool'!$V$2:$V$8725,MATCH($T4,'Player Pool'!$Z$2:$Z$8725,0)),Rosters!$W$2:$W$516,0)),"")),IFERROR(INDEX(Rosters!$I$2:$I$516,MATCH(INDEX('Player Pool'!$V$2:$V$8725,MATCH($T4,'Player Pool'!$Z$2:$Z$8725,0)),Rosters!$W$2:$W$516,0)),""),INDEX('Player Pool'!$H$2:$H$8725,MATCH($T4,'Player Pool'!$Z$2:$Z$8725,0)))),"") | X4: =IFERROR(IF(INDEX('Player Pool'!$I$2:$I$8725,MATCH($T4,'Player Pool'!$Z$2:$Z$8725,0))="","",INDEX('Player Pool'!$I$2:$I$8725,MATCH($T4,'Player Pool'!$Z$2:$Z$8725,0))),"") | Y4: =IFERROR(IF(INDEX('Player Pool'!$P$2:$P$8725,MATCH($T4,'Player Pool'!$Z$2:$Z$8725,0))="","",INDEX('Player Pool'!$P$2:$P$8725,MATCH($T4,'Player Pool'!$Z$2:$Z$8725,0))),"") | Z4: =IFERROR(IF(INDEX('Player Pool'!$R$2:$R$8725,MATCH($T4,'Player Pool'!$Z$2:$Z$8725,0))="","",INDEX('Player Pool'!$R$2:$R$8725,MATCH($T4,'Player Pool'!$Z$2:$Z$8725,0))),"") | AA4: =IFERROR(IF(INDEX('Player Pool'!$U$2:$U$8725,MATCH($T4,'Player Pool'!$Z$2:$Z$8725,0))="","",INDEX('Player Pool'!$U$2:$U$8725,MATCH($T4,'Player Pool'!$Z$2:$Z$8725,0))),"") | AB4: =IFERROR(IF($T4="","",IF(INDEX('Player Pool'!$G$2:$G$8725,MATCH($T4,'Player Pool'!$Z$2:$Z$8725,0))="FA","FA",IF(INDEX('Player Pool'!$G$2:$G$8725,MATCH($T4,'Player Pool'!$Z$2:$Z$8725,0))='League Settings'!$B$2,"MINE","TAKEN"))),"") | AD4: Zach Werenski (CBJ D) | AE4: =IFERROR(IF(INDEX('Player Pool'!$D$2:$D$8725,MATCH($AD4,'Player Pool'!$Z$2:$Z$8725,0))="","",INDEX('Player Pool'!$D$2:$D$8725,MATCH($AD4,'Player Pool'!$Z$2:$Z$8725,0))),"") | AF4: =IFERROR(IF(INDEX('Player Pool'!$E$2:$E$8725,MATCH($AD4,'Player Pool'!$Z$2:$Z$8725,0))="","",INDEX('Player Pool'!$E$2:$E$8725,MATCH($AD4,'Player Pool'!$Z$2:$Z$8725,0))),"") | AG4: =IFERROR(IF($AD4="","",IF(ISNUMBER(IFERROR(INDEX(Rosters!$I$2:$I$516,MATCH(INDEX('Player Pool'!$V$2:$V$8725,MATCH($AD4,'Player Pool'!$Z$2:$Z$8725,0)),Rosters!$W$2:$W$516,0)),"")),IFERROR(INDEX(Rosters!$I$2:$I$516,MATCH(INDEX('Player Pool'!$V$2:$V$8725,MATCH($AD4,'Player Pool'!$Z$2:$Z$8725,0)),Rosters!$W$2:$W$516,0)),""),INDEX('Player Pool'!$H$2:$H$8725,MATCH($AD4,'Player Pool'!$Z$2:$Z$8725,0)))),"") | AH4: =IFERROR(IF(INDEX('Player Pool'!$I$2:$I$8725,MATCH($AD4,'Player Pool'!$Z$2:$Z$8725,0))="","",INDEX('Player Pool'!$I$2:$I$8725,MATCH($AD4,'Player Pool'!$Z$2:$Z$8725,0))),"") | AI4: =IFERROR(IF(INDEX('Player Pool'!$P$2:$P$8725,MATCH($AD4,'Player Pool'!$Z$2:$Z$8725,0))="","",INDEX('Player Pool'!$P$2:$P$8725,MATCH($AD4,'Player Pool'!$Z$2:$Z$8725,0))),"") | AJ4: =IFERROR(IF(INDEX('Player Pool'!$R$2:$R$8725,MATCH($AD4,'Player Pool'!$Z$2:$Z$8725,0))="","",INDEX('Player Pool'!$R$2:$R$8725,MATCH($AD4,'Player Pool'!$Z$2:$Z$8725,0))),"") | AK4: =IFERROR(IF(INDEX('Player Pool'!$U$2:$U$8725,MATCH($AD4,'Player Pool'!$Z$2:$Z$8725,0))="","",INDEX('Player Pool'!$U$2:$U$8725,MATCH($AD4,'Player Pool'!$Z$2:$Z$8725,0))),"") | AL4: =IFERROR(IF($AD4="","",IF(INDEX('Player Pool'!$G$2:$G$8725,MATCH($AD4,'Player Pool'!$Z$2:$Z$8725,0))="FA","FA",IF(INDEX('Player Pool'!$G$2:$G$8725,MATCH($AD4,'Player Pool'!$Z$2:$Z$8725,0))='League Settings'!$B$2,"MINE","TAKEN"))),"") | AN4: Zach Werenski (CBJ D) | AO4: =IFERROR(IF(INDEX('Player Pool'!$D$2:$D$8725,MATCH($AN4,'Player Pool'!$Z$2:$Z$8725,0))="","",INDEX('Player Pool'!$D$2:$D$8725,MATCH($AN4,'Player Pool'!$Z$2:$Z$8725,0))),"") | AP4: =IFERROR(IF(INDEX('Player Pool'!$E$2:$E$8725,MATCH($AN4,'Player Pool'!$Z$2:$Z$8725,0))="","",INDEX('Player Pool'!$E$2:$E$8725,MATCH($AN4,'Player Pool'!$Z$2:$Z$8725,0))),"") | AQ4: =IFERROR(IF($AN4="","",IF(ISNUMBER(IFERROR(INDEX(Rosters!$I$2:$I$516,MATCH(INDEX('Player Pool'!$V$2:$V$8725,MATCH($AN4,'Player Pool'!$Z$2:$Z$8725,0)),Rosters!$W$2:$W$516,0)),"")),IFERROR(INDEX(Rosters!$I$2:$I$516,MATCH(INDEX('Player Pool'!$V$2:$V$8725,MATCH($AN4,'Player Pool'!$Z$2:$Z$8725,0)),Rosters!$W$2:$W$516,0)),""),INDEX('Player Pool'!$H$2:$H$8725,MATCH($AN4,'Player Pool'!$Z$2:$Z$8725,0)))),"") | AR4: =IFERROR(IF(INDEX('Player Pool'!$I$2:$I$8725,MATCH($AN4,'Player Pool'!$Z$2:$Z$8725,0))="","",INDEX('Player Pool'!$I$2:$I$8725,MATCH($AN4,'Player Pool'!$Z$2:$Z$8725,0))),"") | AS4: =IFERROR(IF(INDEX('Player Pool'!$P$2:$P$8725,MATCH($AN4,'Player Pool'!$Z$2:$Z$8725,0))="","",INDEX('Player Pool'!$P$2:$P$8725,MATCH($AN4,'Player Pool'!$Z$2:$Z$8725,0))),"") | AT4: =IFERROR(IF(INDEX('Player Pool'!$R$2:$R$8725,MATCH($AN4,'Player Pool'!$Z$2:$Z$8725,0))="","",INDEX('Player Pool'!$R$2:$R$8725,MATCH($AN4,'Player Pool'!$Z$2:$Z$8725,0))),"") | AU4: =IFERROR(IF(INDEX('Player Pool'!$U$2:$U$8725,MATCH($AN4,'Player Pool'!$Z$2:$Z$8725,0))="","",INDEX('Player Pool'!$U$2:$U$8725,MATCH($AN4,'Player Pool'!$Z$2:$Z$8725,0))),"") | AV4: =IFERROR(IF($AN4="","",IF(INDEX('Player Pool'!$G$2:$G$8725,MATCH($AN4,'Player Pool'!$Z$2:$Z$8725,0))="FA","FA",IF(INDEX('Player Pool'!$G$2:$G$8725,MATCH($AN4,'Player Pool'!$Z$2:$Z$8725,0))='League Settings'!$B$2,"MINE","TAKEN"))),"")
A5: =IFERROR(IF(INDEX(Rosters!$B$2:$B$516,$S5)="","",INDEX(Rosters!$B$2:$B$516,$S5)),"") | B5: =IFERROR(IF(INDEX(Rosters!$C$2:$C$516,$S5)="","",INDEX(Rosters!$C$2:$C$516,$S5)),"") | C5: =IFERROR(IF(INDEX(Rosters!$D$2:$D$516,$S5)="","",INDEX(Rosters!$D$2:$D$516,$S5)),"") | D5: =IFERROR(IF(INDEX(Rosters!$E$2:$E$516,$S5)="","",INDEX(Rosters!$E$2:$E$516,$S5)),"") | E5: =IFERROR(IF(INDEX(Rosters!$F$2:$F$516,$S5)="","",INDEX(Rosters!$F$2:$F$516,$S5)),"") | F5: =IFERROR(IF(INDEX(Rosters!$G$2:$G$516,$S5)="","",INDEX(Rosters!$G$2:$G$516,$S5)),"") | G5: =IFERROR(IF(INDEX(Rosters!$H$2:$H$516,$S5)="","",INDEX(Rosters!$H$2:$H$516,$S5)),"") | H5: =IFERROR(IF(INDEX(Rosters!$I$2:$I$516,$S5)="","",INDEX(Rosters!$I$2:$I$516,$S5)),"") | I5: =IFERROR(IF(INDEX(Rosters!$J$2:$J$516,$S5)="","",INDEX(Rosters!$J$2:$J$516,$S5)),"") | J5: =IFERROR(IF(INDEX(Rosters!$S$2:$S$516,$S5)="","",INDEX(Rosters!$S$2:$S$516,$S5)),"") | K5: =IFERROR(IF(INDEX(Rosters!$K$2:$K$516,$S5)="","",INDEX(Rosters!$K$2:$K$516,$S5)),"") | L5: =IFERROR(IF(INDEX(Rosters!$T$2:$T$516,$S5)="","",INDEX(Rosters!$T$2:$T$516,$S5)),"") | M5: =IFERROR(IF(INDEX(Rosters!$L$2:$L$516,$S5)="","",INDEX(Rosters!$L$2:$L$516,$S5)),"") | N5: =IFERROR(IF(INDEX(Rosters!$Q$2:$Q$516,$S5)="","",INDEX(Rosters!$Q$2:$Q$516,$S5)),"") | O5: =IFERROR(IF(INDEX(Rosters!$R$2:$R$516,$S5)="","",INDEX(Rosters!$R$2:$R$516,$S5)),"") | P5: =IFERROR(IF(INDEX(Rosters!$N$2:$N$516,$S5)="","",INDEX(Rosters!$N$2:$N$516,$S5)),"") | Q5: =IFERROR(IF(INDEX(Rosters!$O$2:$O$516,$S5)="","",INDEX(Rosters!$O$2:$O$516,$S5)),"") | R5: =IFERROR(IF(INDEX(Rosters!$P$2:$P$516,$S5)="","",INDEX(Rosters!$P$2:$P$516,$S5)),"") | S5: =IFERROR(MATCH('League Settings'!$B$2&"|ACTIVE|"&2,Rosters!$AD$2:$AD$516,0),"") | T5: Matthew Tkachuk (FLA RW) | U5: =IFERROR(IF(INDEX('Player Pool'!$D$2:$D$8725,MATCH($T5,'Player Pool'!$Z$2:$Z$8725,0))="","",INDEX('Player Pool'!$D$2:$D$8725,MATCH($T5,'Player Pool'!$Z$2:$Z$8725,0))),"") | V5: =IFERROR(IF(INDEX('Player Pool'!$E$2:$E$8725,MATCH($T5,'Player Pool'!$Z$2:$Z$8725,0))="","",INDEX('Player Pool'!$E$2:$E$8725,MATCH($T5,'Player Pool'!$Z$2:$Z$8725,0))),"") | W5: =IFERROR(IF($T5="","",IF(ISNUMBER(IFERROR(INDEX(Rosters!$I$2:$I$516,MATCH(INDEX('Player Pool'!$V$2:$V$8725,MATCH($T5,'Player Pool'!$Z$2:$Z$8725,0)),Rosters!$W$2:$W$516,0)),"")),IFERROR(INDEX(Rosters!$I$2:$I$516,MATCH(INDEX('Player Pool'!$V$2:$V$8725,MATCH($T5,'Player Pool'!$Z$2:$Z$8725,0)),Rosters!$W$2:$W$516,0)),""),INDEX('Player Pool'!$H$2:$H$8725,MATCH($T5,'Player Pool'!$Z$2:$Z$8725,0)))),"") | X5: =IFERROR(IF(INDEX('Player Pool'!$I$2:$I$8725,MATCH($T5,'Player Pool'!$Z$2:$Z$8725,0))="","",INDEX('Player Pool'!$I$2:$I$8725,MATCH($T5,'Player Pool'!$Z$2:$Z$8725,0))),"") | Y5: =IFERROR(IF(INDEX('Player Pool'!$P$2:$P$8725,MATCH($T5,'Player Pool'!$Z$2:$Z$8725,0))="","",INDEX('Player Pool'!$P$2:$P$8725,MATCH($T5,'Player Pool'!$Z$2:$Z$8725,0))),"") | Z5: =IFERROR(IF(INDEX('Player Pool'!$R$2:$R$8725,MATCH($T5,'Player Pool'!$Z$2:$Z$8725,0))="","",INDEX('Player Pool'!$R$2:$R$8725,MATCH($T5,'Player Pool'!$Z$2:$Z$8725,0))),"") | AA5: =IFERROR(IF(INDEX('Player Pool'!$U$2:$U$8725,MATCH($T5,'Player Pool'!$Z$2:$Z$8725,0))="","",INDEX('Player Pool'!$U$2:$U$8725,MATCH($T5,'Player Pool'!$Z$2:$Z$8725,0))),"") | AB5: =IFERROR(IF($T5="","",IF(INDEX('Player Pool'!$G$2:$G$8725,MATCH($T5,'Player Pool'!$Z$2:$Z$8725,0))="FA","FA",IF(INDEX('Player Pool'!$G$2:$G$8725,MATCH($T5,'Player Pool'!$Z$2:$Z$8725,0))='League Settings'!$B$2,"MINE","TAKEN"))),"") | AD5: Matthew Tkachuk (FLA RW) | AE5: =IFERROR(IF(INDEX('Player Pool'!$D$2:$D$8725,MATCH($AD5,'Player Pool'!$Z$2:$Z$8725,0))="","",INDEX('Player Pool'!$D$2:$D$8725,MATCH($AD5,'Player Pool'!$Z$2:$Z$8725,0))),"") | AF5: =IFERROR(IF(INDEX('Player Pool'!$E$2:$E$8725,MATCH($AD5,'Player Pool'!$Z$2:$Z$8725,0))="","",INDEX('Player Pool'!$E$2:$E$8725,MATCH($AD5,'Player Pool'!$Z$2:$Z$8725,0))),"") | AG5: =IFERROR(IF($AD5="","",IF(ISNUMBER(IFERROR(INDEX(Rosters!$I$2:$I$516,MATCH(INDEX('Player Pool'!$V$2:$V$8725,MATCH($AD5,'Player Pool'!$Z$2:$Z$8725,0)),Rosters!$W$2:$W$516,0)),"")),IFERROR(INDEX(Rosters!$I$2:$I$516,MATCH(INDEX('Player Pool'!$V$2:$V$8725,MATCH($AD5,'Player Pool'!$Z$2:$Z$8725,0)),Rosters!$W$2:$W$516,0)),""),INDEX('Player Pool'!$H$2:$H$8725,MATCH($AD5,'Player Pool'!$Z$2:$Z$8725,0)))),"") | AH5: =IFERROR(IF(INDEX('Player Pool'!$I$2:$I$8725,MATCH($AD5,'Player Pool'!$Z$2:$Z$8725,0))="","",INDEX('Player Pool'!$I$2:$I$8725,MATCH($AD5,'Player Pool'!$Z$2:$Z$8725,0))),"") | AI5: =IFERROR(IF(INDEX('Player Pool'!$P$2:$P$8725,MATCH($AD5,'Player Pool'!$Z$2:$Z$8725,0))="","",INDEX('Player Pool'!$P$2:$P$8725,MATCH($AD5,'Player Pool'!$Z$2:$Z$8725,0))),"") | AJ5: =IFERROR(IF(INDEX('Player Pool'!$R$2:$R$8725,MATCH($AD5,'Player Pool'!$Z$2:$Z$8725,0))="","",INDEX('Player Pool'!$R$2:$R$8725,MATCH($AD5,'Player Pool'!$Z$2:$Z$8725,0))),"") | AK5: =IFERROR(IF(INDEX('Player Pool'!$U$2:$U$8725,MATCH($AD5,'Player Pool'!$Z$2:$Z$8725,0))="","",INDEX('Player Pool'!$U$2:$U$8725,MATCH($AD5,'Player Pool'!$Z$2:$Z$8725,0))),"") | AL5: =IFERROR(IF($AD5="","",IF(INDEX('Player Pool'!$G$2:$G$8725,MATCH($AD5,'Player Pool'!$Z$2:$Z$8725,0))="FA","FA",IF(INDEX('Player Pool'!$G$2:$G$8725,MATCH($AD5,'Player Pool'!$Z$2:$Z$8725,0))='League Settings'!$B$2,"MINE","TAKEN"))),"") | AN5: Matthew Tkachuk (FLA RW) | AO5: =IFERROR(IF(INDEX('Player Pool'!$D$2:$D$8725,MATCH($AN5,'Player Pool'!$Z$2:$Z$8725,0))="","",INDEX('Player Pool'!$D$2:$D$8725,MATCH($AN5,'Player Pool'!$Z$2:$Z$8725,0))),"") | AP5: =IFERROR(IF(INDEX('Player Pool'!$E$2:$E$8725,MATCH($AN5,'Player Pool'!$Z$2:$Z$8725,0))="","",INDEX('Player Pool'!$E$2:$E$8725,MATCH($AN5,'Player Pool'!$Z$2:$Z$8725,0))),"") | AQ5: =IFERROR(IF($AN5="","",IF(ISNUMBER(IFERROR(INDEX(Rosters!$I$2:$I$516,MATCH(INDEX('Player Pool'!$V$2:$V$8725,MATCH($AN5,'Player Pool'!$Z$2:$Z$8725,0)),Rosters!$W$2:$W$516,0)),"")),IFERROR(INDEX(Rosters!$I$2:$I$516,MATCH(INDEX('Player Pool'!$V$2:$V$8725,MATCH($AN5,'Player Pool'!$Z$2:$Z$8725,0)),Rosters!$W$2:$W$516,0)),""),INDEX('Player Pool'!$H$2:$H$8725,MATCH($AN5,'Player Pool'!$Z$2:$Z$8725,0)))),"") | AR5: =IFERROR(IF(INDEX('Player Pool'!$I$2:$I$8725,MATCH($AN5,'Player Pool'!$Z$2:$Z$8725,0))="","",INDEX('Player Pool'!$I$2:$I$8725,MATCH($AN5,'Player Pool'!$Z$2:$Z$8725,0))),"") | AS5: =IFERROR(IF(INDEX('Player Pool'!$P$2:$P$8725,MATCH($AN5,'Player Pool'!$Z$2:$Z$8725,0))="","",INDEX('Player Pool'!$P$2:$P$8725,MATCH($AN5,'Player Pool'!$Z$2:$Z$8725,0))),"") | AT5: =IFERROR(IF(INDEX('Player Pool'!$R$2:$R$8725,MATCH($AN5,'Player Pool'!$Z$2:$Z$8725,0))="","",INDEX('Player Pool'!$R$2:$R$8725,MATCH($AN5,'Player Pool'!$Z$2:$Z$8725,0))),"") | AU5: =IFERROR(IF(INDEX('Player Pool'!$U$2:$U$8725,MATCH($AN5,'Player Pool'!$Z$2:$Z$8725,0))="","",INDEX('Player Pool'!$U$2:$U$8725,MATCH($AN5,'Player Pool'!$Z$2:$Z$8725,0))),"") | AV5: =IFERROR(IF($AN5="","",IF(INDEX('Player Pool'!$G$2:$G$8725,MATCH($AN5,'Player Pool'!$Z$2:$Z$8725,0))="FA","FA",IF(INDEX('Player Pool'!$G$2:$G$8725,MATCH($AN5,'Player Pool'!$Z$2:$Z$8725,0))='League Settings'!$B$2,"MINE","TAKEN"))),"")
A6: =IFERROR(IF(INDEX(Rosters!$B$2:$B$516,$S6)="","",INDEX(Rosters!$B$2:$B$516,$S6)),"") | B6: =IFERROR(IF(INDEX(Rosters!$C$2:$C$516,$S6)="","",INDEX(Rosters!$C$2:$C$516,$S6)),"") | C6: =IFERROR(IF(INDEX(Rosters!$D$2:$D$516,$S6)="","",INDEX(Rosters!$D$2:$D$516,$S6)),"") | D6: =IFERROR(IF(INDEX(Rosters!$E$2:$E$516,$S6)="","",INDEX(Rosters!$E$2:$E$516,$S6)),"") | E6: =IFERROR(IF(INDEX(Rosters!$F$2:$F$516,$S6)="","",INDEX(Rosters!$F$2:$F$516,$S6)),"") | F6: =IFERROR(IF(INDEX(Rosters!$G$2:$G$516,$S6)="","",INDEX(Rosters!$G$2:$G$516,$S6)),"") | G6: =IFERROR(IF(INDEX(Rosters!$H$2:$H$516,$S6)="","",INDEX(Rosters!$H$2:$H$516,$S6)),"") | H6: =IFERROR(IF(INDEX(Rosters!$I$2:$I$516,$S6)="","",INDEX(Rosters!$I$2:$I$516,$S6)),"") | I6: =IFERROR(IF(INDEX(Rosters!$J$2:$J$516,$S6)="","",INDEX(Rosters!$J$2:$J$516,$S6)),"") | J6: =IFERROR(IF(INDEX(Rosters!$S$2:$S$516,$S6)="","",INDEX(Rosters!$S$2:$S$516,$S6)),"") | K6: =IFERROR(IF(INDEX(Rosters!$K$2:$K$516,$S6)="","",INDEX(Rosters!$K$2:$K$516,$S6)),"") | L6: =IFERROR(IF(INDEX(Rosters!$T$2:$T$516,$S6)="","",INDEX(Rosters!$T$2:$T$516,$S6)),"") | M6: =IFERROR(IF(INDEX(Rosters!$L$2:$L$516,$S6)="","",INDEX(Rosters!$L$2:$L$516,$S6)),"") | N6: =IFERROR(IF(INDEX(Rosters!$Q$2:$Q$516,$S6)="","",INDEX(Rosters!$Q$2:$Q$516,$S6)),"") | O6: =IFERROR(IF(INDEX(Rosters!$R$2:$R$516,$S6)="","",INDEX(Rosters!$R$2:$R$516,$S6)),"") | P6: =IFERROR(IF(INDEX(Rosters!$N$2:$N$516,$S6)="","",INDEX(Rosters!$N$2:$N$516,$S6)),"") | Q6: =IFERROR(IF(INDEX(Rosters!$O$2:$O$516,$S6)="","",INDEX(Rosters!$O$2:$O$516,$S6)),"") | R6: =IFERROR(IF(INDEX(Rosters!$P$2:$P$516,$S6)="","",INDEX(Rosters!$P$2:$P$516,$S6)),"") | S6: =IFERROR(MATCH('League Settings'!$B$2&"|ACTIVE|"&3,Rosters!$AD$2:$AD$516,0),"") | T6: Tom Wilson (WSH RW) | U6: =IFERROR(IF(INDEX('Player Pool'!$D$2:$D$8725,MATCH($T6,'Player Pool'!$Z$2:$Z$8725,0))="","",INDEX('Player Pool'!$D$2:$D$8725,MATCH($T6,'Player Pool'!$Z$2:$Z$8725,0))),"") | V6: =IFERROR(IF(INDEX('Player Pool'!$E$2:$E$8725,MATCH($T6,'Player Pool'!$Z$2:$Z$8725,0))="","",INDEX('Player Pool'!$E$2:$E$8725,MATCH($T6,'Player Pool'!$Z$2:$Z$8725,0))),"") | W6: =IFERROR(IF($T6="","",IF(ISNUMBER(IFERROR(INDEX(Rosters!$I$2:$I$516,MATCH(INDEX('Player Pool'!$V$2:$V$8725,MATCH($T6,'Player Pool'!$Z$2:$Z$8725,0)),Rosters!$W$2:$W$516,0)),"")),IFERROR(INDEX(Rosters!$I$2:$I$516,MATCH(INDEX('Player Pool'!$V$2:$V$8725,MATCH($T6,'Player Pool'!$Z$2:$Z$8725,0)),Rosters!$W$2:$W$516,0)),""),INDEX('Player Pool'!$H$2:$H$8725,MATCH($T6,'Player Pool'!$Z$2:$Z$8725,0)))),"") | X6: =IFERROR(IF(INDEX('Player Pool'!$I$2:$I$8725,MATCH($T6,'Player Pool'!$Z$2:$Z$8725,0))="","",INDEX('Player Pool'!$I$2:$I$8725,MATCH($T6,'Player Pool'!$Z$2:$Z$8725,0))),"") | Y6: =IFERROR(IF(INDEX('Player Pool'!$P$2:$P$8725,MATCH($T6,'Player Pool'!$Z$2:$Z$8725,0))="","",INDEX('Player Pool'!$P$2:$P$8725,MATCH($T6,'Player Pool'!$Z$2:$Z$8725,0))),"") | Z6: =IFERROR(IF(INDEX('Player Pool'!$R$2:$R$8725,MATCH($T6,'Player Pool'!$Z$2:$Z$8725,0))="","",INDEX('Player Pool'!$R$2:$R$8725,MATCH($T6,'Player Pool'!$Z$2:$Z$8725,0))),"") | AA6: =IFERROR(IF(INDEX('Player Pool'!$U$2:$U$8725,MATCH($T6,'Player Pool'!$Z$2:$Z$8725,0))="","",INDEX('Player Pool'!$U$2:$U$8725,MATCH($T6,'Player Pool'!$Z$2:$Z$8725,0))),"") | AB6: =IFERROR(IF($T6="","",IF(INDEX('Player Pool'!$G$2:$G$8725,MATCH($T6,'Player Pool'!$Z$2:$Z$8725,0))="FA","FA",IF(INDEX('Player Pool'!$G$2:$G$8725,MATCH($T6,'Player Pool'!$Z$2:$Z$8725,0))='League Settings'!$B$2,"MINE","TAKEN"))),"") | AD6: Tom Wilson (WSH RW) | AE6: =IFERROR(IF(INDEX('Player Pool'!$D$2:$D$8725,MATCH($AD6,'Player Pool'!$Z$2:$Z$8725,0))="","",INDEX('Player Pool'!$D$2:$D$8725,MATCH($AD6,'Player Pool'!$Z$2:$Z$8725,0))),"") | AF6: =IFERROR(IF(INDEX('Player Pool'!$E$2:$E$8725,MATCH($AD6,'Player Pool'!$Z$2:$Z$8725,0))="","",INDEX('Player Pool'!$E$2:$E$8725,MATCH($AD6,'Player Pool'!$Z$2:$Z$8725,0))),"") | AG6: =IFERROR(IF($AD6="","",IF(ISNUMBER(IFERROR(INDEX(Rosters!$I$2:$I$516,MATCH(INDEX('Player Pool'!$V$2:$V$8725,MATCH($AD6,'Player Pool'!$Z$2:$Z$8725,0)),Rosters!$W$2:$W$516,0)),"")),IFERROR(INDEX(Rosters!$I$2:$I$516,MATCH(INDEX('Player Pool'!$V$2:$V$8725,MATCH($AD6,'Player Pool'!$Z$2:$Z$8725,0)),Rosters!$W$2:$W$516,0)),""),INDEX('Player Pool'!$H$2:$H$8725,MATCH($AD6,'Player Pool'!$Z$2:$Z$8725,0)))),"") | AH6: =IFERROR(IF(INDEX('Player Pool'!$I$2:$I$8725,MATCH($AD6,'Player Pool'!$Z$2:$Z$8725,0))="","",INDEX('Player Pool'!$I$2:$I$8725,MATCH($AD6,'Player Pool'!$Z$2:$Z$8725,0))),"") | AI6: =IFERROR(IF(INDEX('Player Pool'!$P$2:$P$8725,MATCH($AD6,'Player Pool'!$Z$2:$Z$8725,0))="","",INDEX('Player Pool'!$P$2:$P$8725,MATCH($AD6,'Player Pool'!$Z$2:$Z$8725,0))),"") | AJ6: =IFERROR(IF(INDEX('Player Pool'!$R$2:$R$8725,MATCH($AD6,'Player Pool'!$Z$2:$Z$8725,0))="","",INDEX('Player Pool'!$R$2:$R$8725,MATCH($AD6,'Player Pool'!$Z$2:$Z$8725,0))),"") | AK6: =IFERROR(IF(INDEX('Player Pool'!$U$2:$U$8725,MATCH($AD6,'Player Pool'!$Z$2:$Z$8725,0))="","",INDEX('Player Pool'!$U$2:$U$8725,MATCH($AD6,'Player Pool'!$Z$2:$Z$8725,0))),"") | AL6: =IFERROR(IF($AD6="","",IF(INDEX('Player Pool'!$G$2:$G$8725,MATCH($AD6,'Player Pool'!$Z$2:$Z$8725,0))="FA","FA",IF(INDEX('Player Pool'!$G$2:$G$8725,MATCH($AD6,'Player Pool'!$Z$2:$Z$8725,0))='League Settings'!$B$2,"MINE","TAKEN"))),"") | AN6: Tom Wilson (WSH RW) | AO6: =IFERROR(IF(INDEX('Player Pool'!$D$2:$D$8725,MATCH($AN6,'Player Pool'!$Z$2:$Z$8725,0))="","",INDEX('Player Pool'!$D$2:$D$8725,MATCH($AN6,'Player Pool'!$Z$2:$Z$8725,0))),"") | AP6: =IFERROR(IF(INDEX('Player Pool'!$E$2:$E$8725,MATCH($AN6,'Player Pool'!$Z$2:$Z$8725,0))="","",INDEX('Player Pool'!$E$2:$E$8725,MATCH($AN6,'Player Pool'!$Z$2:$Z$8725,0))),"") | AQ6: =IFERROR(IF($AN6="","",IF(ISNUMBER(IFERROR(INDEX(Rosters!$I$2:$I$516,MATCH(INDEX('Player Pool'!$V$2:$V$8725,MATCH($AN6,'Player Pool'!$Z$2:$Z$8725,0)),Rosters!$W$2:$W$516,0)),"")),IFERROR(INDEX(Rosters!$I$2:$I$516,MATCH(INDEX('Player Pool'!$V$2:$V$8725,MATCH($AN6,'Player Pool'!$Z$2:$Z$8725,0)),Rosters!$W$2:$W$516,0)),""),INDEX('Player Pool'!$H$2:$H$8725,MATCH($AN6,'Player Pool'!$Z$2:$Z$8725,0)))),"") | AR6: =IFERROR(IF(INDEX('Player Pool'!$I$2:$I$8725,MATCH($AN6,'Player Pool'!$Z$2:$Z$8725,0))="","",INDEX('Player Pool'!$I$2:$I$8725,MATCH($AN6,'Player Pool'!$Z$2:$Z$8725,0))),"") | AS6: =IFERROR(IF(INDEX('Player Pool'!$P$2:$P$8725,MATCH($AN6,'Player Pool'!$Z$2:$Z$8725,0))="","",INDEX('Player Pool'!$P$2:$P$8725,MATCH($AN6,'Player Pool'!$Z$2:$Z$8725,0))),"") | AT6: =IFERROR(IF(INDEX('Player Pool'!$R$2:$R$8725,MATCH($AN6,'Player Pool'!$Z$2:$Z$8725,0))="","",INDEX('Player Pool'!$R$2:$R$8725,MATCH($AN6,'Player Pool'!$Z$2:$Z$8725,0))),"") | AU6: =IFERROR(IF(INDEX('Player Pool'!$U$2:$U$8725,MATCH($AN6,'Player Pool'!$Z$2:$Z$8725,0))="","",INDEX('Player Pool'!$U$2:$U$8725,MATCH($AN6,'Player Pool'!$Z$2:$Z$8725,0))),"") | AV6: =IFERROR(IF($AN6="","",IF(INDEX('Player Pool'!$G$2:$G$8725,MATCH($AN6,'Player Pool'!$Z$2:$Z$8725,0))="FA","FA",IF(INDEX('Player Pool'!$G$2:$G$8725,MATCH($AN6,'Player Pool'!$Z$2:$Z$8725,0))='League Settings'!$B$2,"MINE","TAKEN"))),"")
A7: =IFERROR(IF(INDEX(Rosters!$B$2:$B$516,$S7)="","",INDEX(Rosters!$B$2:$B$516,$S7)),"") | B7: =IFERROR(IF(INDEX(Rosters!$C$2:$C$516,$S7)="","",INDEX(Rosters!$C$2:$C$516,$S7)),"") | C7: =IFERROR(IF(INDEX(Rosters!$D$2:$D$516,$S7)="","",INDEX(Rosters!$D$2:$D$516,$S7)),"") | D7: =IFERROR(IF(INDEX(Rosters!$E$2:$E$516,$S7)="","",INDEX(Rosters!$E$2:$E$516,$S7)),"") | E7: =IFERROR(IF(INDEX(Rosters!$F$2:$F$516,$S7)="","",INDEX(Rosters!$F$2:$F$516,$S7)),"") | F7: =IFERROR(IF(INDEX(Rosters!$G$2:$G$516,$S7)="","",INDEX(Rosters!$G$2:$G$516,$S7)),"") | G7: =IFERROR(IF(INDEX(Rosters!$H$2:$H$516,$S7)="","",INDEX(Rosters!$H$2:$H$516,$S7)),"") | H7: =IFERROR(IF(INDEX(Rosters!$I$2:$I$516,$S7)="","",INDEX(Rosters!$I$2:$I$516,$S7)),"") | I7: =IFERROR(IF(INDEX(Rosters!$J$2:$J$516,$S7)="","",INDEX(Rosters!$J$2:$J$516,$S7)),"") | J7: =IFERROR(IF(INDEX(Rosters!$S$2:$S$516,$S7)="","",INDEX(Rosters!$S$2:$S$516,$S7)),"") | K7: =IFERROR(IF(INDEX(Rosters!$K$2:$K$516,$S7)="","",INDEX(Rosters!$K$2:$K$516,$S7)),"") | L7: =IFERROR(IF(INDEX(Rosters!$T$2:$T$516,$S7)="","",INDEX(Rosters!$T$2:$T$516,$S7)),"") | M7: =IFERROR(IF(INDEX(Rosters!$L$2:$L$516,$S7)="","",INDEX(Rosters!$L$2:$L$516,$S7)),"") | N7: =IFERROR(IF(INDEX(Rosters!$Q$2:$Q$516,$S7)="","",INDEX(Rosters!$Q$2:$Q$516,$S7)),"") | O7: =IFERROR(IF(INDEX(Rosters!$R$2:$R$516,$S7)="","",INDEX(Rosters!$R$2:$R$516,$S7)),"") | P7: =IFERROR(IF(INDEX(Rosters!$N$2:$N$516,$S7)="","",INDEX(Rosters!$N$2:$N$516,$S7)),"") | Q7: =IFERROR(IF(INDEX(Rosters!$O$2:$O$516,$S7)="","",INDEX(Rosters!$O$2:$O$516,$S7)),"") | R7: =IFERROR(IF(INDEX(Rosters!$P$2:$P$516,$S7)="","",INDEX(Rosters!$P$2:$P$516,$S7)),"") | S7: =IFERROR(MATCH('League Settings'!$B$2&"|ACTIVE|"&4,Rosters!$AD$2:$AD$516,0),"") | T7: Karel Vejmelka (UTA G) | U7: =IFERROR(IF(INDEX('Player Pool'!$D$2:$D$8725,MATCH($T7,'Player Pool'!$Z$2:$Z$8725,0))="","",INDEX('Player Pool'!$D$2:$D$8725,MATCH($T7,'Player Pool'!$Z$2:$Z$8725,0))),"") | V7: =IFERROR(IF(INDEX('Player Pool'!$E$2:$E$8725,MATCH($T7,'Player Pool'!$Z$2:$Z$8725,0))="","",INDEX('Player Pool'!$E$2:$E$8725,MATCH($T7,'Player Pool'!$Z$2:$Z$8725,0))),"") | W7: =IFERROR(IF($T7="","",IF(ISNUMBER(IFERROR(INDEX(Rosters!$I$2:$I$516,MATCH(INDEX('Player Pool'!$V$2:$V$8725,MATCH($T7,'Player Pool'!$Z$2:$Z$8725,0)),Rosters!$W$2:$W$516,0)),"")),IFERROR(INDEX(Rosters!$I$2:$I$516,MATCH(INDEX('Player Pool'!$V$2:$V$8725,MATCH($T7,'Player Pool'!$Z$2:$Z$8725,0)),Rosters!$W$2:$W$516,0)),""),INDEX('Player Pool'!$H$2:$H$8725,MATCH($T7,'Player Pool'!$Z$2:$Z$8725,0)))),"") | X7: =IFERROR(IF(INDEX('Player Pool'!$I$2:$I$8725,MATCH($T7,'Player Pool'!$Z$2:$Z$8725,0))="","",INDEX('Player Pool'!$I$2:$I$8725,MATCH($T7,'Player Pool'!$Z$2:$Z$8725,0))),"") | Y7: =IFERROR(IF(INDEX('Player Pool'!$P$2:$P$8725,MATCH($T7,'Player Pool'!$Z$2:$Z$8725,0))="","",INDEX('Player Pool'!$P$2:$P$8725,MATCH($T7,'Player Pool'!$Z$2:$Z$8725,0))),"") | Z7: =IFERROR(IF(INDEX('Player Pool'!$R$2:$R$8725,MATCH($T7,'Player Pool'!$Z$2:$Z$8725,0))="","",INDEX('Player Pool'!$R$2:$R$8725,MATCH($T7,'Player Pool'!$Z$2:$Z$8725,0))),"") | AA7: =IFERROR(IF(INDEX('Player Pool'!$U$2:$U$8725,MATCH($T7,'Player Pool'!$Z$2:$Z$8725,0))="","",INDEX('Player Pool'!$U$2:$U$8725,MATCH($T7,'Player Pool'!$Z$2:$Z$8725,0))),"") | AB7: =IFERROR(IF($T7="","",IF(INDEX('Player Pool'!$G$2:$G$8725,MATCH($T7,'Player Pool'!$Z$2:$Z$8725,0))="FA","FA",IF(INDEX('Player Pool'!$G$2:$G$8725,MATCH($T7,'Player Pool'!$Z$2:$Z$8725,0))='League Settings'!$B$2,"MINE","TAKEN"))),"") | AD7: Karel Vejmelka (UTA G) | AE7: =IFERROR(IF(INDEX('Player Pool'!$D$2:$D$8725,MATCH($AD7,'Player Pool'!$Z$2:$Z$8725,0))="","",INDEX('Player Pool'!$D$2:$D$8725,MATCH($AD7,'Player Pool'!$Z$2:$Z$8725,0))),"") | AF7: =IFERROR(IF(INDEX('Player Pool'!$E$2:$E$8725,MATCH($AD7,'Player Pool'!$Z$2:$Z$8725,0))="","",INDEX('Player Pool'!$E$2:$E$8725,MATCH($AD7,'Player Pool'!$Z$2:$Z$8725,0))),"") | AG7: =IFERROR(IF($AD7="","",IF(ISNUMBER(IFERROR(INDEX(Rosters!$I$2:$I$516,MATCH(INDEX('Player Pool'!$V$2:$V$8725,MATCH($AD7,'Player Pool'!$Z$2:$Z$8725,0)),Rosters!$W$2:$W$516,0)),"")),IFERROR(INDEX(Rosters!$I$2:$I$516,MATCH(INDEX('Player Pool'!$V$2:$V$8725,MATCH($AD7,'Player Pool'!$Z$2:$Z$8725,0)),Rosters!$W$2:$W$516,0)),""),INDEX('Player Pool'!$H$2:$H$8725,MATCH($AD7,'Player Pool'!$Z$2:$Z$8725,0)))),"") | AH7: =IFERROR(IF(INDEX('Player Pool'!$I$2:$I$8725,MATCH($AD7,'Player Pool'!$Z$2:$Z$8725,0))="","",INDEX('Player Pool'!$I$2:$I$8725,MATCH($AD7,'Player Pool'!$Z$2:$Z$8725,0))),"") | AI7: =IFERROR(IF(INDEX('Player Pool'!$P$2:$P$8725,MATCH($AD7,'Player Pool'!$Z$2:$Z$8725,0))="","",INDEX('Player Pool'!$P$2:$P$8725,MATCH($AD7,'Player Pool'!$Z$2:$Z$8725,0))),"") | AJ7: =IFERROR(IF(INDEX('Player Pool'!$R$2:$R$8725,MATCH($AD7,'Player Pool'!$Z$2:$Z$8725,0))="","",INDEX('Player Pool'!$R$2:$R$8725,MATCH($AD7,'Player Pool'!$Z$2:$Z$8725,0))),"") | AK7: =IFERROR(IF(INDEX('Player Pool'!$U$2:$U$8725,MATCH($AD7,'Player Pool'!$Z$2:$Z$8725,0))="","",INDEX('Player Pool'!$U$2:$U$8725,MATCH($AD7,'Player Pool'!$Z$2:$Z$8725,0))),"") | AL7: =IFERROR(IF($AD7="","",IF(INDEX('Player Pool'!$G$2:$G$8725,MATCH($AD7,'Player Pool'!$Z$2:$Z$8725,0))="FA","FA",IF(INDEX('Player Pool'!$G$2:$G$8725,MATCH($AD7,'Player Pool'!$Z$2:$Z$8725,0))='League Settings'!$B$2,"MINE","TAKEN"))),"") | AN7: Karel Vejmelka (UTA G) | AO7: =IFERROR(IF(INDEX('Player Pool'!$D$2:$D$8725,MATCH($AN7,'Player Pool'!$Z$2:$Z$8725,0))="","",INDEX('Player Pool'!$D$2:$D$8725,MATCH($AN7,'Player Pool'!$Z$2:$Z$8725,0))),"") | AP7: =IFERROR(IF(INDEX('Player Pool'!$E$2:$E$8725,MATCH($AN7,'Player Pool'!$Z$2:$Z$8725,0))="","",INDEX('Player Pool'!$E$2:$E$8725,MATCH($AN7,'Player Pool'!$Z$2:$Z$8725,0))),"") | AQ7: =IFERROR(IF($AN7="","",IF(ISNUMBER(IFERROR(INDEX(Rosters!$I$2:$I$516,MATCH(INDEX('Player Pool'!$V$2:$V$8725,MATCH($AN7,'Player Pool'!$Z$2:$Z$8725,0)),Rosters!$W$2:$W$516,0)),"")),IFERROR(INDEX(Rosters!$I$2:$I$516,MATCH(INDEX('Player Pool'!$V$2:$V$8725,MATCH($AN7,'Player Pool'!$Z$2:$Z$8725,0)),Rosters!$W$2:$W$516,0)),""),INDEX('Player Pool'!$H$2:$H$8725,MATCH($AN7,'Player Pool'!$Z$2:$Z$8725,0)))),"") | AR7: =IFERROR(IF(INDEX('Player Pool'!$I$2:$I$8725,MATCH($AN7,'Player Pool'!$Z$2:$Z$8725,0))="","",INDEX('Player Pool'!$I$2:$I$8725,MATCH($AN7,'Player Pool'!$Z$2:$Z$8725,0))),"") | AS7: =IFERROR(IF(INDEX('Player Pool'!$P$2:$P$8725,MATCH($AN7,'Player Pool'!$Z$2:$Z$8725,0))="","",INDEX('Player Pool'!$P$2:$P$8725,MATCH($AN7,'Player Pool'!$Z$2:$Z$8725,0))),"") | AT7: =IFERROR(IF(INDEX('Player Pool'!$R$2:$R$8725,MATCH($AN7,'Player Pool'!$Z$2:$Z$8725,0))="","",INDEX('Player Pool'!$R$2:$R$8725,MATCH($AN7,'Player Pool'!$Z$2:$Z$8725,0))),"") | AU7: =IFERROR(IF(INDEX('Player Pool'!$U$2:$U$8725,MATCH($AN7,'Player Pool'!$Z$2:$Z$8725,0))="","",INDEX('Player Pool'!$U$2:$U$8725,MATCH($AN7,'Player Pool'!$Z$2:$Z$8725,0))),"") | AV7: =IFERROR(IF($AN7="","",IF(INDEX('Player Pool'!$G$2:$G$8725,MATCH($AN7,'Player Pool'!$Z$2:$Z$8725,0))="FA","FA",IF(INDEX('Player Pool'!$G$2:$G$8725,MATCH($AN7,'Player Pool'!$Z$2:$Z$8725,0))='League Settings'!$B$2,"MINE","TAKEN"))),"")
A8: =IFERROR(IF(INDEX(Rosters!$B$2:$B$516,$S8)="","",INDEX(Rosters!$B$2:$B$516,$S8)),"") | B8: =IFERROR(IF(INDEX(Rosters!$C$2:$C$516,$S8)="","",INDEX(Rosters!$C$2:$C$516,$S8)),"") | C8: =IFERROR(IF(INDEX(Rosters!$D$2:$D$516,$S8)="","",INDEX(Rosters!$D$2:$D$516,$S8)),"") | D8: =IFERROR(IF(INDEX(Rosters!$E$2:$E$516,$S8)="","",INDEX(Rosters!$E$2:$E$516,$S8)),"") | E8: =IFERROR(IF(INDEX(Rosters!$F$2:$F$516,$S8)="","",INDEX(Rosters!$F$2:$F$516,$S8)),"") | F8: =IFERROR(IF(INDEX(Rosters!$G$2:$G$516,$S8)="","",INDEX(Rosters!$G$2:$G$516,$S8)),"") | G8: =IFERROR(IF(INDEX(Rosters!$H$2:$H$516,$S8)="","",INDEX(Rosters!$H$2:$H$516,$S8)),"") | H8: =IFERROR(IF(INDEX(Rosters!$I$2:$I$516,$S8)="","",INDEX(Rosters!$I$2:$I$516,$S8)),"") | I8: =IFERROR(IF(INDEX(Rosters!$J$2:$J$516,$S8)="","",INDEX(Rosters!$J$2:$J$516,$S8)),"") | J8: =IFERROR(IF(INDEX(Rosters!$S$2:$S$516,$S8)="","",INDEX(Rosters!$S$2:$S$516,$S8)),"") | K8: =IFERROR(IF(INDEX(Rosters!$K$2:$K$516,$S8)="","",INDEX(Rosters!$K$2:$K$516,$S8)),"") | L8: =IFERROR(IF(INDEX(Rosters!$T$2:$T$516,$S8)="","",INDEX(Rosters!$T$2:$T$516,$S8)),"") | M8: =IFERROR(IF(INDEX(Rosters!$L$2:$L$516,$S8)="","",INDEX(Rosters!$L$2:$L$516,$S8)),"") | N8: =IFERROR(IF(INDEX(Rosters!$Q$2:$Q$516,$S8)="","",INDEX(Rosters!$Q$2:$Q$516,$S8)),"") | O8: =IFERROR(IF(INDEX(Rosters!$R$2:$R$516,$S8)="","",INDEX(Rosters!$R$2:$R$516,$S8)),"") | P8: =IFERROR(IF(INDEX(Rosters!$N$2:$N$516,$S8)="","",INDEX(Rosters!$N$2:$N$516,$S8)),"") | Q8: =IFERROR(IF(INDEX(Rosters!$O$2:$O$516,$S8)="","",INDEX(Rosters!$O$2:$O$516,$S8)),"") | R8: =IFERROR(IF(INDEX(Rosters!$P$2:$P$516,$S8)="","",INDEX(Rosters!$P$2:$P$516,$S8)),"") | S8: =IFERROR(MATCH('League Settings'!$B$2&"|ACTIVE|"&5,Rosters!$AD$2:$AD$516,0),"") | T8: Sebastian Aho (CAR C) | U8: =IFERROR(IF(INDEX('Player Pool'!$D$2:$D$8725,MATCH($T8,'Player Pool'!$Z$2:$Z$8725,0))="","",INDEX('Player Pool'!$D$2:$D$8725,MATCH($T8,'Player Pool'!$Z$2:$Z$8725,0))),"") | V8: =IFERROR(IF(INDEX('Player Pool'!$E$2:$E$8725,MATCH($T8,'Player Pool'!$Z$2:$Z$8725,0))="","",INDEX('Player Pool'!$E$2:$E$8725,MATCH($T8,'Player Pool'!$Z$2:$Z$8725,0))),"") | W8: =IFERROR(IF($T8="","",IF(ISNUMBER(IFERROR(INDEX(Rosters!$I$2:$I$516,MATCH(INDEX('Player Pool'!$V$2:$V$8725,MATCH($T8,'Player Pool'!$Z$2:$Z$8725,0)),Rosters!$W$2:$W$516,0)),"")),IFERROR(INDEX(Rosters!$I$2:$I$516,MATCH(INDEX('Player Pool'!$V$2:$V$8725,MATCH($T8,'Player Pool'!$Z$2:$Z$8725,0)),Rosters!$W$2:$W$516,0)),""),INDEX('Player Pool'!$H$2:$H$8725,MATCH($T8,'Player Pool'!$Z$2:$Z$8725,0)))),"") | X8: =IFERROR(IF(INDEX('Player Pool'!$I$2:$I$8725,MATCH($T8,'Player Pool'!$Z$2:$Z$8725,0))="","",INDEX('Player Pool'!$I$2:$I$8725,MATCH($T8,'Player Pool'!$Z$2:$Z$8725,0))),"") | Y8: =IFERROR(IF(INDEX('Player Pool'!$P$2:$P$8725,MATCH($T8,'Player Pool'!$Z$2:$Z$8725,0))="","",INDEX('Player Pool'!$P$2:$P$8725,MATCH($T8,'Player Pool'!$Z$2:$Z$8725,0))),"") | Z8: =IFERROR(IF(INDEX('Player Pool'!$R$2:$R$8725,MATCH($T8,'Player Pool'!$Z$2:$Z$8725,0))="","",INDEX('Player Pool'!$R$2:$R$8725,MATCH($T8,'Player Pool'!$Z$2:$Z$8725,0))),"") | AA8: =IFERROR(IF(INDEX('Player Pool'!$U$2:$U$8725,MATCH($T8,'Player Pool'!$Z$2:$Z$8725,0))="","",INDEX('Player Pool'!$U$2:$U$8725,MATCH($T8,'Player Pool'!$Z$2:$Z$8725,0))),"") | AB8: =IFERROR(IF($T8="","",IF(INDEX('Player Pool'!$G$2:$G$8725,MATCH($T8,'Player Pool'!$Z$2:$Z$8725,0))="FA","FA",IF(INDEX('Player Pool'!$G$2:$G$8725,MATCH($T8,'Player Pool'!$Z$2:$Z$8725,0))='League Settings'!$B$2,"MINE","TAKEN"))),"") | AD8: Sebastian Aho (CAR C) | AE8: =IFERROR(IF(INDEX('Player Pool'!$D$2:$D$8725,MATCH($AD8,'Player Pool'!$Z$2:$Z$8725,0))="","",INDEX('Player Pool'!$D$2:$D$8725,MATCH($AD8,'Player Pool'!$Z$2:$Z$8725,0))),"") | AF8: =IFERROR(IF(INDEX('Player Pool'!$E$2:$E$8725,MATCH($AD8,'Player Pool'!$Z$2:$Z$8725,0))="","",INDEX('Player Pool'!$E$2:$E$8725,MATCH($AD8,'Player Pool'!$Z$2:$Z$8725,0))),"") | AG8: =IFERROR(IF($AD8="","",IF(ISNUMBER(IFERROR(INDEX(Rosters!$I$2:$I$516,MATCH(INDEX('Player Pool'!$V$2:$V$8725,MATCH($AD8,'Player Pool'!$Z$2:$Z$8725,0)),Rosters!$W$2:$W$516,0)),"")),IFERROR(INDEX(Rosters!$I$2:$I$516,MATCH(INDEX('Player Pool'!$V$2:$V$8725,MATCH($AD8,'Player Pool'!$Z$2:$Z$8725,0)),Rosters!$W$2:$W$516,0)),""),INDEX('Player Pool'!$H$2:$H$8725,MATCH($AD8,'Player Pool'!$Z$2:$Z$8725,0)))),"") | AH8: =IFERROR(IF(INDEX('Player Pool'!$I$2:$I$8725,MATCH($AD8,'Player Pool'!$Z$2:$Z$8725,0))="","",INDEX('Player Pool'!$I$2:$I$8725,MATCH($AD8,'Player Pool'!$Z$2:$Z$8725,0))),"") | AI8: =IFERROR(IF(INDEX('Player Pool'!$P$2:$P$8725,MATCH($AD8,'Player Pool'!$Z$2:$Z$8725,0))="","",INDEX('Player Pool'!$P$2:$P$8725,MATCH($AD8,'Player Pool'!$Z$2:$Z$8725,0))),"") | AJ8: =IFERROR(IF(INDEX('Player Pool'!$R$2:$R$8725,MATCH($AD8,'Player Pool'!$Z$2:$Z$8725,0))="","",INDEX('Player Pool'!$R$2:$R$8725,MATCH($AD8,'Player Pool'!$Z$2:$Z$8725,0))),"") | AK8: =IFERROR(IF(INDEX('Player Pool'!$U$2:$U$8725,MATCH($AD8,'Player Pool'!$Z$2:$Z$8725,0))="","",INDEX('Player Pool'!$U$2:$U$8725,MATCH($AD8,'Player Pool'!$Z$2:$Z$8725,0))),"") | AL8: =IFERROR(IF($AD8="","",IF(INDEX('Player Pool'!$G$2:$G$8725,MATCH($AD8,'Player Pool'!$Z$2:$Z$8725,0))="FA","FA",IF(INDEX('Player Pool'!$G$2:$G$8725,MATCH($AD8,'Player Pool'!$Z$2:$Z$8725,0))='League Settings'!$B$2,"MINE","TAKEN"))),"") | AN8: Sebastian Aho (CAR C) | AO8: =IFERROR(IF(INDEX('Player Pool'!$D$2:$D$8725,MATCH($AN8,'Player Pool'!$Z$2:$Z$8725,0))="","",INDEX('Player Pool'!$D$2:$D$8725,MATCH($AN8,'Player Pool'!$Z$2:$Z$8725,0))),"") | AP8: =IFERROR(IF(INDEX('Player Pool'!$E$2:$E$8725,MATCH($AN8,'Player Pool'!$Z$2:$Z$8725,0))="","",INDEX('Player Pool'!$E$2:$E$8725,MATCH($AN8,'Player Pool'!$Z$2:$Z$8725,0))),"") | AQ8: =IFERROR(IF($AN8="","",IF(ISNUMBER(IFERROR(INDEX(Rosters!$I$2:$I$516,MATCH(INDEX('Player Pool'!$V$2:$V$8725,MATCH($AN8,'Player Pool'!$Z$2:$Z$8725,0)),Rosters!$W$2:$W$516,0)),"")),IFERROR(INDEX(Rosters!$I$2:$I$516,MATCH(INDEX('Player Pool'!$V$2:$V$8725,MATCH($AN8,'Player Pool'!$Z$2:$Z$8725,0)),Rosters!$W$2:$W$516,0)),""),INDEX('Player Pool'!$H$2:$H$8725,MATCH($AN8,'Player Pool'!$Z$2:$Z$8725,0)))),"") | AR8: =IFERROR(IF(INDEX('Player Pool'!$I$2:$I$8725,MATCH($AN8,'Player Pool'!$Z$2:$Z$8725,0))="","",INDEX('Player Pool'!$I$2:$I$8725,MATCH($AN8,'Player Pool'!$Z$2:$Z$8725,0))),"") | AS8: =IFERROR(IF(INDEX('Player Pool'!$P$2:$P$8725,MATCH($AN8,'Player Pool'!$Z$2:$Z$8725,0))="","",INDEX('Player Pool'!$P$2:$P$8725,MATCH($AN8,'Player Pool'!$Z$2:$Z$8725,0))),"") | AT8: =IFERROR(IF(INDEX('Player Pool'!$R$2:$R$8725,MATCH($AN8,'Player Pool'!$Z$2:$Z$8725,0))="","",INDEX('Player Pool'!$R$2:$R$8725,MATCH($AN8,'Player Pool'!$Z$2:$Z$8725,0))),"") | AU8: =IFERROR(IF(INDEX('Player Pool'!$U$2:$U$8725,MATCH($AN8,'Player Pool'!$Z$2:$Z$8725,0))="","",INDEX('Player Pool'!$U$2:$U$8725,MATCH($AN8,'Player Pool'!$Z$2:$Z$8725,0))),"") | AV8: =IFERROR(IF($AN8="","",IF(INDEX('Player Pool'!$G$2:$G$8725,MATCH($AN8,'Player Pool'!$Z$2:$Z$8725,0))="FA","FA",IF(INDEX('Player Pool'!$G$2:$G$8725,MATCH($AN8,'Player Pool'!$Z$2:$Z$8725,0))='League Settings'!$B$2,"MINE","TAKEN"))),"")
A9: =IFERROR(IF(INDEX(Rosters!$B$2:$B$516,$S9)="","",INDEX(Rosters!$B$2:$B$516,$S9)),"") | B9: =IFERROR(IF(INDEX(Rosters!$C$2:$C$516,$S9)="","",INDEX(Rosters!$C$2:$C$516,$S9)),"") | C9: =IFERROR(IF(INDEX(Rosters!$D$2:$D$516,$S9)="","",INDEX(Rosters!$D$2:$D$516,$S9)),"") | D9: =IFERROR(IF(INDEX(Rosters!$E$2:$E$516,$S9)="","",INDEX(Rosters!$E$2:$E$516,$S9)),"") | E9: =IFERROR(IF(INDEX(Rosters!$F$2:$F$516,$S9)="","",INDEX(Rosters!$F$2:$F$516,$S9)),"") | F9: =IFERROR(IF(INDEX(Rosters!$G$2:$G$516,$S9)="","",INDEX(Rosters!$G$2:$G$516,$S9)),"") | G9: =IFERROR(IF(INDEX(Rosters!$H$2:$H$516,$S9)="","",INDEX(Rosters!$H$2:$H$516,$S9)),"") | H9: =IFERROR(IF(INDEX(Rosters!$I$2:$I$516,$S9)="","",INDEX(Rosters!$I$2:$I$516,$S9)),"") | I9: =IFERROR(IF(INDEX(Rosters!$J$2:$J$516,$S9)="","",INDEX(Rosters!$J$2:$J$516,$S9)),"") | J9: =IFERROR(IF(INDEX(Rosters!$S$2:$S$516,$S9)="","",INDEX(Rosters!$S$2:$S$516,$S9)),"") | K9: =IFERROR(IF(INDEX(Rosters!$K$2:$K$516,$S9)="","",INDEX(Rosters!$K$2:$K$516,$S9)),"") | L9: =IFERROR(IF(INDEX(Rosters!$T$2:$T$516,$S9)="","",INDEX(Rosters!$T$2:$T$516,$S9)),"") | M9: =IFERROR(IF(INDEX(Rosters!$L$2:$L$516,$S9)="","",INDEX(Rosters!$L$2:$L$516,$S9)),"") | N9: =IFERROR(IF(INDEX(Rosters!$Q$2:$Q$516,$S9)="","",INDEX(Rosters!$Q$2:$Q$516,$S9)),"") | O9: =IFERROR(IF(INDEX(Rosters!$R$2:$R$516,$S9)="","",INDEX(Rosters!$R$2:$R$516,$S9)),"") | P9: =IFERROR(IF(INDEX(Rosters!$N$2:$N$516,$S9)="","",INDEX(Rosters!$N$2:$N$516,$S9)),"") | Q9: =IFERROR(IF(INDEX(Rosters!$O$2:$O$516,$S9)="","",INDEX(Rosters!$O$2:$O$516,$S9)),"") | R9: =IFERROR(IF(INDEX(Rosters!$P$2:$P$516,$S9)="","",INDEX(Rosters!$P$2:$P$516,$S9)),"") | S9: =IFERROR(MATCH('League Settings'!$B$2&"|ACTIVE|"&6,Rosters!$AD$2:$AD$516,0),"") | T9: Josh Morrissey (WPG D) | U9: =IFERROR(IF(INDEX('Player Pool'!$D$2:$D$8725,MATCH($T9,'Player Pool'!$Z$2:$Z$8725,0))="","",INDEX('Player Pool'!$D$2:$D$8725,MATCH($T9,'Player Pool'!$Z$2:$Z$8725,0))),"") | V9: =IFERROR(IF(INDEX('Player Pool'!$E$2:$E$8725,MATCH($T9,'Player Pool'!$Z$2:$Z$8725,0))="","",INDEX('Player Pool'!$E$2:$E$8725,MATCH($T9,'Player Pool'!$Z$2:$Z$8725,0))),"") | W9: =IFERROR(IF($T9="","",IF(ISNUMBER(IFERROR(INDEX(Rosters!$I$2:$I$516,MATCH(INDEX('Player Pool'!$V$2:$V$8725,MATCH($T9,'Player Pool'!$Z$2:$Z$8725,0)),Rosters!$W$2:$W$516,0)),"")),IFERROR(INDEX(Rosters!$I$2:$I$516,MATCH(INDEX('Player Pool'!$V$2:$V$8725,MATCH($T9,'Player Pool'!$Z$2:$Z$8725,0)),Rosters!$W$2:$W$516,0)),""),INDEX('Player Pool'!$H$2:$H$8725,MATCH($T9,'Player Pool'!$Z$2:$Z$8725,0)))),"") | X9: =IFERROR(IF(INDEX('Player Pool'!$I$2:$I$8725,MATCH($T9,'Player Pool'!$Z$2:$Z$8725,0))="","",INDEX('Player Pool'!$I$2:$I$8725,MATCH($T9,'Player Pool'!$Z$2:$Z$8725,0))),"") | Y9: =IFERROR(IF(INDEX('Player Pool'!$P$2:$P$8725,MATCH($T9,'Player Pool'!$Z$2:$Z$8725,0))="","",INDEX('Player Pool'!$P$2:$P$8725,MATCH($T9,'Player Pool'!$Z$2:$Z$8725,0))),"") | Z9: =IFERROR(IF(INDEX('Player Pool'!$R$2:$R$8725,MATCH($T9,'Player Pool'!$Z$2:$Z$8725,0))="","",INDEX('Player Pool'!$R$2:$R$8725,MATCH($T9,'Player Pool'!$Z$2:$Z$8725,0))),"") | AA9: =IFERROR(IF(INDEX('Player Pool'!$U$2:$U$8725,MATCH($T9,'Player Pool'!$Z$2:$Z$8725,0))="","",INDEX('Player Pool'!$U$2:$U$8725,MATCH($T9,'Player Pool'!$Z$2:$Z$8725,0))),"") | AB9: =IFERROR(IF($T9="","",IF(INDEX('Player Pool'!$G$2:$G$8725,MATCH($T9,'Player Pool'!$Z$2:$Z$8725,0))="FA","FA",IF(INDEX('Player Pool'!$G$2:$G$8725,MATCH($T9,'Player Pool'!$Z$2:$Z$8725,0))='League Settings'!$B$2,"MINE","TAKEN"))),"") | AD9: Josh Morrissey (WPG D) | AE9: =IFERROR(IF(INDEX('Player Pool'!$D$2:$D$8725,MATCH($AD9,'Player Pool'!$Z$2:$Z$8725,0))="","",INDEX('Player Pool'!$D$2:$D$8725,MATCH($AD9,'Player Pool'!$Z$2:$Z$8725,0))),"") | AF9: =IFERROR(IF(INDEX('Player Pool'!$E$2:$E$8725,MATCH($AD9,'Player Pool'!$Z$2:$Z$8725,0))="","",INDEX('Player Pool'!$E$2:$E$8725,MATCH($AD9,'Player Pool'!$Z$2:$Z$8725,0))),"") | AG9: =IFERROR(IF($AD9="","",IF(ISNUMBER(IFERROR(INDEX(Rosters!$I$2:$I$516,MATCH(INDEX('Player Pool'!$V$2:$V$8725,MATCH($AD9,'Player Pool'!$Z$2:$Z$8725,0)),Rosters!$W$2:$W$516,0)),"")),IFERROR(INDEX(Rosters!$I$2:$I$516,MATCH(INDEX('Player Pool'!$V$2:$V$8725,MATCH($AD9,'Player Pool'!$Z$2:$Z$8725,0)),Rosters!$W$2:$W$516,0)),""),INDEX('Player Pool'!$H$2:$H$8725,MATCH($AD9,'Player Pool'!$Z$2:$Z$8725,0)))),"") | AH9: =IFERROR(IF(INDEX('Player Pool'!$I$2:$I$8725,MATCH($AD9,'Player Pool'!$Z$2:$Z$8725,0))="","",INDEX('Player Pool'!$I$2:$I$8725,MATCH($AD9,'Player Pool'!$Z$2:$Z$8725,0))),"") | AI9: =IFERROR(IF(INDEX('Player Pool'!$P$2:$P$8725,MATCH($AD9,'Player Pool'!$Z$2:$Z$8725,0))="","",INDEX('Player Pool'!$P$2:$P$8725,MATCH($AD9,'Player Pool'!$Z$2:$Z$8725,0))),"") | AJ9: =IFERROR(IF(INDEX('Player Pool'!$R$2:$R$8725,MATCH($AD9,'Player Pool'!$Z$2:$Z$8725,0))="","",INDEX('Player Pool'!$R$2:$R$8725,MATCH($AD9,'Player Pool'!$Z$2:$Z$8725,0))),"") | AK9: =IFERROR(IF(INDEX('Player Pool'!$U$2:$U$8725,MATCH($AD9,'Player Pool'!$Z$2:$Z$8725,0))="","",INDEX('Player Pool'!$U$2:$U$8725,MATCH($AD9,'Player Pool'!$Z$2:$Z$8725,0))),"") | AL9: =IFERROR(IF($AD9="","",IF(INDEX('Player Pool'!$G$2:$G$8725,MATCH($AD9,'Player Pool'!$Z$2:$Z$8725,0))="FA","FA",IF(INDEX('Player Pool'!$G$2:$G$8725,MATCH($AD9,'Player Pool'!$Z$2:$Z$8725,0))='League Settings'!$B$2,"MINE","TAKEN"))),"") | AN9: Josh Morrissey (WPG D) | AO9: =IFERROR(IF(INDEX('Player Pool'!$D$2:$D$8725,MATCH($AN9,'Player Pool'!$Z$2:$Z$8725,0))="","",INDEX('Player Pool'!$D$2:$D$8725,MATCH($AN9,'Player Pool'!$Z$2:$Z$8725,0))),"") | AP9: =IFERROR(IF(INDEX('Player Pool'!$E$2:$E$8725,MATCH($AN9,'Player Pool'!$Z$2:$Z$8725,0))="","",INDEX('Player Pool'!$E$2:$E$8725,MATCH($AN9,'Player Pool'!$Z$2:$Z$8725,0))),"") | AQ9: =IFERROR(IF($AN9="","",IF(ISNUMBER(IFERROR(INDEX(Rosters!$I$2:$I$516,MATCH(INDEX('Player Pool'!$V$2:$V$8725,MATCH($AN9,'Player Pool'!$Z$2:$Z$8725,0)),Rosters!$W$2:$W$516,0)),"")),IFERROR(INDEX(Rosters!$I$2:$I$516,MATCH(INDEX('Player Pool'!$V$2:$V$8725,MATCH($AN9,'Player Pool'!$Z$2:$Z$8725,0)),Rosters!$W$2:$W$516,0)),""),INDEX('Player Pool'!$H$2:$H$8725,MATCH($AN9,'Player Pool'!$Z$2:$Z$8725,0)))),"") | AR9: =IFERROR(IF(INDEX('Player Pool'!$I$2:$I$8725,MATCH($AN9,'Player Pool'!$Z$2:$Z$8725,0))="","",INDEX('Player Pool'!$I$2:$I$8725,MATCH($AN9,'Player Pool'!$Z$2:$Z$8725,0))),"") | AS9: =IFERROR(IF(INDEX('Player Pool'!$P$2:$P$8725,MATCH($AN9,'Player Pool'!$Z$2:$Z$8725,0))="","",INDEX('Player Pool'!$P$2:$P$8725,MATCH($AN9,'Player Pool'!$Z$2:$Z$8725,0))),"") | AT9: =IFERROR(IF(INDEX('Player Pool'!$R$2:$R$8725,MATCH($AN9,'Player Pool'!$Z$2:$Z$8725,0))="","",INDEX('Player Pool'!$R$2:$R$8725,MATCH($AN9,'Player Pool'!$Z$2:$Z$8725,0))),"") | AU9: =IFERROR(IF(INDEX('Player Pool'!$U$2:$U$8725,MATCH($AN9,'Player Pool'!$Z$2:$Z$8725,0))="","",INDEX('Player Pool'!$U$2:$U$8725,MATCH($AN9,'Player Pool'!$Z$2:$Z$8725,0))),"") | AV9: =IFERROR(IF($AN9="","",IF(INDEX('Player Pool'!$G$2:$G$8725,MATCH($AN9,'Player Pool'!$Z$2:$Z$8725,0))="FA","FA",IF(INDEX('Player Pool'!$G$2:$G$8725,MATCH($AN9,'Player Pool'!$Z$2:$Z$8725,0))='League Settings'!$B$2,"MINE","TAKEN"))),"")
A10: =IFERROR(IF(INDEX(Rosters!$B$2:$B$516,$S10)="","",INDEX(Rosters!$B$2:$B$516,$S10)),"") | B10: =IFERROR(IF(INDEX(Rosters!$C$2:$C$516,$S10)="","",INDEX(Rosters!$C$2:$C$516,$S10)),"") | C10: =IFERROR(IF(INDEX(Rosters!$D$2:$D$516,$S10)="","",INDEX(Rosters!$D$2:$D$516,$S10)),"") | D10: =IFERROR(IF(INDEX(Rosters!$E$2:$E$516,$S10)="","",INDEX(Rosters!$E$2:$E$516,$S10)),"") | E10: =IFERROR(IF(INDEX(Rosters!$F$2:$F$516,$S10)="","",INDEX(Rosters!$F$2:$F$516,$S10)),"") | F10: =IFERROR(IF(INDEX(Rosters!$G$2:$G$516,$S10)="","",INDEX(Rosters!$G$2:$G$516,$S10)),"") | G10: =IFERROR(IF(INDEX(Rosters!$H$2:$H$516,$S10)="","",INDEX(Rosters!$H$2:$H$516,$S10)),"") | H10: =IFERROR(IF(INDEX(Rosters!$I$2:$I$516,$S10)="","",INDEX(Rosters!$I$2:$I$516,$S10)),"") | I10: =IFERROR(IF(INDEX(Rosters!$J$2:$J$516,$S10)="","",INDEX(Rosters!$J$2:$J$516,$S10)),"") | J10: =IFERROR(IF(INDEX(Rosters!$S$2:$S$516,$S10)="","",INDEX(Rosters!$S$2:$S$516,$S10)),"") | K10: =IFERROR(IF(INDEX(Rosters!$K$2:$K$516,$S10)="","",INDEX(Rosters!$K$2:$K$516,$S10)),"") | L10: =IFERROR(IF(INDEX(Rosters!$T$2:$T$516,$S10)="","",INDEX(Rosters!$T$2:$T$516,$S10)),"") | M10: =IFERROR(IF(INDEX(Rosters!$L$2:$L$516,$S10)="","",INDEX(Rosters!$L$2:$L$516,$S10)),"") | N10: =IFERROR(IF(INDEX(Rosters!$Q$2:$Q$516,$S10)="","",INDEX(Rosters!$Q$2:$Q$516,$S10)),"") | O10: =IFERROR(IF(INDEX(Rosters!$R$2:$R$516,$S10)="","",INDEX(Rosters!$R$2:$R$516,$S10)),"") | P10: =IFERROR(IF(INDEX(Rosters!$N$2:$N$516,$S10)="","",INDEX(Rosters!$N$2:$N$516,$S10)),"") | Q10: =IFERROR(IF(INDEX(Rosters!$O$2:$O$516,$S10)="","",INDEX(Rosters!$O$2:$O$516,$S10)),"") | R10: =IFERROR(IF(INDEX(Rosters!$P$2:$P$516,$S10)="","",INDEX(Rosters!$P$2:$P$516,$S10)),"") | S10: =IFERROR(MATCH('League Settings'!$B$2&"|ACTIVE|"&7,Rosters!$AD$2:$AD$516,0),"") | T10: Jackson LaCombe (ANA D) | U10: =IFERROR(IF(INDEX('Player Pool'!$D$2:$D$8725,MATCH($T10,'Player Pool'!$Z$2:$Z$8725,0))="","",INDEX('Player Pool'!$D$2:$D$8725,MATCH($T10,'Player Pool'!$Z$2:$Z$8725,0))),"") | V10: =IFERROR(IF(INDEX('Player Pool'!$E$2:$E$8725,MATCH($T10,'Player Pool'!$Z$2:$Z$8725,0))="","",INDEX('Player Pool'!$E$2:$E$8725,MATCH($T10,'Player Pool'!$Z$2:$Z$8725,0))),"") | W10: =IFERROR(IF($T10="","",IF(ISNUMBER(IFERROR(INDEX(Rosters!$I$2:$I$516,MATCH(INDEX('Player Pool'!$V$2:$V$8725,MATCH($T10,'Player Pool'!$Z$2:$Z$8725,0)),Rosters!$W$2:$W$516,0)),"")),IFERROR(INDEX(Rosters!$I$2:$I$516,MATCH(INDEX('Player Pool'!$V$2:$V$8725,MATCH($T10,'Player Pool'!$Z$2:$Z$8725,0)),Rosters!$W$2:$W$516,0)),""),INDEX('Player Pool'!$H$2:$H$8725,MATCH($T10,'Player Pool'!$Z$2:$Z$8725,0)))),"") | X10: =IFERROR(IF(INDEX('Player Pool'!$I$2:$I$8725,MATCH($T10,'Player Pool'!$Z$2:$Z$8725,0))="","",INDEX('Player Pool'!$I$2:$I$8725,MATCH($T10,'Player Pool'!$Z$2:$Z$8725,0))),"") | Y10: =IFERROR(IF(INDEX('Player Pool'!$P$2:$P$8725,MATCH($T10,'Player Pool'!$Z$2:$Z$8725,0))="","",INDEX('Player Pool'!$P$2:$P$8725,MATCH($T10,'Player Pool'!$Z$2:$Z$8725,0))),"") | Z10: =IFERROR(IF(INDEX('Player Pool'!$R$2:$R$8725,MATCH($T10,'Player Pool'!$Z$2:$Z$8725,0))="","",INDEX('Player Pool'!$R$2:$R$8725,MATCH($T10,'Player Pool'!$Z$2:$Z$8725,0))),"") | AA10: =IFERROR(IF(INDEX('Player Pool'!$U$2:$U$8725,MATCH($T10,'Player Pool'!$Z$2:$Z$8725,0))="","",INDEX('Player Pool'!$U$2:$U$8725,MATCH($T10,'Player Pool'!$Z$2:$Z$8725,0))),"") | AB10: =IFERROR(IF($T10="","",IF(INDEX('Player Pool'!$G$2:$G$8725,MATCH($T10,'Player Pool'!$Z$2:$Z$8725,0))="FA","FA",IF(INDEX('Player Pool'!$G$2:$G$8725,MATCH($T10,'Player Pool'!$Z$2:$Z$8725,0))='League Settings'!$B$2,"MINE","TAKEN"))),"") | AD10: Jackson LaCombe (ANA D) | AE10: =IFERROR(IF(INDEX('Player Pool'!$D$2:$D$8725,MATCH($AD10,'Player Pool'!$Z$2:$Z$8725,0))="","",INDEX('Player Pool'!$D$2:$D$8725,MATCH($AD10,'Player Pool'!$Z$2:$Z$8725,0))),"") | AF10: =IFERROR(IF(INDEX('Player Pool'!$E$2:$E$8725,MATCH($AD10,'Player Pool'!$Z$2:$Z$8725,0))="","",INDEX('Player Pool'!$E$2:$E$8725,MATCH($AD10,'Player Pool'!$Z$2:$Z$8725,0))),"") | AG10: =IFERROR(IF($AD10="","",IF(ISNUMBER(IFERROR(INDEX(Rosters!$I$2:$I$516,MATCH(INDEX('Player Pool'!$V$2:$V$8725,MATCH($AD10,'Player Pool'!$Z$2:$Z$8725,0)),Rosters!$W$2:$W$516,0)),"")),IFERROR(INDEX(Rosters!$I$2:$I$516,MATCH(INDEX('Player Pool'!$V$2:$V$8725,MATCH($AD10,'Player Pool'!$Z$2:$Z$8725,0)),Rosters!$W$2:$W$516,0)),""),INDEX('Player Pool'!$H$2:$H$8725,MATCH($AD10,'Player Pool'!$Z$2:$Z$8725,0)))),"") | AH10: =IFERROR(IF(INDEX('Player Pool'!$I$2:$I$8725,MATCH($AD10,'Player Pool'!$Z$2:$Z$8725,0))="","",INDEX('Player Pool'!$I$2:$I$8725,MATCH($AD10,'Player Pool'!$Z$2:$Z$8725,0))),"") | AI10: =IFERROR(IF(INDEX('Player Pool'!$P$2:$P$8725,MATCH($AD10,'Player Pool'!$Z$2:$Z$8725,0))="","",INDEX('Player Pool'!$P$2:$P$8725,MATCH($AD10,'Player Pool'!$Z$2:$Z$8725,0))),"") | AJ10: =IFERROR(IF(INDEX('Player Pool'!$R$2:$R$8725,MATCH($AD10,'Player Pool'!$Z$2:$Z$8725,0))="","",INDEX('Player Pool'!$R$2:$R$8725,MATCH($AD10,'Player Pool'!$Z$2:$Z$8725,0))),"") | AK10: =IFERROR(IF(INDEX('Player Pool'!$U$2:$U$8725,MATCH($AD10,'Player Pool'!$Z$2:$Z$8725,0))="","",INDEX('Player Pool'!$U$2:$U$8725,MATCH($AD10,'Player Pool'!$Z$2:$Z$8725,0))),"") | AL10: =IFERROR(IF($AD10="","",IF(INDEX('Player Pool'!$G$2:$G$8725,MATCH($AD10,'Player Pool'!$Z$2:$Z$8725,0))="FA","FA",IF(INDEX('Player Pool'!$G$2:$G$8725,MATCH($AD10,'Player Pool'!$Z$2:$Z$8725,0))='League Settings'!$B$2,"MINE","TAKEN"))),"") | AN10: Jackson LaCombe (ANA D) | AO10: =IFERROR(IF(INDEX('Player Pool'!$D$2:$D$8725,MATCH($AN10,'Player Pool'!$Z$2:$Z$8725,0))="","",INDEX('Player Pool'!$D$2:$D$8725,MATCH($AN10,'Player Pool'!$Z$2:$Z$8725,0))),"") | AP10: =IFERROR(IF(INDEX('Player Pool'!$E$2:$E$8725,MATCH($AN10,'Player Pool'!$Z$2:$Z$8725,0))="","",INDEX('Player Pool'!$E$2:$E$8725,MATCH($AN10,'Player Pool'!$Z$2:$Z$8725,0))),"") | AQ10: =IFERROR(IF($AN10="","",IF(ISNUMBER(IFERROR(INDEX(Rosters!$I$2:$I$516,MATCH(INDEX('Player Pool'!$V$2:$V$8725,MATCH($AN10,'Player Pool'!$Z$2:$Z$8725,0)),Rosters!$W$2:$W$516,0)),"")),IFERROR(INDEX(Rosters!$I$2:$I$516,MATCH(INDEX('Player Pool'!$V$2:$V$8725,MATCH($AN10,'Player Pool'!$Z$2:$Z$8725,0)),Rosters!$W$2:$W$516,0)),""),INDEX('Player Pool'!$H$2:$H$8725,MATCH($AN10,'Player Pool'!$Z$2:$Z$8725,0)))),"") | AR10: =IFERROR(IF(INDEX('Player Pool'!$I$2:$I$8725,MATCH($AN10,'Player Pool'!$Z$2:$Z$8725,0))="","",INDEX('Player Pool'!$I$2:$I$8725,MATCH($AN10,'Player Pool'!$Z$2:$Z$8725,0))),"") | AS10: =IFERROR(IF(INDEX('Player Pool'!$P$2:$P$8725,MATCH($AN10,'Player Pool'!$Z$2:$Z$8725,0))="","",INDEX('Player Pool'!$P$2:$P$8725,MATCH($AN10,'Player Pool'!$Z$2:$Z$8725,0))),"") | AT10: =IFERROR(IF(INDEX('Player Pool'!$R$2:$R$8725,MATCH($AN10,'Player Pool'!$Z$2:$Z$8725,0))="","",INDEX('Player Pool'!$R$2:$R$8725,MATCH($AN10,'Player Pool'!$Z$2:$Z$8725,0))),"") | AU10: =IFERROR(IF(INDEX('Player Pool'!$U$2:$U$8725,MATCH($AN10,'Player Pool'!$Z$2:$Z$8725,0))="","",INDEX('Player Pool'!$U$2:$U$8725,MATCH($AN10,'Player Pool'!$Z$2:$Z$8725,0))),"") | AV10: =IFERROR(IF($AN10="","",IF(INDEX('Player Pool'!$G$2:$G$8725,MATCH($AN10,'Player Pool'!$Z$2:$Z$8725,0))="FA","FA",IF(INDEX('Player Pool'!$G$2:$G$8725,MATCH($AN10,'Player Pool'!$Z$2:$Z$8725,0))='League Settings'!$B$2,"MINE","TAKEN"))),"")
A11: =IFERROR(IF(INDEX(Rosters!$B$2:$B$516,$S11)="","",INDEX(Rosters!$B$2:$B$516,$S11)),"") | B11: =IFERROR(IF(INDEX(Rosters!$C$2:$C$516,$S11)="","",INDEX(Rosters!$C$2:$C$516,$S11)),"") | C11: =IFERROR(IF(INDEX(Rosters!$D$2:$D$516,$S11)="","",INDEX(Rosters!$D$2:$D$516,$S11)),"") | D11: =IFERROR(IF(INDEX(Rosters!$E$2:$E$516,$S11)="","",INDEX(Rosters!$E$2:$E$516,$S11)),"") | E11: =IFERROR(IF(INDEX(Rosters!$F$2:$F$516,$S11)="","",INDEX(Rosters!$F$2:$F$516,$S11)),"") | F11: =IFERROR(IF(INDEX(Rosters!$G$2:$G$516,$S11)="","",INDEX(Rosters!$G$2:$G$516,$S11)),"") | G11: =IFERROR(IF(INDEX(Rosters!$H$2:$H$516,$S11)="","",INDEX(Rosters!$H$2:$H$516,$S11)),"") | H11: =IFERROR(IF(INDEX(Rosters!$I$2:$I$516,$S11)="","",INDEX(Rosters!$I$2:$I$516,$S11)),"") | I11: =IFERROR(IF(INDEX(Rosters!$J$2:$J$516,$S11)="","",INDEX(Rosters!$J$2:$J$516,$S11)),"") | J11: =IFERROR(IF(INDEX(Rosters!$S$2:$S$516,$S11)="","",INDEX(Rosters!$S$2:$S$516,$S11)),"") | K11: =IFERROR(IF(INDEX(Rosters!$K$2:$K$516,$S11)="","",INDEX(Rosters!$K$2:$K$516,$S11)),"") | L11: =IFERROR(IF(INDEX(Rosters!$T$2:$T$516,$S11)="","",INDEX(Rosters!$T$2:$T$516,$S11)),"") | M11: =IFERROR(IF(INDEX(Rosters!$L$2:$L$516,$S11)="","",INDEX(Rosters!$L$2:$L$516,$S11)),"") | N11: =IFERROR(IF(INDEX(Rosters!$Q$2:$Q$516,$S11)="","",INDEX(Rosters!$Q$2:$Q$516,$S11)),"") | O11: =IFERROR(IF(INDEX(Rosters!$R$2:$R$516,$S11)="","",INDEX(Rosters!$R$2:$R$516,$S11)),"") | P11: =IFERROR(IF(INDEX(Rosters!$N$2:$N$516,$S11)="","",INDEX(Rosters!$N$2:$N$516,$S11)),"") | Q11: =IFERROR(IF(INDEX(Rosters!$O$2:$O$516,$S11)="","",INDEX(Rosters!$O$2:$O$516,$S11)),"") | R11: =IFERROR(IF(INDEX(Rosters!$P$2:$P$516,$S11)="","",INDEX(Rosters!$P$2:$P$516,$S11)),"") | S11: =IFERROR(MATCH('League Settings'!$B$2&"|ACTIVE|"&8,Rosters!$AD$2:$AD$516,0),"") | T11: Morgan Geekie (BOS LW) | U11: =IFERROR(IF(INDEX('Player Pool'!$D$2:$D$8725,MATCH($T11,'Player Pool'!$Z$2:$Z$8725,0))="","",INDEX('Player Pool'!$D$2:$D$8725,MATCH($T11,'Player Pool'!$Z$2:$Z$8725,0))),"") | V11: =IFERROR(IF(INDEX('Player Pool'!$E$2:$E$8725,MATCH($T11,'Player Pool'!$Z$2:$Z$8725,0))="","",INDEX('Player Pool'!$E$2:$E$8725,MATCH($T11,'Player Pool'!$Z$2:$Z$8725,0))),"") | W11: =IFERROR(IF($T11="","",IF(ISNUMBER(IFERROR(INDEX(Rosters!$I$2:$I$516,MATCH(INDEX('Player Pool'!$V$2:$V$8725,MATCH($T11,'Player Pool'!$Z$2:$Z$8725,0)),Rosters!$W$2:$W$516,0)),"")),IFERROR(INDEX(Rosters!$I$2:$I$516,MATCH(INDEX('Player Pool'!$V$2:$V$8725,MATCH($T11,'Player Pool'!$Z$2:$Z$8725,0)),Rosters!$W$2:$W$516,0)),""),INDEX('Player Pool'!$H$2:$H$8725,MATCH($T11,'Player Pool'!$Z$2:$Z$8725,0)))),"") | X11: =IFERROR(IF(INDEX('Player Pool'!$I$2:$I$8725,MATCH($T11,'Player Pool'!$Z$2:$Z$8725,0))="","",INDEX('Player Pool'!$I$2:$I$8725,MATCH($T11,'Player Pool'!$Z$2:$Z$8725,0))),"") | Y11: =IFERROR(IF(INDEX('Player Pool'!$P$2:$P$8725,MATCH($T11,'Player Pool'!$Z$2:$Z$8725,0))="","",INDEX('Player Pool'!$P$2:$P$8725,MATCH($T11,'Player Pool'!$Z$2:$Z$8725,0))),"") | Z11: =IFERROR(IF(INDEX('Player Pool'!$R$2:$R$8725,MATCH($T11,'Player Pool'!$Z$2:$Z$8725,0))="","",INDEX('Player Pool'!$R$2:$R$8725,MATCH($T11,'Player Pool'!$Z$2:$Z$8725,0))),"") | AA11: =IFERROR(IF(INDEX('Player Pool'!$U$2:$U$8725,MATCH($T11,'Player Pool'!$Z$2:$Z$8725,0))="","",INDEX('Player Pool'!$U$2:$U$8725,MATCH($T11,'Player Pool'!$Z$2:$Z$8725,0))),"") | AB11: =IFERROR(IF($T11="","",IF(INDEX('Player Pool'!$G$2:$G$8725,MATCH($T11,'Player Pool'!$Z$2:$Z$8725,0))="FA","FA",IF(INDEX('Player Pool'!$G$2:$G$8725,MATCH($T11,'Player Pool'!$Z$2:$Z$8725,0))='League Settings'!$B$2,"MINE","TAKEN"))),"") | AD11: Morgan Geekie (BOS LW) | AE11: =IFERROR(IF(INDEX('Player Pool'!$D$2:$D$8725,MATCH($AD11,'Player Pool'!$Z$2:$Z$8725,0))="","",INDEX('Player Pool'!$D$2:$D$8725,MATCH($AD11,'Player Pool'!$Z$2:$Z$8725,0))),"") | AF11: =IFERROR(IF(INDEX('Player Pool'!$E$2:$E$8725,MATCH($AD11,'Player Pool'!$Z$2:$Z$8725,0))="","",INDEX('Player Pool'!$E$2:$E$8725,MATCH($AD11,'Player Pool'!$Z$2:$Z$8725,0))),"") | AG11: =IFERROR(IF($AD11="","",IF(ISNUMBER(IFERROR(INDEX(Rosters!$I$2:$I$516,MATCH(INDEX('Player Pool'!$V$2:$V$8725,MATCH($AD11,'Player Pool'!$Z$2:$Z$8725,0)),Rosters!$W$2:$W$516,0)),"")),IFERROR(INDEX(Rosters!$I$2:$I$516,MATCH(INDEX('Player Pool'!$V$2:$V$8725,MATCH($AD11,'Player Pool'!$Z$2:$Z$8725,0)),Rosters!$W$2:$W$516,0)),""),INDEX('Player Pool'!$H$2:$H$8725,MATCH($AD11,'Player Pool'!$Z$2:$Z$8725,0)))),"") | AH11: =IFERROR(IF(INDEX('Player Pool'!$I$2:$I$8725,MATCH($AD11,'Player Pool'!$Z$2:$Z$8725,0))="","",INDEX('Player Pool'!$I$2:$I$8725,MATCH($AD11,'Player Pool'!$Z$2:$Z$8725,0))),"") | AI11: =IFERROR(IF(INDEX('Player Pool'!$P$2:$P$8725,MATCH($AD11,'Player Pool'!$Z$2:$Z$8725,0))="","",INDEX('Player Pool'!$P$2:$P$8725,MATCH($AD11,'Player Pool'!$Z$2:$Z$8725,0))),"") | AJ11: =IFERROR(IF(INDEX('Player Pool'!$R$2:$R$8725,MATCH($AD11,'Player Pool'!$Z$2:$Z$8725,0))="","",INDEX('Player Pool'!$R$2:$R$8725,MATCH($AD11,'Player Pool'!$Z$2:$Z$8725,0))),"") | AK11: =IFERROR(IF(INDEX('Player Pool'!$U$2:$U$8725,MATCH($AD11,'Player Pool'!$Z$2:$Z$8725,0))="","",INDEX('Player Pool'!$U$2:$U$8725,MATCH($AD11,'Player Pool'!$Z$2:$Z$8725,0))),"") | AL11: =IFERROR(IF($AD11="","",IF(INDEX('Player Pool'!$G$2:$G$8725,MATCH($AD11,'Player Pool'!$Z$2:$Z$8725,0))="FA","FA",IF(INDEX('Player Pool'!$G$2:$G$8725,MATCH($AD11,'Player Pool'!$Z$2:$Z$8725,0))='League Settings'!$B$2,"MINE","TAKEN"))),"") | AN11: Morgan Geekie (BOS LW) | AO11: =IFERROR(IF(INDEX('Player Pool'!$D$2:$D$8725,MATCH($AN11,'Player Pool'!$Z$2:$Z$8725,0))="","",INDEX('Player Pool'!$D$2:$D$8725,MATCH($AN11,'Player Pool'!$Z$2:$Z$8725,0))),"") | AP11: =IFERROR(IF(INDEX('Player Pool'!$E$2:$E$8725,MATCH($AN11,'Player Pool'!$Z$2:$Z$8725,0))="","",INDEX('Player Pool'!$E$2:$E$8725,MATCH($AN11,'Player Pool'!$Z$2:$Z$8725,0))),"") | AQ11: =IFERROR(IF($AN11="","",IF(ISNUMBER(IFERROR(INDEX(Rosters!$I$2:$I$516,MATCH(INDEX('Player Pool'!$V$2:$V$8725,MATCH($AN11,'Player Pool'!$Z$2:$Z$8725,0)),Rosters!$W$2:$W$516,0)),"")),IFERROR(INDEX(Rosters!$I$2:$I$516,MATCH(INDEX('Player Pool'!$V$2:$V$8725,MATCH($AN11,'Player Pool'!$Z$2:$Z$8725,0)),Rosters!$W$2:$W$516,0)),""),INDEX('Player Pool'!$H$2:$H$8725,MATCH($AN11,'Player Pool'!$Z$2:$Z$8725,0)))),"") | AR11: =IFERROR(IF(INDEX('Player Pool'!$I$2:$I$8725,MATCH($AN11,'Player Pool'!$Z$2:$Z$8725,0))="","",INDEX('Player Pool'!$I$2:$I$8725,MATCH($AN11,'Player Pool'!$Z$2:$Z$8725,0))),"") | AS11: =IFERROR(IF(INDEX('Player Pool'!$P$2:$P$8725,MATCH($AN11,'Player Pool'!$Z$2:$Z$8725,0))="","",INDEX('Player Pool'!$P$2:$P$8725,MATCH($AN11,'Player Pool'!$Z$2:$Z$8725,0))),"") | AT11: =IFERROR(IF(INDEX('Player Pool'!$R$2:$R$8725,MATCH($AN11,'Player Pool'!$Z$2:$Z$8725,0))="","",INDEX('Player Pool'!$R$2:$R$8725,MATCH($AN11,'Player Pool'!$Z$2:$Z$8725,0))),"") | AU11: =IFERROR(IF(INDEX('Player Pool'!$U$2:$U$8725,MATCH($AN11,'Player Pool'!$Z$2:$Z$8725,0))="","",INDEX('Player Pool'!$U$2:$U$8725,MATCH($AN11,'Player Pool'!$Z$2:$Z$8725,0))),"") | AV11: =IFERROR(IF($AN11="","",IF(INDEX('Player Pool'!$G$2:$G$8725,MATCH($AN11,'Player Pool'!$Z$2:$Z$8725,0))="FA","FA",IF(INDEX('Player Pool'!$G$2:$G$8725,MATCH($AN11,'Player Pool'!$Z$2:$Z$8725,0))='League Settings'!$B$2,"MINE","TAKEN"))),"")
A12: =IFERROR(IF(INDEX(Rosters!$B$2:$B$516,$S12)="","",INDEX(Rosters!$B$2:$B$516,$S12)),"") | B12: =IFERROR(IF(INDEX(Rosters!$C$2:$C$516,$S12)="","",INDEX(Rosters!$C$2:$C$516,$S12)),"") | C12: =IFERROR(IF(INDEX(Rosters!$D$2:$D$516,$S12)="","",INDEX(Rosters!$D$2:$D$516,$S12)),"") | D12: =IFERROR(IF(INDEX(Rosters!$E$2:$E$516,$S12)="","",INDEX(Rosters!$E$2:$E$516,$S12)),"") | E12: =IFERROR(IF(INDEX(Rosters!$F$2:$F$516,$S12)="","",INDEX(Rosters!$F$2:$F$516,$S12)),"") | F12: =IFERROR(IF(INDEX(Rosters!$G$2:$G$516,$S12)="","",INDEX(Rosters!$G$2:$G$516,$S12)),"") | G12: =IFERROR(IF(INDEX(Rosters!$H$2:$H$516,$S12)="","",INDEX(Rosters!$H$2:$H$516,$S12)),"") | H12: =IFERROR(IF(INDEX(Rosters!$I$2:$I$516,$S12)="","",INDEX(Rosters!$I$2:$I$516,$S12)),"") | I12: =IFERROR(IF(INDEX(Rosters!$J$2:$J$516,$S12)="","",INDEX(Rosters!$J$2:$J$516,$S12)),"") | J12: =IFERROR(IF(INDEX(Rosters!$S$2:$S$516,$S12)="","",INDEX(Rosters!$S$2:$S$516,$S12)),"") | K12: =IFERROR(IF(INDEX(Rosters!$K$2:$K$516,$S12)="","",INDEX(Rosters!$K$2:$K$516,$S12)),"") | L12: =IFERROR(IF(INDEX(Rosters!$T$2:$T$516,$S12)="","",INDEX(Rosters!$T$2:$T$516,$S12)),"") | M12: =IFERROR(IF(INDEX(Rosters!$L$2:$L$516,$S12)="","",INDEX(Rosters!$L$2:$L$516,$S12)),"") | N12: =IFERROR(IF(INDEX(Rosters!$Q$2:$Q$516,$S12)="","",INDEX(Rosters!$Q$2:$Q$516,$S12)),"") | O12: =IFERROR(IF(INDEX(Rosters!$R$2:$R$516,$S12)="","",INDEX(Rosters!$R$2:$R$516,$S12)),"") | P12: =IFERROR(IF(INDEX(Rosters!$N$2:$N$516,$S12)="","",INDEX(Rosters!$N$2:$N$516,$S12)),"") | Q12: =IFERROR(IF(INDEX(Rosters!$O$2:$O$516,$S12)="","",INDEX(Rosters!$O$2:$O$516,$S12)),"") | R12: =IFERROR(IF(INDEX(Rosters!$P$2:$P$516,$S12)="","",INDEX(Rosters!$P$2:$P$516,$S12)),"") | S12: =IFERROR(MATCH('League Settings'!$B$2&"|ACTIVE|"&9,Rosters!$AD$2:$AD$516,0),"") | T12: Mackenzie Blackwood (COL G) | U12: =IFERROR(IF(INDEX('Player Pool'!$D$2:$D$8725,MATCH($T12,'Player Pool'!$Z$2:$Z$8725,0))="","",INDEX('Player Pool'!$D$2:$D$8725,MATCH($T12,'Player Pool'!$Z$2:$Z$8725,0))),"") | V12: =IFERROR(IF(INDEX('Player Pool'!$E$2:$E$8725,MATCH($T12,'Player Pool'!$Z$2:$Z$8725,0))="","",INDEX('Player Pool'!$E$2:$E$8725,MATCH($T12,'Player Pool'!$Z$2:$Z$8725,0))),"") | W12: =IFERROR(IF($T12="","",IF(ISNUMBER(IFERROR(INDEX(Rosters!$I$2:$I$516,MATCH(INDEX('Player Pool'!$V$2:$V$8725,MATCH($T12,'Player Pool'!$Z$2:$Z$8725,0)),Rosters!$W$2:$W$516,0)),"")),IFERROR(INDEX(Rosters!$I$2:$I$516,MATCH(INDEX('Player Pool'!$V$2:$V$8725,MATCH($T12,'Player Pool'!$Z$2:$Z$8725,0)),Rosters!$W$2:$W$516,0)),""),INDEX('Player Pool'!$H$2:$H$8725,MATCH($T12,'Player Pool'!$Z$2:$Z$8725,0)))),"") | X12: =IFERROR(IF(INDEX('Player Pool'!$I$2:$I$8725,MATCH($T12,'Player Pool'!$Z$2:$Z$8725,0))="","",INDEX('Player Pool'!$I$2:$I$8725,MATCH($T12,'Player Pool'!$Z$2:$Z$8725,0))),"") | Y12: =IFERROR(IF(INDEX('Player Pool'!$P$2:$P$8725,MATCH($T12,'Player Pool'!$Z$2:$Z$8725,0))="","",INDEX('Player Pool'!$P$2:$P$8725,MATCH($T12,'Player Pool'!$Z$2:$Z$8725,0))),"") | Z12: =IFERROR(IF(INDEX('Player Pool'!$R$2:$R$8725,MATCH($T12,'Player Pool'!$Z$2:$Z$8725,0))="","",INDEX('Player Pool'!$R$2:$R$8725,MATCH($T12,'Player Pool'!$Z$2:$Z$8725,0))),"") | AA12: =IFERROR(IF(INDEX('Player Pool'!$U$2:$U$8725,MATCH($T12,'Player Pool'!$Z$2:$Z$8725,0))="","",INDEX('Player Pool'!$U$2:$U$8725,MATCH($T12,'Player Pool'!$Z$2:$Z$8725,0))),"") | AB12: =IFERROR(IF($T12="","",IF(INDEX('Player Pool'!$G$2:$G$8725,MATCH($T12,'Player Pool'!$Z$2:$Z$8725,0))="FA","FA",IF(INDEX('Player Pool'!$G$2:$G$8725,MATCH($T12,'Player Pool'!$Z$2:$Z$8725,0))='League Settings'!$B$2,"MINE","TAKEN"))),"") | AD12: Mackenzie Blackwood (COL G) | AE12: =IFERROR(IF(INDEX('Player Pool'!$D$2:$D$8725,MATCH($AD12,'Player Pool'!$Z$2:$Z$8725,0))="","",INDEX('Player Pool'!$D$2:$D$8725,MATCH($AD12,'Player Pool'!$Z$2:$Z$8725,0))),"") | AF12: =IFERROR(IF(INDEX('Player Pool'!$E$2:$E$8725,MATCH($AD12,'Player Pool'!$Z$2:$Z$8725,0))="","",INDEX('Player Pool'!$E$2:$E$8725,MATCH($AD12,'Player Pool'!$Z$2:$Z$8725,0))),"") | AG12: =IFERROR(IF($AD12="","",IF(ISNUMBER(IFERROR(INDEX(Rosters!$I$2:$I$516,MATCH(INDEX('Player Pool'!$V$2:$V$8725,MATCH($AD12,'Player Pool'!$Z$2:$Z$8725,0)),Rosters!$W$2:$W$516,0)),"")),IFERROR(INDEX(Rosters!$I$2:$I$516,MATCH(INDEX('Player Pool'!$V$2:$V$8725,MATCH($AD12,'Player Pool'!$Z$2:$Z$8725,0)),Rosters!$W$2:$W$516,0)),""),INDEX('Player Pool'!$H$2:$H$8725,MATCH($AD12,'Player Pool'!$Z$2:$Z$8725,0)))),"") | AH12: =IFERROR(IF(INDEX('Player Pool'!$I$2:$I$8725,MATCH($AD12,'Player Pool'!$Z$2:$Z$8725,0))="","",INDEX('Player Pool'!$I$2:$I$8725,MATCH($AD12,'Player Pool'!$Z$2:$Z$8725,0))),"") | AI12: =IFERROR(IF(INDEX('Player Pool'!$P$2:$P$8725,MATCH($AD12,'Player Pool'!$Z$2:$Z$8725,0))="","",INDEX('Player Pool'!$P$2:$P$8725,MATCH($AD12,'Player Pool'!$Z$2:$Z$8725,0))),"") | AJ12: =IFERROR(IF(INDEX('Player Pool'!$R$2:$R$8725,MATCH($AD12,'Player Pool'!$Z$2:$Z$8725,0))="","",INDEX('Player Pool'!$R$2:$R$8725,MATCH($AD12,'Player Pool'!$Z$2:$Z$8725,0))),"") | AK12: =IFERROR(IF(INDEX('Player Pool'!$U$2:$U$8725,MATCH($AD12,'Player Pool'!$Z$2:$Z$8725,0))="","",INDEX('Player Pool'!$U$2:$U$8725,MATCH($AD12,'Player Pool'!$Z$2:$Z$8725,0))),"") | AL12: =IFERROR(IF($AD12="","",IF(INDEX('Player Pool'!$G$2:$G$8725,MATCH($AD12,'Player Pool'!$Z$2:$Z$8725,0))="FA","FA",IF(INDEX('Player Pool'!$G$2:$G$8725,MATCH($AD12,'Player Pool'!$Z$2:$Z$8725,0))='League Settings'!$B$2,"MINE","TAKEN"))),"") | AN12: Mackenzie Blackwood (COL G) | AO12: =IFERROR(IF(INDEX('Player Pool'!$D$2:$D$8725,MATCH($AN12,'Player Pool'!$Z$2:$Z$8725,0))="","",INDEX('Player Pool'!$D$2:$D$8725,MATCH($AN12,'Player Pool'!$Z$2:$Z$8725,0))),"") | AP12: =IFERROR(IF(INDEX('Player Pool'!$E$2:$E$8725,MATCH($AN12,'Player Pool'!$Z$2:$Z$8725,0))="","",INDEX('Player Pool'!$E$2:$E$8725,MATCH($AN12,'Player Pool'!$Z$2:$Z$8725,0))),"") | AQ12: =IFERROR(IF($AN12="","",IF(ISNUMBER(IFERROR(INDEX(Rosters!$I$2:$I$516,MATCH(INDEX('Player Pool'!$V$2:$V$8725,MATCH($AN12,'Player Pool'!$Z$2:$Z$8725,0)),Rosters!$W$2:$W$516,0)),"")),IFERROR(INDEX(Rosters!$I$2:$I$516,MATCH(INDEX('Player Pool'!$V$2:$V$8725,MATCH($AN12,'Player Pool'!$Z$2:$Z$8725,0)),Rosters!$W$2:$W$516,0)),""),INDEX('Player Pool'!$H$2:$H$8725,MATCH($AN12,'Player Pool'!$Z$2:$Z$8725,0)))),"") | AR12: =IFERROR(IF(INDEX('Player Pool'!$I$2:$I$8725,MATCH($AN12,'Player Pool'!$Z$2:$Z$8725,0))="","",INDEX('Player Pool'!$I$2:$I$8725,MATCH($AN12,'Player Pool'!$Z$2:$Z$8725,0))),"") | AS12: =IFERROR(IF(INDEX('Player Pool'!$P$2:$P$8725,MATCH($AN12,'Player Pool'!$Z$2:$Z$8725,0))="","",INDEX('Player Pool'!$P$2:$P$8725,MATCH($AN12,'Player Pool'!$Z$2:$Z$8725,0))),"") | AT12: =IFERROR(IF(INDEX('Player Pool'!$R$2:$R$8725,MATCH($AN12,'Player Pool'!$Z$2:$Z$8725,0))="","",INDEX('Player Pool'!$R$2:$R$8725,MATCH($AN12,'Player Pool'!$Z$2:$Z$8725,0))),"") | AU12: =IFERROR(IF(INDEX('Player Pool'!$U$2:$U$8725,MATCH($AN12,'Player Pool'!$Z$2:$Z$8725,0))="","",INDEX('Player Pool'!$U$2:$U$8725,MATCH($AN12,'Player Pool'!$Z$2:$Z$8725,0))),"") | AV12: =IFERROR(IF($AN12="","",IF(INDEX('Player Pool'!$G$2:$G$8725,MATCH($AN12,'Player Pool'!$Z$2:$Z$8725,0))="FA","FA",IF(INDEX('Player Pool'!$G$2:$G$8725,MATCH($AN12,'Player Pool'!$Z$2:$Z$8725,0))='League Settings'!$B$2,"MINE","TAKEN"))),"")
A13: =IFERROR(IF(INDEX(Rosters!$B$2:$B$516,$S13)="","",INDEX(Rosters!$B$2:$B$516,$S13)),"") | B13: =IFERROR(IF(INDEX(Rosters!$C$2:$C$516,$S13)="","",INDEX(Rosters!$C$2:$C$516,$S13)),"") | C13: =IFERROR(IF(INDEX(Rosters!$D$2:$D$516,$S13)="","",INDEX(Rosters!$D$2:$D$516,$S13)),"") | D13: =IFERROR(IF(INDEX(Rosters!$E$2:$E$516,$S13)="","",INDEX(Rosters!$E$2:$E$516,$S13)),"") | E13: =IFERROR(IF(INDEX(Rosters!$F$2:$F$516,$S13)="","",INDEX(Rosters!$F$2:$F$516,$S13)),"") | F13: =IFERROR(IF(INDEX(Rosters!$G$2:$G$516,$S13)="","",INDEX(Rosters!$G$2:$G$516,$S13)),"") | G13: =IFERROR(IF(INDEX(Rosters!$H$2:$H$516,$S13)="","",INDEX(Rosters!$H$2:$H$516,$S13)),"") | H13: =IFERROR(IF(INDEX(Rosters!$I$2:$I$516,$S13)="","",INDEX(Rosters!$I$2:$I$516,$S13)),"") | I13: =IFERROR(IF(INDEX(Rosters!$J$2:$J$516,$S13)="","",INDEX(Rosters!$J$2:$J$516,$S13)),"") | J13: =IFERROR(IF(INDEX(Rosters!$S$2:$S$516,$S13)="","",INDEX(Rosters!$S$2:$S$516,$S13)),"") | K13: =IFERROR(IF(INDEX(Rosters!$K$2:$K$516,$S13)="","",INDEX(Rosters!$K$2:$K$516,$S13)),"") | L13: =IFERROR(IF(INDEX(Rosters!$T$2:$T$516,$S13)="","",INDEX(Rosters!$T$2:$T$516,$S13)),"") | M13: =IFERROR(IF(INDEX(Rosters!$L$2:$L$516,$S13)="","",INDEX(Rosters!$L$2:$L$516,$S13)),"") | N13: =IFERROR(IF(INDEX(Rosters!$Q$2:$Q$516,$S13)="","",INDEX(Rosters!$Q$2:$Q$516,$S13)),"") | O13: =IFERROR(IF(INDEX(Rosters!$R$2:$R$516,$S13)="","",INDEX(Rosters!$R$2:$R$516,$S13)),"") | P13: =IFERROR(IF(INDEX(Rosters!$N$2:$N$516,$S13)="","",INDEX(Rosters!$N$2:$N$516,$S13)),"") | Q13: =IFERROR(IF(INDEX(Rosters!$O$2:$O$516,$S13)="","",INDEX(Rosters!$O$2:$O$516,$S13)),"") | R13: =IFERROR(IF(INDEX(Rosters!$P$2:$P$516,$S13)="","",INDEX(Rosters!$P$2:$P$516,$S13)),"") | S13: =IFERROR(MATCH('League Settings'!$B$2&"|ACTIVE|"&10,Rosters!$AD$2:$AD$516,0),"") | T13: Seth Jarvis (CAR RW) | U13: =IFERROR(IF(INDEX('Player Pool'!$D$2:$D$8725,MATCH($T13,'Player Pool'!$Z$2:$Z$8725,0))="","",INDEX('Player Pool'!$D$2:$D$8725,MATCH($T13,'Player Pool'!$Z$2:$Z$8725,0))),"") | V13: =IFERROR(IF(INDEX('Player Pool'!$E$2:$E$8725,MATCH($T13,'Player Pool'!$Z$2:$Z$8725,0))="","",INDEX('Player Pool'!$E$2:$E$8725,MATCH($T13,'Player Pool'!$Z$2:$Z$8725,0))),"") | W13: =IFERROR(IF($T13="","",IF(ISNUMBER(IFERROR(INDEX(Rosters!$I$2:$I$516,MATCH(INDEX('Player Pool'!$V$2:$V$8725,MATCH($T13,'Player Pool'!$Z$2:$Z$8725,0)),Rosters!$W$2:$W$516,0)),"")),IFERROR(INDEX(Rosters!$I$2:$I$516,MATCH(INDEX('Player Pool'!$V$2:$V$8725,MATCH($T13,'Player Pool'!$Z$2:$Z$8725,0)),Rosters!$W$2:$W$516,0)),""),INDEX('Player Pool'!$H$2:$H$8725,MATCH($T13,'Player Pool'!$Z$2:$Z$8725,0)))),"") | X13: =IFERROR(IF(INDEX('Player Pool'!$I$2:$I$8725,MATCH($T13,'Player Pool'!$Z$2:$Z$8725,0))="","",INDEX('Player Pool'!$I$2:$I$8725,MATCH($T13,'Player Pool'!$Z$2:$Z$8725,0))),"") | Y13: =IFERROR(IF(INDEX('Player Pool'!$P$2:$P$8725,MATCH($T13,'Player Pool'!$Z$2:$Z$8725,0))="","",INDEX('Player Pool'!$P$2:$P$8725,MATCH($T13,'Player Pool'!$Z$2:$Z$8725,0))),"") | Z13: =IFERROR(IF(INDEX('Player Pool'!$R$2:$R$8725,MATCH($T13,'Player Pool'!$Z$2:$Z$8725,0))="","",INDEX('Player Pool'!$R$2:$R$8725,MATCH($T13,'Player Pool'!$Z$2:$Z$8725,0))),"") | AA13: =IFERROR(IF(INDEX('Player Pool'!$U$2:$U$8725,MATCH($T13,'Player Pool'!$Z$2:$Z$8725,0))="","",INDEX('Player Pool'!$U$2:$U$8725,MATCH($T13,'Player Pool'!$Z$2:$Z$8725,0))),"") | AB13: =IFERROR(IF($T13="","",IF(INDEX('Player Pool'!$G$2:$G$8725,MATCH($T13,'Player Pool'!$Z$2:$Z$8725,0))="FA","FA",IF(INDEX('Player Pool'!$G$2:$G$8725,MATCH($T13,'Player Pool'!$Z$2:$Z$8725,0))='League Settings'!$B$2,"MINE","TAKEN"))),"") | AD13: Seth Jarvis (CAR RW) | AE13: =IFERROR(IF(INDEX('Player Pool'!$D$2:$D$8725,MATCH($AD13,'Player Pool'!$Z$2:$Z$8725,0))="","",INDEX('Player Pool'!$D$2:$D$8725,MATCH($AD13,'Player Pool'!$Z$2:$Z$8725,0))),"") | AF13: =IFERROR(IF(INDEX('Player Pool'!$E$2:$E$8725,MATCH($AD13,'Player Pool'!$Z$2:$Z$8725,0))="","",INDEX('Player Pool'!$E$2:$E$8725,MATCH($AD13,'Player Pool'!$Z$2:$Z$8725,0))),"") | AG13: =IFERROR(IF($AD13="","",IF(ISNUMBER(IFERROR(INDEX(Rosters!$I$2:$I$516,MATCH(INDEX('Player Pool'!$V$2:$V$8725,MATCH($AD13,'Player Pool'!$Z$2:$Z$8725,0)),Rosters!$W$2:$W$516,0)),"")),IFERROR(INDEX(Rosters!$I$2:$I$516,MATCH(INDEX('Player Pool'!$V$2:$V$8725,MATCH($AD13,'Player Pool'!$Z$2:$Z$8725,0)),Rosters!$W$2:$W$516,0)),""),INDEX('Player Pool'!$H$2:$H$8725,MATCH($AD13,'Player Pool'!$Z$2:$Z$8725,0)))),"") | AH13: =IFERROR(IF(INDEX('Player Pool'!$I$2:$I$8725,MATCH($AD13,'Player Pool'!$Z$2:$Z$8725,0))="","",INDEX('Player Pool'!$I$2:$I$8725,MATCH($AD13,'Player Pool'!$Z$2:$Z$8725,0))),"") | AI13: =IFERROR(IF(INDEX('Player Pool'!$P$2:$P$8725,MATCH($AD13,'Player Pool'!$Z$2:$Z$8725,0))="","",INDEX('Player Pool'!$P$2:$P$8725,MATCH($AD13,'Player Pool'!$Z$2:$Z$8725,0))),"") | AJ13: =IFERROR(IF(INDEX('Player Pool'!$R$2:$R$8725,MATCH($AD13,'Player Pool'!$Z$2:$Z$8725,0))="","",INDEX('Player Pool'!$R$2:$R$8725,MATCH($AD13,'Player Pool'!$Z$2:$Z$8725,0))),"") | AK13: =IFERROR(IF(INDEX('Player Pool'!$U$2:$U$8725,MATCH($AD13,'Player Pool'!$Z$2:$Z$8725,0))="","",INDEX('Player Pool'!$U$2:$U$8725,MATCH($AD13,'Player Pool'!$Z$2:$Z$8725,0))),"") | AL13: =IFERROR(IF($AD13="","",IF(INDEX('Player Pool'!$G$2:$G$8725,MATCH($AD13,'Player Pool'!$Z$2:$Z$8725,0))="FA","FA",IF(INDEX('Player Pool'!$G$2:$G$8725,MATCH($AD13,'Player Pool'!$Z$2:$Z$8725,0))='League Settings'!$B$2,"MINE","TAKEN"))),"") | AN13: Seth Jarvis (CAR RW) | AO13: =IFERROR(IF(INDEX('Player Pool'!$D$2:$D$8725,MATCH($AN13,'Player Pool'!$Z$2:$Z$8725,0))="","",INDEX('Player Pool'!$D$2:$D$8725,MATCH($AN13,'Player Pool'!$Z$2:$Z$8725,0))),"") | AP13: =IFERROR(IF(INDEX('Player Pool'!$E$2:$E$8725,MATCH($AN13,'Player Pool'!$Z$2:$Z$8725,0))="","",INDEX('Player Pool'!$E$2:$E$8725,MATCH($AN13,'Player Pool'!$Z$2:$Z$8725,0))),"") | AQ13: =IFERROR(IF($AN13="","",IF(ISNUMBER(IFERROR(INDEX(Rosters!$I$2:$I$516,MATCH(INDEX('Player Pool'!$V$2:$V$8725,MATCH($AN13,'Player Pool'!$Z$2:$Z$8725,0)),Rosters!$W$2:$W$516,0)),"")),IFERROR(INDEX(Rosters!$I$2:$I$516,MATCH(INDEX('Player Pool'!$V$2:$V$8725,MATCH($AN13,'Player Pool'!$Z$2:$Z$8725,0)),Rosters!$W$2:$W$516,0)),""),INDEX('Player Pool'!$H$2:$H$8725,MATCH($AN13,'Player Pool'!$Z$2:$Z$8725,0)))),"") | AR13: =IFERROR(IF(INDEX('Player Pool'!$I$2:$I$8725,MATCH($AN13,'Player Pool'!$Z$2:$Z$8725,0))="","",INDEX('Player Pool'!$I$2:$I$8725,MATCH($AN13,'Player Pool'!$Z$2:$Z$8725,0))),"") | AS13: =IFERROR(IF(INDEX('Player Pool'!$P$2:$P$8725,MATCH($AN13,'Player Pool'!$Z$2:$Z$8725,0))="","",INDEX('Player Pool'!$P$2:$P$8725,MATCH($AN13,'Player Pool'!$Z$2:$Z$8725,0))),"") | AT13: =IFERROR(IF(INDEX('Player Pool'!$R$2:$R$8725,MATCH($AN13,'Player Pool'!$Z$2:$Z$8725,0))="","",INDEX('Player Pool'!$R$2:$R$8725,MATCH($AN13,'Player Pool'!$Z$2:$Z$8725,0))),"") | AU13: =IFERROR(IF(INDEX('Player Pool'!$U$2:$U$8725,MATCH($AN13,'Player Pool'!$Z$2:$Z$8725,0))="","",INDEX('Player Pool'!$U$2:$U$8725,MATCH($AN13,'Player Pool'!$Z$2:$Z$8725,0))),"") | AV13: =IFERROR(IF($AN13="","",IF(INDEX('Player Pool'!$G$2:$G$8725,MATCH($AN13,'Player Pool'!$Z$2:$Z$8725,0))="FA","FA",IF(INDEX('Player Pool'!$G$2:$G$8725,MATCH($AN13,'Player Pool'!$Z$2:$Z$8725,0))='League Settings'!$B$2,"MINE","TAKEN"))),"")
A14: =IFERROR(IF(INDEX(Rosters!$B$2:$B$516,$S14)="","",INDEX(Rosters!$B$2:$B$516,$S14)),"") | B14: =IFERROR(IF(INDEX(Rosters!$C$2:$C$516,$S14)="","",INDEX(Rosters!$C$2:$C$516,$S14)),"") | C14: =IFERROR(IF(INDEX(Rosters!$D$2:$D$516,$S14)="","",INDEX(Rosters!$D$2:$D$516,$S14)),"") | D14: =IFERROR(IF(INDEX(Rosters!$E$2:$E$516,$S14)="","",INDEX(Rosters!$E$2:$E$516,$S14)),"") | E14: =IFERROR(IF(INDEX(Rosters!$F$2:$F$516,$S14)="","",INDEX(Rosters!$F$2:$F$516,$S14)),"") | F14: =IFERROR(IF(INDEX(Rosters!$G$2:$G$516,$S14)="","",INDEX(Rosters!$G$2:$G$516,$S14)),"") | G14: =IFERROR(IF(INDEX(Rosters!$H$2:$H$516,$S14)="","",INDEX(Rosters!$H$2:$H$516,$S14)),"") | H14: =IFERROR(IF(INDEX(Rosters!$I$2:$I$516,$S14)="","",INDEX(Rosters!$I$2:$I$516,$S14)),"") | I14: =IFERROR(IF(INDEX(Rosters!$J$2:$J$516,$S14)="","",INDEX(Rosters!$J$2:$J$516,$S14)),"") | J14: =IFERROR(IF(INDEX(Rosters!$S$2:$S$516,$S14)="","",INDEX(Rosters!$S$2:$S$516,$S14)),"") | K14: =IFERROR(IF(INDEX(Rosters!$K$2:$K$516,$S14)="","",INDEX(Rosters!$K$2:$K$516,$S14)),"") | L14: =IFERROR(IF(INDEX(Rosters!$T$2:$T$516,$S14)="","",INDEX(Rosters!$T$2:$T$516,$S14)),"") | M14: =IFERROR(IF(INDEX(Rosters!$L$2:$L$516,$S14)="","",INDEX(Rosters!$L$2:$L$516,$S14)),"") | N14: =IFERROR(IF(INDEX(Rosters!$Q$2:$Q$516,$S14)="","",INDEX(Rosters!$Q$2:$Q$516,$S14)),"") | O14: =IFERROR(IF(INDEX(Rosters!$R$2:$R$516,$S14)="","",INDEX(Rosters!$R$2:$R$516,$S14)),"") | P14: =IFERROR(IF(INDEX(Rosters!$N$2:$N$516,$S14)="","",INDEX(Rosters!$N$2:$N$516,$S14)),"") | Q14: =IFERROR(IF(INDEX(Rosters!$O$2:$O$516,$S14)="","",INDEX(Rosters!$O$2:$O$516,$S14)),"") | R14: =IFERROR(IF(INDEX(Rosters!$P$2:$P$516,$S14)="","",INDEX(Rosters!$P$2:$P$516,$S14)),"") | S14: =IFERROR(MATCH('League Settings'!$B$2&"|ACTIVE|"&11,Rosters!$AD$2:$AD$516,0),"") | T14: Matvei Michkov (PHI RW) | U14: =IFERROR(IF(INDEX('Player Pool'!$D$2:$D$8725,MATCH($T14,'Player Pool'!$Z$2:$Z$8725,0))="","",INDEX('Player Pool'!$D$2:$D$8725,MATCH($T14,'Player Pool'!$Z$2:$Z$8725,0))),"") | V14: =IFERROR(IF(INDEX('Player Pool'!$E$2:$E$8725,MATCH($T14,'Player Pool'!$Z$2:$Z$8725,0))="","",INDEX('Player Pool'!$E$2:$E$8725,MATCH($T14,'Player Pool'!$Z$2:$Z$8725,0))),"") | W14: =IFERROR(IF($T14="","",IF(ISNUMBER(IFERROR(INDEX(Rosters!$I$2:$I$516,MATCH(INDEX('Player Pool'!$V$2:$V$8725,MATCH($T14,'Player Pool'!$Z$2:$Z$8725,0)),Rosters!$W$2:$W$516,0)),"")),IFERROR(INDEX(Rosters!$I$2:$I$516,MATCH(INDEX('Player Pool'!$V$2:$V$8725,MATCH($T14,'Player Pool'!$Z$2:$Z$8725,0)),Rosters!$W$2:$W$516,0)),""),INDEX('Player Pool'!$H$2:$H$8725,MATCH($T14,'Player Pool'!$Z$2:$Z$8725,0)))),"") | X14: =IFERROR(IF(INDEX('Player Pool'!$I$2:$I$8725,MATCH($T14,'Player Pool'!$Z$2:$Z$8725,0))="","",INDEX('Player Pool'!$I$2:$I$8725,MATCH($T14,'Player Pool'!$Z$2:$Z$8725,0))),"") | Y14: =IFERROR(IF(INDEX('Player Pool'!$P$2:$P$8725,MATCH($T14,'Player Pool'!$Z$2:$Z$8725,0))="","",INDEX('Player Pool'!$P$2:$P$8725,MATCH($T14,'Player Pool'!$Z$2:$Z$8725,0))),"") | Z14: =IFERROR(IF(INDEX('Player Pool'!$R$2:$R$8725,MATCH($T14,'Player Pool'!$Z$2:$Z$8725,0))="","",INDEX('Player Pool'!$R$2:$R$8725,MATCH($T14,'Player Pool'!$Z$2:$Z$8725,0))),"") | AA14: =IFERROR(IF(INDEX('Player Pool'!$U$2:$U$8725,MATCH($T14,'Player Pool'!$Z$2:$Z$8725,0))="","",INDEX('Player Pool'!$U$2:$U$8725,MATCH($T14,'Player Pool'!$Z$2:$Z$8725,0))),"") | AB14: =IFERROR(IF($T14="","",IF(INDEX('Player Pool'!$G$2:$G$8725,MATCH($T14,'Player Pool'!$Z$2:$Z$8725,0))="FA","FA",IF(INDEX('Player Pool'!$G$2:$G$8725,MATCH($T14,'Player Pool'!$Z$2:$Z$8725,0))='League Settings'!$B$2,"MINE","TAKEN"))),"") | AD14: Matvei Michkov (PHI RW) | AE14: =IFERROR(IF(INDEX('Player Pool'!$D$2:$D$8725,MATCH($AD14,'Player Pool'!$Z$2:$Z$8725,0))="","",INDEX('Player Pool'!$D$2:$D$8725,MATCH($AD14,'Player Pool'!$Z$2:$Z$8725,0))),"") | AF14: =IFERROR(IF(INDEX('Player Pool'!$E$2:$E$8725,MATCH($AD14,'Player Pool'!$Z$2:$Z$8725,0))="","",INDEX('Player Pool'!$E$2:$E$8725,MATCH($AD14,'Player Pool'!$Z$2:$Z$8725,0))),"") | AG14: =IFERROR(IF($AD14="","",IF(ISNUMBER(IFERROR(INDEX(Rosters!$I$2:$I$516,MATCH(INDEX('Player Pool'!$V$2:$V$8725,MATCH($AD14,'Player Pool'!$Z$2:$Z$8725,0)),Rosters!$W$2:$W$516,0)),"")),IFERROR(INDEX(Rosters!$I$2:$I$516,MATCH(INDEX('Player Pool'!$V$2:$V$8725,MATCH($AD14,'Player Pool'!$Z$2:$Z$8725,0)),Rosters!$W$2:$W$516,0)),""),INDEX('Player Pool'!$H$2:$H$8725,MATCH($AD14,'Player Pool'!$Z$2:$Z$8725,0)))),"") | AH14: =IFERROR(IF(INDEX('Player Pool'!$I$2:$I$8725,MATCH($AD14,'Player Pool'!$Z$2:$Z$8725,0))="","",INDEX('Player Pool'!$I$2:$I$8725,MATCH($AD14,'Player Pool'!$Z$2:$Z$8725,0))),"") | AI14: =IFERROR(IF(INDEX('Player Pool'!$P$2:$P$8725,MATCH($AD14,'Player Pool'!$Z$2:$Z$8725,0))="","",INDEX('Player Pool'!$P$2:$P$8725,MATCH($AD14,'Player Pool'!$Z$2:$Z$8725,0))),"") | AJ14: =IFERROR(IF(INDEX('Player Pool'!$R$2:$R$8725,MATCH($AD14,'Player Pool'!$Z$2:$Z$8725,0))="","",INDEX('Player Pool'!$R$2:$R$8725,MATCH($AD14,'Player Pool'!$Z$2:$Z$8725,0))),"") | AK14: =IFERROR(IF(INDEX('Player Pool'!$U$2:$U$8725,MATCH($AD14,'Player Pool'!$Z$2:$Z$8725,0))="","",INDEX('Player Pool'!$U$2:$U$8725,MATCH($AD14,'Player Pool'!$Z$2:$Z$8725,0))),"") | AL14: =IFERROR(IF($AD14="","",IF(INDEX('Player Pool'!$G$2:$G$8725,MATCH($AD14,'Player Pool'!$Z$2:$Z$8725,0))="FA","FA",IF(INDEX('Player Pool'!$G$2:$G$8725,MATCH($AD14,'Player Pool'!$Z$2:$Z$8725,0))='League Settings'!$B$2,"MINE","TAKEN"))),"") | AN14: Matvei Michkov (PHI RW) | AO14: =IFERROR(IF(INDEX('Player Pool'!$D$2:$D$8725,MATCH($AN14,'Player Pool'!$Z$2:$Z$8725,0))="","",INDEX('Player Pool'!$D$2:$D$8725,MATCH($AN14,'Player Pool'!$Z$2:$Z$8725,0))),"") | AP14: =IFERROR(IF(INDEX('Player Pool'!$E$2:$E$8725,MATCH($AN14,'Player Pool'!$Z$2:$Z$8725,0))="","",INDEX('Player Pool'!$E$2:$E$8725,MATCH($AN14,'Player Pool'!$Z$2:$Z$8725,0))),"") | AQ14: =IFERROR(IF($AN14="","",IF(ISNUMBER(IFERROR(INDEX(Rosters!$I$2:$I$516,MATCH(INDEX('Player Pool'!$V$2:$V$8725,MATCH($AN14,'Player Pool'!$Z$2:$Z$8725,0)),Rosters!$W$2:$W$516,0)),"")),IFERROR(INDEX(Rosters!$I$2:$I$516,MATCH(INDEX('Player Pool'!$V$2:$V$8725,MATCH($AN14,'Player Pool'!$Z$2:$Z$8725,0)),Rosters!$W$2:$W$516,0)),""),INDEX('Player Pool'!$H$2:$H$8725,MATCH($AN14,'Player Pool'!$Z$2:$Z$8725,0)))),"") | AR14: =IFERROR(IF(INDEX('Player Pool'!$I$2:$I$8725,MATCH($AN14,'Player Pool'!$Z$2:$Z$8725,0))="","",INDEX('Player Pool'!$I$2:$I$8725,MATCH($AN14,'Player Pool'!$Z$2:$Z$8725,0))),"") | AS14: =IFERROR(IF(INDEX('Player Pool'!$P$2:$P$8725,MATCH($AN14,'Player Pool'!$Z$2:$Z$8725,0))="","",INDEX('Player Pool'!$P$2:$P$8725,MATCH($AN14,'Player Pool'!$Z$2:$Z$8725,0))),"") | AT14: =IFERROR(IF(INDEX('Player Pool'!$R$2:$R$8725,MATCH($AN14,'Player Pool'!$Z$2:$Z$8725,0))="","",INDEX('Player Pool'!$R$2:$R$8725,MATCH($AN14,'Player Pool'!$Z$2:$Z$8725,0))),"") | AU14: =IFERROR(IF(INDEX('Player Pool'!$U$2:$U$8725,MATCH($AN14,'Player Pool'!$Z$2:$Z$8725,0))="","",INDEX('Player Pool'!$U$2:$U$8725,MATCH($AN14,'Player Pool'!$Z$2:$Z$8725,0))),"") | AV14: =IFERROR(IF($AN14="","",IF(INDEX('Player Pool'!$G$2:$G$8725,MATCH($AN14,'Player Pool'!$Z$2:$Z$8725,0))="FA","FA",IF(INDEX('Player Pool'!$G$2:$G$8725,MATCH($AN14,'Player Pool'!$Z$2:$Z$8725,0))='League Settings'!$B$2,"MINE","TAKEN"))),"")
A15: =IFERROR(IF(INDEX(Rosters!$B$2:$B$516,$S15)="","",INDEX(Rosters!$B$2:$B$516,$S15)),"") | B15: =IFERROR(IF(INDEX(Rosters!$C$2:$C$516,$S15)="","",INDEX(Rosters!$C$2:$C$516,$S15)),"") | C15: =IFERROR(IF(INDEX(Rosters!$D$2:$D$516,$S15)="","",INDEX(Rosters!$D$2:$D$516,$S15)),"") | D15: =IFERROR(IF(INDEX(Rosters!$E$2:$E$516,$S15)="","",INDEX(Rosters!$E$2:$E$516,$S15)),"") | E15: =IFERROR(IF(INDEX(Rosters!$F$2:$F$516,$S15)="","",INDEX(Rosters!$F$2:$F$516,$S15)),"") | F15: =IFERROR(IF(INDEX(Rosters!$G$2:$G$516,$S15)="","",INDEX(Rosters!$G$2:$G$516,$S15)),"") | G15: =IFERROR(IF(INDEX(Rosters!$H$2:$H$516,$S15)="","",INDEX(Rosters!$H$2:$H$516,$S15)),"") | H15: =IFERROR(IF(INDEX(Rosters!$I$2:$I$516,$S15)="","",INDEX(Rosters!$I$2:$I$516,$S15)),"") | I15: =IFERROR(IF(INDEX(Rosters!$J$2:$J$516,$S15)="","",INDEX(Rosters!$J$2:$J$516,$S15)),"") | J15: =IFERROR(IF(INDEX(Rosters!$S$2:$S$516,$S15)="","",INDEX(Rosters!$S$2:$S$516,$S15)),"") | K15: =IFERROR(IF(INDEX(Rosters!$K$2:$K$516,$S15)="","",INDEX(Rosters!$K$2:$K$516,$S15)),"") | L15: =IFERROR(IF(INDEX(Rosters!$T$2:$T$516,$S15)="","",INDEX(Rosters!$T$2:$T$516,$S15)),"") | M15: =IFERROR(IF(INDEX(Rosters!$L$2:$L$516,$S15)="","",INDEX(Rosters!$L$2:$L$516,$S15)),"") | N15: =IFERROR(IF(INDEX(Rosters!$Q$2:$Q$516,$S15)="","",INDEX(Rosters!$Q$2:$Q$516,$S15)),"") | O15: =IFERROR(IF(INDEX(Rosters!$R$2:$R$516,$S15)="","",INDEX(Rosters!$R$2:$R$516,$S15)),"") | P15: =IFERROR(IF(INDEX(Rosters!$N$2:$N$516,$S15)="","",INDEX(Rosters!$N$2:$N$516,$S15)),"") | Q15: =IFERROR(IF(INDEX(Rosters!$O$2:$O$516,$S15)="","",INDEX(Rosters!$O$2:$O$516,$S15)),"") | R15: =IFERROR(IF(INDEX(Rosters!$P$2:$P$516,$S15)="","",INDEX(Rosters!$P$2:$P$516,$S15)),"") | S15: =IFERROR(MATCH('League Settings'!$B$2&"|ACTIVE|"&12,Rosters!$AD$2:$AD$516,0),"") | T15: Cole Hutson (WSH D) | U15: =IFERROR(IF(INDEX('Player Pool'!$D$2:$D$8725,MATCH($T15,'Player Pool'!$Z$2:$Z$8725,0))="","",INDEX('Player Pool'!$D$2:$D$8725,MATCH($T15,'Player Pool'!$Z$2:$Z$8725,0))),"") | V15: =IFERROR(IF(INDEX('Player Pool'!$E$2:$E$8725,MATCH($T15,'Player Pool'!$Z$2:$Z$8725,0))="","",INDEX('Player Pool'!$E$2:$E$8725,MATCH($T15,'Player Pool'!$Z$2:$Z$8725,0))),"") | W15: =IFERROR(IF($T15="","",IF(ISNUMBER(IFERROR(INDEX(Rosters!$I$2:$I$516,MATCH(INDEX('Player Pool'!$V$2:$V$8725,MATCH($T15,'Player Pool'!$Z$2:$Z$8725,0)),Rosters!$W$2:$W$516,0)),"")),IFERROR(INDEX(Rosters!$I$2:$I$516,MATCH(INDEX('Player Pool'!$V$2:$V$8725,MATCH($T15,'Player Pool'!$Z$2:$Z$8725,0)),Rosters!$W$2:$W$516,0)),""),INDEX('Player Pool'!$H$2:$H$8725,MATCH($T15,'Player Pool'!$Z$2:$Z$8725,0)))),"") | X15: =IFERROR(IF(INDEX('Player Pool'!$I$2:$I$8725,MATCH($T15,'Player Pool'!$Z$2:$Z$8725,0))="","",INDEX('Player Pool'!$I$2:$I$8725,MATCH($T15,'Player Pool'!$Z$2:$Z$8725,0))),"") | Y15: =IFERROR(IF(INDEX('Player Pool'!$P$2:$P$8725,MATCH($T15,'Player Pool'!$Z$2:$Z$8725,0))="","",INDEX('Player Pool'!$P$2:$P$8725,MATCH($T15,'Player Pool'!$Z$2:$Z$8725,0))),"") | Z15: =IFERROR(IF(INDEX('Player Pool'!$R$2:$R$8725,MATCH($T15,'Player Pool'!$Z$2:$Z$8725,0))="","",INDEX('Player Pool'!$R$2:$R$8725,MATCH($T15,'Player Pool'!$Z$2:$Z$8725,0))),"") | AA15: =IFERROR(IF(INDEX('Player Pool'!$U$2:$U$8725,MATCH($T15,'Player Pool'!$Z$2:$Z$8725,0))="","",INDEX('Player Pool'!$U$2:$U$8725,MATCH($T15,'Player Pool'!$Z$2:$Z$8725,0))),"") | AB15: =IFERROR(IF($T15="","",IF(INDEX('Player Pool'!$G$2:$G$8725,MATCH($T15,'Player Pool'!$Z$2:$Z$8725,0))="FA","FA",IF(INDEX('Player Pool'!$G$2:$G$8725,MATCH($T15,'Player Pool'!$Z$2:$Z$8725,0))='League Settings'!$B$2,"MINE","TAKEN"))),"") | AD15: Cole Hutson (WSH D) | AE15: =IFERROR(IF(INDEX('Player Pool'!$D$2:$D$8725,MATCH($AD15,'Player Pool'!$Z$2:$Z$8725,0))="","",INDEX('Player Pool'!$D$2:$D$8725,MATCH($AD15,'Player Pool'!$Z$2:$Z$8725,0))),"") | AF15: =IFERROR(IF(INDEX('Player Pool'!$E$2:$E$8725,MATCH($AD15,'Player Pool'!$Z$2:$Z$8725,0))="","",INDEX('Player Pool'!$E$2:$E$8725,MATCH($AD15,'Player Pool'!$Z$2:$Z$8725,0))),"") | AG15: =IFERROR(IF($AD15="","",IF(ISNUMBER(IFERROR(INDEX(Rosters!$I$2:$I$516,MATCH(INDEX('Player Pool'!$V$2:$V$8725,MATCH($AD15,'Player Pool'!$Z$2:$Z$8725,0)),Rosters!$W$2:$W$516,0)),"")),IFERROR(INDEX(Rosters!$I$2:$I$516,MATCH(INDEX('Player Pool'!$V$2:$V$8725,MATCH($AD15,'Player Pool'!$Z$2:$Z$8725,0)),Rosters!$W$2:$W$516,0)),""),INDEX('Player Pool'!$H$2:$H$8725,MATCH($AD15,'Player Pool'!$Z$2:$Z$8725,0)))),"") | AH15: =IFERROR(IF(INDEX('Player Pool'!$I$2:$I$8725,MATCH($AD15,'Player Pool'!$Z$2:$Z$8725,0))="","",INDEX('Player Pool'!$I$2:$I$8725,MATCH($AD15,'Player Pool'!$Z$2:$Z$8725,0))),"") | AI15: =IFERROR(IF(INDEX('Player Pool'!$P$2:$P$8725,MATCH($AD15,'Player Pool'!$Z$2:$Z$8725,0))="","",INDEX('Player Pool'!$P$2:$P$8725,MATCH($AD15,'Player Pool'!$Z$2:$Z$8725,0))),"") | AJ15: =IFERROR(IF(INDEX('Player Pool'!$R$2:$R$8725,MATCH($AD15,'Player Pool'!$Z$2:$Z$8725,0))="","",INDEX('Player Pool'!$R$2:$R$8725,MATCH($AD15,'Player Pool'!$Z$2:$Z$8725,0))),"") | AK15: =IFERROR(IF(INDEX('Player Pool'!$U$2:$U$8725,MATCH($AD15,'Player Pool'!$Z$2:$Z$8725,0))="","",INDEX('Player Pool'!$U$2:$U$8725,MATCH($AD15,'Player Pool'!$Z$2:$Z$8725,0))),"") | AL15: =IFERROR(IF($AD15="","",IF(INDEX('Player Pool'!$G$2:$G$8725,MATCH($AD15,'Player Pool'!$Z$2:$Z$8725,0))="FA","FA",IF(INDEX('Player Pool'!$G$2:$G$8725,MATCH($AD15,'Player Pool'!$Z$2:$Z$8725,0))='League Settings'!$B$2,"MINE","TAKEN"))),"") | AN15: Cole Hutson (WSH D) | AO15: =IFERROR(IF(INDEX('Player Pool'!$D$2:$D$8725,MATCH($AN15,'Player Pool'!$Z$2:$Z$8725,0))="","",INDEX('Player Pool'!$D$2:$D$8725,MATCH($AN15,'Player Pool'!$Z$2:$Z$8725,0))),"") | AP15: =IFERROR(IF(INDEX('Player Pool'!$E$2:$E$8725,MATCH($AN15,'Player Pool'!$Z$2:$Z$8725,0))="","",INDEX('Player Pool'!$E$2:$E$8725,MATCH($AN15,'Player Pool'!$Z$2:$Z$8725,0))),"") | AQ15: =IFERROR(IF($AN15="","",IF(ISNUMBER(IFERROR(INDEX(Rosters!$I$2:$I$516,MATCH(INDEX('Player Pool'!$V$2:$V$8725,MATCH($AN15,'Player Pool'!$Z$2:$Z$8725,0)),Rosters!$W$2:$W$516,0)),"")),IFERROR(INDEX(Rosters!$I$2:$I$516,MATCH(INDEX('Player Pool'!$V$2:$V$8725,MATCH($AN15,'Player Pool'!$Z$2:$Z$8725,0)),Rosters!$W$2:$W$516,0)),""),INDEX('Player Pool'!$H$2:$H$8725,MATCH($AN15,'Player Pool'!$Z$2:$Z$8725,0)))),"") | AR15: =IFERROR(IF(INDEX('Player Pool'!$I$2:$I$8725,MATCH($AN15,'Player Pool'!$Z$2:$Z$8725,0))="","",INDEX('Player Pool'!$I$2:$I$8725,MATCH($AN15,'Player Pool'!$Z$2:$Z$8725,0))),"") | AS15: =IFERROR(IF(INDEX('Player Pool'!$P$2:$P$8725,MATCH($AN15,'Player Pool'!$Z$2:$Z$8725,0))="","",INDEX('Player Pool'!$P$2:$P$8725,MATCH($AN15,'Player Pool'!$Z$2:$Z$8725,0))),"") | AT15: =IFERROR(IF(INDEX('Player Pool'!$R$2:$R$8725,MATCH($AN15,'Player Pool'!$Z$2:$Z$8725,0))="","",INDEX('Player Pool'!$R$2:$R$8725,MATCH($AN15,'Player Pool'!$Z$2:$Z$8725,0))),"") | AU15: =IFERROR(IF(INDEX('Player Pool'!$U$2:$U$8725,MATCH($AN15,'Player Pool'!$Z$2:$Z$8725,0))="","",INDEX('Player Pool'!$U$2:$U$8725,MATCH($AN15,'Player Pool'!$Z$2:$Z$8725,0))),"") | AV15: =IFERROR(IF($AN15="","",IF(INDEX('Player Pool'!$G$2:$G$8725,MATCH($AN15,'Player Pool'!$Z$2:$Z$8725,0))="FA","FA",IF(INDEX('Player Pool'!$G$2:$G$8725,MATCH($AN15,'Player Pool'!$Z$2:$Z$8725,0))='League Settings'!$B$2,"MINE","TAKEN"))),"")
A16: =IFERROR(IF(INDEX(Rosters!$B$2:$B$516,$S16)="","",INDEX(Rosters!$B$2:$B$516,$S16)),"") | B16: =IFERROR(IF(INDEX(Rosters!$C$2:$C$516,$S16)="","",INDEX(Rosters!$C$2:$C$516,$S16)),"") | C16: =IFERROR(IF(INDEX(Rosters!$D$2:$D$516,$S16)="","",INDEX(Rosters!$D$2:$D$516,$S16)),"") | D16: =IFERROR(IF(INDEX(Rosters!$E$2:$E$516,$S16)="","",INDEX(Rosters!$E$2:$E$516,$S16)),"") | E16: =IFERROR(IF(INDEX(Rosters!$F$2:$F$516,$S16)="","",INDEX(Rosters!$F$2:$F$516,$S16)),"") | F16: =IFERROR(IF(INDEX(Rosters!$G$2:$G$516,$S16)="","",INDEX(Rosters!$G$2:$G$516,$S16)),"") | G16: =IFERROR(IF(INDEX(Rosters!$H$2:$H$516,$S16)="","",INDEX(Rosters!$H$2:$H$516,$S16)),"") | H16: =IFERROR(IF(INDEX(Rosters!$I$2:$I$516,$S16)="","",INDEX(Rosters!$I$2:$I$516,$S16)),"") | I16: =IFERROR(IF(INDEX(Rosters!$J$2:$J$516,$S16)="","",INDEX(Rosters!$J$2:$J$516,$S16)),"") | J16: =IFERROR(IF(INDEX(Rosters!$S$2:$S$516,$S16)="","",INDEX(Rosters!$S$2:$S$516,$S16)),"") | K16: =IFERROR(IF(INDEX(Rosters!$K$2:$K$516,$S16)="","",INDEX(Rosters!$K$2:$K$516,$S16)),"") | L16: =IFERROR(IF(INDEX(Rosters!$T$2:$T$516,$S16)="","",INDEX(Rosters!$T$2:$T$516,$S16)),"") | M16: =IFERROR(IF(INDEX(Rosters!$L$2:$L$516,$S16)="","",INDEX(Rosters!$L$2:$L$516,$S16)),"") | N16: =IFERROR(IF(INDEX(Rosters!$Q$2:$Q$516,$S16)="","",INDEX(Rosters!$Q$2:$Q$516,$S16)),"") | O16: =IFERROR(IF(INDEX(Rosters!$R$2:$R$516,$S16)="","",INDEX(Rosters!$R$2:$R$516,$S16)),"") | P16: =IFERROR(IF(INDEX(Rosters!$N$2:$N$516,$S16)="","",INDEX(Rosters!$N$2:$N$516,$S16)),"") | Q16: =IFERROR(IF(INDEX(Rosters!$O$2:$O$516,$S16)="","",INDEX(Rosters!$O$2:$O$516,$S16)),"") | R16: =IFERROR(IF(INDEX(Rosters!$P$2:$P$516,$S16)="","",INDEX(Rosters!$P$2:$P$516,$S16)),"") | S16: =IFERROR(MATCH('League Settings'!$B$2&"|ACTIVE|"&13,Rosters!$AD$2:$AD$516,0),"") | T16: Jamie Drysdale (PHI D) | U16: =IFERROR(IF(INDEX('Player Pool'!$D$2:$D$8725,MATCH($T16,'Player Pool'!$Z$2:$Z$8725,0))="","",INDEX('Player Pool'!$D$2:$D$8725,MATCH($T16,'Player Pool'!$Z$2:$Z$8725,0))),"") | V16: =IFERROR(IF(INDEX('Player Pool'!$E$2:$E$8725,MATCH($T16,'Player Pool'!$Z$2:$Z$8725,0))="","",INDEX('Player Pool'!$E$2:$E$8725,MATCH($T16,'Player Pool'!$Z$2:$Z$8725,0))),"") | W16: =IFERROR(IF($T16="","",IF(ISNUMBER(IFERROR(INDEX(Rosters!$I$2:$I$516,MATCH(INDEX('Player Pool'!$V$2:$V$8725,MATCH($T16,'Player Pool'!$Z$2:$Z$8725,0)),Rosters!$W$2:$W$516,0)),"")),IFERROR(INDEX(Rosters!$I$2:$I$516,MATCH(INDEX('Player Pool'!$V$2:$V$8725,MATCH($T16,'Player Pool'!$Z$2:$Z$8725,0)),Rosters!$W$2:$W$516,0)),""),INDEX('Player Pool'!$H$2:$H$8725,MATCH($T16,'Player Pool'!$Z$2:$Z$8725,0)))),"") | X16: =IFERROR(IF(INDEX('Player Pool'!$I$2:$I$8725,MATCH($T16,'Player Pool'!$Z$2:$Z$8725,0))="","",INDEX('Player Pool'!$I$2:$I$8725,MATCH($T16,'Player Pool'!$Z$2:$Z$8725,0))),"") | Y16: =IFERROR(IF(INDEX('Player Pool'!$P$2:$P$8725,MATCH($T16,'Player Pool'!$Z$2:$Z$8725,0))="","",INDEX('Player Pool'!$P$2:$P$8725,MATCH($T16,'Player Pool'!$Z$2:$Z$8725,0))),"") | Z16: =IFERROR(IF(INDEX('Player Pool'!$R$2:$R$8725,MATCH($T16,'Player Pool'!$Z$2:$Z$8725,0))="","",INDEX('Player Pool'!$R$2:$R$8725,MATCH($T16,'Player Pool'!$Z$2:$Z$8725,0))),"") | AA16: =IFERROR(IF(INDEX('Player Pool'!$U$2:$U$8725,MATCH($T16,'Player Pool'!$Z$2:$Z$8725,0))="","",INDEX('Player Pool'!$U$2:$U$8725,MATCH($T16,'Player Pool'!$Z$2:$Z$8725,0))),"") | AB16: =IFERROR(IF($T16="","",IF(INDEX('Player Pool'!$G$2:$G$8725,MATCH($T16,'Player Pool'!$Z$2:$Z$8725,0))="FA","FA",IF(INDEX('Player Pool'!$G$2:$G$8725,MATCH($T16,'Player Pool'!$Z$2:$Z$8725,0))='League Settings'!$B$2,"MINE","TAKEN"))),"") | AD16: Jamie Drysdale (PHI D) | AE16: =IFERROR(IF(INDEX('Player Pool'!$D$2:$D$8725,MATCH($AD16,'Player Pool'!$Z$2:$Z$8725,0))="","",INDEX('Player Pool'!$D$2:$D$8725,MATCH($AD16,'Player Pool'!$Z$2:$Z$8725,0))),"") | AF16: =IFERROR(IF(INDEX('Player Pool'!$E$2:$E$8725,MATCH($AD16,'Player Pool'!$Z$2:$Z$8725,0))="","",INDEX('Player Pool'!$E$2:$E$8725,MATCH($AD16,'Player Pool'!$Z$2:$Z$8725,0))),"") | AG16: =IFERROR(IF($AD16="","",IF(ISNUMBER(IFERROR(INDEX(Rosters!$I$2:$I$516,MATCH(INDEX('Player Pool'!$V$2:$V$8725,MATCH($AD16,'Player Pool'!$Z$2:$Z$8725,0)),Rosters!$W$2:$W$516,0)),"")),IFERROR(INDEX(Rosters!$I$2:$I$516,MATCH(INDEX('Player Pool'!$V$2:$V$8725,MATCH($AD16,'Player Pool'!$Z$2:$Z$8725,0)),Rosters!$W$2:$W$516,0)),""),INDEX('Player Pool'!$H$2:$H$8725,MATCH($AD16,'Player Pool'!$Z$2:$Z$8725,0)))),"") | AH16: =IFERROR(IF(INDEX('Player Pool'!$I$2:$I$8725,MATCH($AD16,'Player Pool'!$Z$2:$Z$8725,0))="","",INDEX('Player Pool'!$I$2:$I$8725,MATCH($AD16,'Player Pool'!$Z$2:$Z$8725,0))),"") | AI16: =IFERROR(IF(INDEX('Player Pool'!$P$2:$P$8725,MATCH($AD16,'Player Pool'!$Z$2:$Z$8725,0))="","",INDEX('Player Pool'!$P$2:$P$8725,MATCH($AD16,'Player Pool'!$Z$2:$Z$8725,0))),"") | AJ16: =IFERROR(IF(INDEX('Player Pool'!$R$2:$R$8725,MATCH($AD16,'Player Pool'!$Z$2:$Z$8725,0))="","",INDEX('Player Pool'!$R$2:$R$8725,MATCH($AD16,'Player Pool'!$Z$2:$Z$8725,0))),"") | AK16: =IFERROR(IF(INDEX('Player Pool'!$U$2:$U$8725,MATCH($AD16,'Player Pool'!$Z$2:$Z$8725,0))="","",INDEX('Player Pool'!$U$2:$U$8725,MATCH($AD16,'Player Pool'!$Z$2:$Z$8725,0))),"") | AL16: =IFERROR(IF($AD16="","",IF(INDEX('Player Pool'!$G$2:$G$8725,MATCH($AD16,'Player Pool'!$Z$2:$Z$8725,0))="FA","FA",IF(INDEX('Player Pool'!$G$2:$G$8725,MATCH($AD16,'Player Pool'!$Z$2:$Z$8725,0))='League Settings'!$B$2,"MINE","TAKEN"))),"") | AN16: Jamie Drysdale (PHI D) | AO16: =IFERROR(IF(INDEX('Player Pool'!$D$2:$D$8725,MATCH($AN16,'Player Pool'!$Z$2:$Z$8725,0))="","",INDEX('Player Pool'!$D$2:$D$8725,MATCH($AN16,'Player Pool'!$Z$2:$Z$8725,0))),"") | AP16: =IFERROR(IF(INDEX('Player Pool'!$E$2:$E$8725,MATCH($AN16,'Player Pool'!$Z$2:$Z$8725,0))="","",INDEX('Player Pool'!$E$2:$E$8725,MATCH($AN16,'Player Pool'!$Z$2:$Z$8725,0))),"") | AQ16: =IFERROR(IF($AN16="","",IF(ISNUMBER(IFERROR(INDEX(Rosters!$I$2:$I$516,MATCH(INDEX('Player Pool'!$V$2:$V$8725,MATCH($AN16,'Player Pool'!$Z$2:$Z$8725,0)),Rosters!$W$2:$W$516,0)),"")),IFERROR(INDEX(Rosters!$I$2:$I$516,MATCH(INDEX('Player Pool'!$V$2:$V$8725,MATCH($AN16,'Player Pool'!$Z$2:$Z$8725,0)),Rosters!$W$2:$W$516,0)),""),INDEX('Player Pool'!$H$2:$H$8725,MATCH($AN16,'Player Pool'!$Z$2:$Z$8725,0)))),"") | AR16: =IFERROR(IF(INDEX('Player Pool'!$I$2:$I$8725,MATCH($AN16,'Player Pool'!$Z$2:$Z$8725,0))="","",INDEX('Player Pool'!$I$2:$I$8725,MATCH($AN16,'Player Pool'!$Z$2:$Z$8725,0))),"") | AS16: =IFERROR(IF(INDEX('Player Pool'!$P$2:$P$8725,MATCH($AN16,'Player Pool'!$Z$2:$Z$8725,0))="","",INDEX('Player Pool'!$P$2:$P$8725,MATCH($AN16,'Player Pool'!$Z$2:$Z$8725,0))),"") | AT16: =IFERROR(IF(INDEX('Player Pool'!$R$2:$R$8725,MATCH($AN16,'Player Pool'!$Z$2:$Z$8725,0))="","",INDEX('Player Pool'!$R$2:$R$8725,MATCH($AN16,'Player Pool'!$Z$2:$Z$8725,0))),"") | AU16: =IFERROR(IF(INDEX('Player Pool'!$U$2:$U$8725,MATCH($AN16,'Player Pool'!$Z$2:$Z$8725,0))="","",INDEX('Player Pool'!$U$2:$U$8725,MATCH($AN16,'Player Pool'!$Z$2:$Z$8725,0))),"") | AV16: =IFERROR(IF($AN16="","",IF(INDEX('Player Pool'!$G$2:$G$8725,MATCH($AN16,'Player Pool'!$Z$2:$Z$8725,0))="FA","FA",IF(INDEX('Player Pool'!$G$2:$G$8725,MATCH($AN16,'Player Pool'!$Z$2:$Z$8725,0))='League Settings'!$B$2,"MINE","TAKEN"))),"")
A17: =IFERROR(IF(INDEX(Rosters!$B$2:$B$516,$S17)="","",INDEX(Rosters!$B$2:$B$516,$S17)),"") | B17: =IFERROR(IF(INDEX(Rosters!$C$2:$C$516,$S17)="","",INDEX(Rosters!$C$2:$C$516,$S17)),"") | C17: =IFERROR(IF(INDEX(Rosters!$D$2:$D$516,$S17)="","",INDEX(Rosters!$D$2:$D$516,$S17)),"") | D17: =IFERROR(IF(INDEX(Rosters!$E$2:$E$516,$S17)="","",INDEX(Rosters!$E$2:$E$516,$S17)),"") | E17: =IFERROR(IF(INDEX(Rosters!$F$2:$F$516,$S17)="","",INDEX(Rosters!$F$2:$F$516,$S17)),"") | F17: =IFERROR(IF(INDEX(Rosters!$G$2:$G$516,$S17)="","",INDEX(Rosters!$G$2:$G$516,$S17)),"") | G17: =IFERROR(IF(INDEX(Rosters!$H$2:$H$516,$S17)="","",INDEX(Rosters!$H$2:$H$516,$S17)),"") | H17: =IFERROR(IF(INDEX(Rosters!$I$2:$I$516,$S17)="","",INDEX(Rosters!$I$2:$I$516,$S17)),"") | I17: =IFERROR(IF(INDEX(Rosters!$J$2:$J$516,$S17)="","",INDEX(Rosters!$J$2:$J$516,$S17)),"") | J17: =IFERROR(IF(INDEX(Rosters!$S$2:$S$516,$S17)="","",INDEX(Rosters!$S$2:$S$516,$S17)),"") | K17: =IFERROR(IF(INDEX(Rosters!$K$2:$K$516,$S17)="","",INDEX(Rosters!$K$2:$K$516,$S17)),"") | L17: =IFERROR(IF(INDEX(Rosters!$T$2:$T$516,$S17)="","",INDEX(Rosters!$T$2:$T$516,$S17)),"") | M17: =IFERROR(IF(INDEX(Rosters!$L$2:$L$516,$S17)="","",INDEX(Rosters!$L$2:$L$516,$S17)),"") | N17: =IFERROR(IF(INDEX(Rosters!$Q$2:$Q$516,$S17)="","",INDEX(Rosters!$Q$2:$Q$516,$S17)),"") | O17: =IFERROR(IF(INDEX(Rosters!$R$2:$R$516,$S17)="","",INDEX(Rosters!$R$2:$R$516,$S17)),"") | P17: =IFERROR(IF(INDEX(Rosters!$N$2:$N$516,$S17)="","",INDEX(Rosters!$N$2:$N$516,$S17)),"") | Q17: =IFERROR(IF(INDEX(Rosters!$O$2:$O$516,$S17)="","",INDEX(Rosters!$O$2:$O$516,$S17)),"") | R17: =IFERROR(IF(INDEX(Rosters!$P$2:$P$516,$S17)="","",INDEX(Rosters!$P$2:$P$516,$S17)),"") | S17: =IFERROR(MATCH('League Settings'!$B$2&"|ACTIVE|"&14,Rosters!$AD$2:$AD$516,0),"") | T17: Louis Crevier (BUF D) | U17: =IFERROR(IF(INDEX('Player Pool'!$D$2:$D$8725,MATCH($T17,'Player Pool'!$Z$2:$Z$8725,0))="","",INDEX('Player Pool'!$D$2:$D$8725,MATCH($T17,'Player Pool'!$Z$2:$Z$8725,0))),"") | V17: =IFERROR(IF(INDEX('Player Pool'!$E$2:$E$8725,MATCH($T17,'Player Pool'!$Z$2:$Z$8725,0))="","",INDEX('Player Pool'!$E$2:$E$8725,MATCH($T17,'Player Pool'!$Z$2:$Z$8725,0))),"") | W17: =IFERROR(IF($T17="","",IF(ISNUMBER(IFERROR(INDEX(Rosters!$I$2:$I$516,MATCH(INDEX('Player Pool'!$V$2:$V$8725,MATCH($T17,'Player Pool'!$Z$2:$Z$8725,0)),Rosters!$W$2:$W$516,0)),"")),IFERROR(INDEX(Rosters!$I$2:$I$516,MATCH(INDEX('Player Pool'!$V$2:$V$8725,MATCH($T17,'Player Pool'!$Z$2:$Z$8725,0)),Rosters!$W$2:$W$516,0)),""),INDEX('Player Pool'!$H$2:$H$8725,MATCH($T17,'Player Pool'!$Z$2:$Z$8725,0)))),"") | X17: =IFERROR(IF(INDEX('Player Pool'!$I$2:$I$8725,MATCH($T17,'Player Pool'!$Z$2:$Z$8725,0))="","",INDEX('Player Pool'!$I$2:$I$8725,MATCH($T17,'Player Pool'!$Z$2:$Z$8725,0))),"") | Y17: =IFERROR(IF(INDEX('Player Pool'!$P$2:$P$8725,MATCH($T17,'Player Pool'!$Z$2:$Z$8725,0))="","",INDEX('Player Pool'!$P$2:$P$8725,MATCH($T17,'Player Pool'!$Z$2:$Z$8725,0))),"") | Z17: =IFERROR(IF(INDEX('Player Pool'!$R$2:$R$8725,MATCH($T17,'Player Pool'!$Z$2:$Z$8725,0))="","",INDEX('Player Pool'!$R$2:$R$8725,MATCH($T17,'Player Pool'!$Z$2:$Z$8725,0))),"") | AA17: =IFERROR(IF(INDEX('Player Pool'!$U$2:$U$8725,MATCH($T17,'Player Pool'!$Z$2:$Z$8725,0))="","",INDEX('Player Pool'!$U$2:$U$8725,MATCH($T17,'Player Pool'!$Z$2:$Z$8725,0))),"") | AB17: =IFERROR(IF($T17="","",IF(INDEX('Player Pool'!$G$2:$G$8725,MATCH($T17,'Player Pool'!$Z$2:$Z$8725,0))="FA","FA",IF(INDEX('Player Pool'!$G$2:$G$8725,MATCH($T17,'Player Pool'!$Z$2:$Z$8725,0))='League Settings'!$B$2,"MINE","TAKEN"))),"") | AD17: Louis Crevier (BUF D) | AE17: =IFERROR(IF(INDEX('Player Pool'!$D$2:$D$8725,MATCH($AD17,'Player Pool'!$Z$2:$Z$8725,0))="","",INDEX('Player Pool'!$D$2:$D$8725,MATCH($AD17,'Player Pool'!$Z$2:$Z$8725,0))),"") | AF17: =IFERROR(IF(INDEX('Player Pool'!$E$2:$E$8725,MATCH($AD17,'Player Pool'!$Z$2:$Z$8725,0))="","",INDEX('Player Pool'!$E$2:$E$8725,MATCH($AD17,'Player Pool'!$Z$2:$Z$8725,0))),"") | AG17: =IFERROR(IF($AD17="","",IF(ISNUMBER(IFERROR(INDEX(Rosters!$I$2:$I$516,MATCH(INDEX('Player Pool'!$V$2:$V$8725,MATCH($AD17,'Player Pool'!$Z$2:$Z$8725,0)),Rosters!$W$2:$W$516,0)),"")),IFERROR(INDEX(Rosters!$I$2:$I$516,MATCH(INDEX('Player Pool'!$V$2:$V$8725,MATCH($AD17,'Player Pool'!$Z$2:$Z$8725,0)),Rosters!$W$2:$W$516,0)),""),INDEX('Player Pool'!$H$2:$H$8725,MATCH($AD17,'Player Pool'!$Z$2:$Z$8725,0)))),"") | AH17: =IFERROR(IF(INDEX('Player Pool'!$I$2:$I$8725,MATCH($AD17,'Player Pool'!$Z$2:$Z$8725,0))="","",INDEX('Player Pool'!$I$2:$I$8725,MATCH($AD17,'Player Pool'!$Z$2:$Z$8725,0))),"") | AI17: =IFERROR(IF(INDEX('Player Pool'!$P$2:$P$8725,MATCH($AD17,'Player Pool'!$Z$2:$Z$8725,0))="","",INDEX('Player Pool'!$P$2:$P$8725,MATCH($AD17,'Player Pool'!$Z$2:$Z$8725,0))),"") | AJ17: =IFERROR(IF(INDEX('Player Pool'!$R$2:$R$8725,MATCH($AD17,'Player Pool'!$Z$2:$Z$8725,0))="","",INDEX('Player Pool'!$R$2:$R$8725,MATCH($AD17,'Player Pool'!$Z$2:$Z$8725,0))),"") | AK17: =IFERROR(IF(INDEX('Player Pool'!$U$2:$U$8725,MATCH($AD17,'Player Pool'!$Z$2:$Z$8725,0))="","",INDEX('Player Pool'!$U$2:$U$8725,MATCH($AD17,'Player Pool'!$Z$2:$Z$8725,0))),"") | AL17: =IFERROR(IF($AD17="","",IF(INDEX('Player Pool'!$G$2:$G$8725,MATCH($AD17,'Player Pool'!$Z$2:$Z$8725,0))="FA","FA",IF(INDEX('Player Pool'!$G$2:$G$8725,MATCH($AD17,'Player Pool'!$Z$2:$Z$8725,0))='League Settings'!$B$2,"MINE","TAKEN"))),"") | AN17: Louis Crevier (BUF D) | AO17: =IFERROR(IF(INDEX('Player Pool'!$D$2:$D$8725,MATCH($AN17,'Player Pool'!$Z$2:$Z$8725,0))="","",INDEX('Player Pool'!$D$2:$D$8725,MATCH($AN17,'Player Pool'!$Z$2:$Z$8725,0))),"") | AP17: =IFERROR(IF(INDEX('Player Pool'!$E$2:$E$8725,MATCH($AN17,'Player Pool'!$Z$2:$Z$8725,0))="","",INDEX('Player Pool'!$E$2:$E$8725,MATCH($AN17,'Player Pool'!$Z$2:$Z$8725,0))),"") | AQ17: =IFERROR(IF($AN17="","",IF(ISNUMBER(IFERROR(INDEX(Rosters!$I$2:$I$516,MATCH(INDEX('Player Pool'!$V$2:$V$8725,MATCH($AN17,'Player Pool'!$Z$2:$Z$8725,0)),Rosters!$W$2:$W$516,0)),"")),IFERROR(INDEX(Rosters!$I$2:$I$516,MATCH(INDEX('Player Pool'!$V$2:$V$8725,MATCH($AN17,'Player Pool'!$Z$2:$Z$8725,0)),Rosters!$W$2:$W$516,0)),""),INDEX('Player Pool'!$H$2:$H$8725,MATCH($AN17,'Player Pool'!$Z$2:$Z$8725,0)))),"") | AR17: =IFERROR(IF(INDEX('Player Pool'!$I$2:$I$8725,MATCH($AN17,'Player Pool'!$Z$2:$Z$8725,0))="","",INDEX('Player Pool'!$I$2:$I$8725,MATCH($AN17,'Player Pool'!$Z$2:$Z$8725,0))),"") | AS17: =IFERROR(IF(INDEX('Player Pool'!$P$2:$P$8725,MATCH($AN17,'Player Pool'!$Z$2:$Z$8725,0))="","",INDEX('Player Pool'!$P$2:$P$8725,MATCH($AN17,'Player Pool'!$Z$2:$Z$8725,0))),"") | AT17: =IFERROR(IF(INDEX('Player Pool'!$R$2:$R$8725,MATCH($AN17,'Player Pool'!$Z$2:$Z$8725,0))="","",INDEX('Player Pool'!$R$2:$R$8725,MATCH($AN17,'Player Pool'!$Z$2:$Z$8725,0))),"") | AU17: =IFERROR(IF(INDEX('Player Pool'!$U$2:$U$8725,MATCH($AN17,'Player Pool'!$Z$2:$Z$8725,0))="","",INDEX('Player Pool'!$U$2:$U$8725,MATCH($AN17,'Player Pool'!$Z$2:$Z$8725,0))),"") | AV17: =IFERROR(IF($AN17="","",IF(INDEX('Player Pool'!$G$2:$G$8725,MATCH($AN17,'Player Pool'!$Z$2:$Z$8725,0))="FA","FA",IF(INDEX('Player Pool'!$G$2:$G$8725,MATCH($AN17,'Player Pool'!$Z$2:$Z$8725,0))='League Settings'!$B$2,"MINE","TAKEN"))),"")
A18: =IFERROR(IF(INDEX(Rosters!$B$2:$B$516,$S18)="","",INDEX(Rosters!$B$2:$B$516,$S18)),"") | B18: =IFERROR(IF(INDEX(Rosters!$C$2:$C$516,$S18)="","",INDEX(Rosters!$C$2:$C$516,$S18)),"") | C18: =IFERROR(IF(INDEX(Rosters!$D$2:$D$516,$S18)="","",INDEX(Rosters!$D$2:$D$516,$S18)),"") | D18: =IFERROR(IF(INDEX(Rosters!$E$2:$E$516,$S18)="","",INDEX(Rosters!$E$2:$E$516,$S18)),"") | E18: =IFERROR(IF(INDEX(Rosters!$F$2:$F$516,$S18)="","",INDEX(Rosters!$F$2:$F$516,$S18)),"") | F18: =IFERROR(IF(INDEX(Rosters!$G$2:$G$516,$S18)="","",INDEX(Rosters!$G$2:$G$516,$S18)),"") | G18: =IFERROR(IF(INDEX(Rosters!$H$2:$H$516,$S18)="","",INDEX(Rosters!$H$2:$H$516,$S18)),"") | H18: =IFERROR(IF(INDEX(Rosters!$I$2:$I$516,$S18)="","",INDEX(Rosters!$I$2:$I$516,$S18)),"") | I18: =IFERROR(IF(INDEX(Rosters!$J$2:$J$516,$S18)="","",INDEX(Rosters!$J$2:$J$516,$S18)),"") | J18: =IFERROR(IF(INDEX(Rosters!$S$2:$S$516,$S18)="","",INDEX(Rosters!$S$2:$S$516,$S18)),"") | K18: =IFERROR(IF(INDEX(Rosters!$K$2:$K$516,$S18)="","",INDEX(Rosters!$K$2:$K$516,$S18)),"") | L18: =IFERROR(IF(INDEX(Rosters!$T$2:$T$516,$S18)="","",INDEX(Rosters!$T$2:$T$516,$S18)),"") | M18: =IFERROR(IF(INDEX(Rosters!$L$2:$L$516,$S18)="","",INDEX(Rosters!$L$2:$L$516,$S18)),"") | N18: =IFERROR(IF(INDEX(Rosters!$Q$2:$Q$516,$S18)="","",INDEX(Rosters!$Q$2:$Q$516,$S18)),"") | O18: =IFERROR(IF(INDEX(Rosters!$R$2:$R$516,$S18)="","",INDEX(Rosters!$R$2:$R$516,$S18)),"") | P18: =IFERROR(IF(INDEX(Rosters!$N$2:$N$516,$S18)="","",INDEX(Rosters!$N$2:$N$516,$S18)),"") | Q18: =IFERROR(IF(INDEX(Rosters!$O$2:$O$516,$S18)="","",INDEX(Rosters!$O$2:$O$516,$S18)),"") | R18: =IFERROR(IF(INDEX(Rosters!$P$2:$P$516,$S18)="","",INDEX(Rosters!$P$2:$P$516,$S18)),"") | S18: =IFERROR(MATCH('League Settings'!$B$2&"|ACTIVE|"&15,Rosters!$AD$2:$AD$516,0),"") | T18: Bobby Brink (MIN RW) | U18: =IFERROR(IF(INDEX('Player Pool'!$D$2:$D$8725,MATCH($T18,'Player Pool'!$Z$2:$Z$8725,0))="","",INDEX('Player Pool'!$D$2:$D$8725,MATCH($T18,'Player Pool'!$Z$2:$Z$8725,0))),"") | V18: =IFERROR(IF(INDEX('Player Pool'!$E$2:$E$8725,MATCH($T18,'Player Pool'!$Z$2:$Z$8725,0))="","",INDEX('Player Pool'!$E$2:$E$8725,MATCH($T18,'Player Pool'!$Z$2:$Z$8725,0))),"") | W18: =IFERROR(IF($T18="","",IF(ISNUMBER(IFERROR(INDEX(Rosters!$I$2:$I$516,MATCH(INDEX('Player Pool'!$V$2:$V$8725,MATCH($T18,'Player Pool'!$Z$2:$Z$8725,0)),Rosters!$W$2:$W$516,0)),"")),IFERROR(INDEX(Rosters!$I$2:$I$516,MATCH(INDEX('Player Pool'!$V$2:$V$8725,MATCH($T18,'Player Pool'!$Z$2:$Z$8725,0)),Rosters!$W$2:$W$516,0)),""),INDEX('Player Pool'!$H$2:$H$8725,MATCH($T18,'Player Pool'!$Z$2:$Z$8725,0)))),"") | X18: =IFERROR(IF(INDEX('Player Pool'!$I$2:$I$8725,MATCH($T18,'Player Pool'!$Z$2:$Z$8725,0))="","",INDEX('Player Pool'!$I$2:$I$8725,MATCH($T18,'Player Pool'!$Z$2:$Z$8725,0))),"") | Y18: =IFERROR(IF(INDEX('Player Pool'!$P$2:$P$8725,MATCH($T18,'Player Pool'!$Z$2:$Z$8725,0))="","",INDEX('Player Pool'!$P$2:$P$8725,MATCH($T18,'Player Pool'!$Z$2:$Z$8725,0))),"") | Z18: =IFERROR(IF(INDEX('Player Pool'!$R$2:$R$8725,MATCH($T18,'Player Pool'!$Z$2:$Z$8725,0))="","",INDEX('Player Pool'!$R$2:$R$8725,MATCH($T18,'Player Pool'!$Z$2:$Z$8725,0))),"") | AA18: =IFERROR(IF(INDEX('Player Pool'!$U$2:$U$8725,MATCH($T18,'Player Pool'!$Z$2:$Z$8725,0))="","",INDEX('Player Pool'!$U$2:$U$8725,MATCH($T18,'Player Pool'!$Z$2:$Z$8725,0))),"") | AB18: =IFERROR(IF($T18="","",IF(INDEX('Player Pool'!$G$2:$G$8725,MATCH($T18,'Player Pool'!$Z$2:$Z$8725,0))="FA","FA",IF(INDEX('Player Pool'!$G$2:$G$8725,MATCH($T18,'Player Pool'!$Z$2:$Z$8725,0))='League Settings'!$B$2,"MINE","TAKEN"))),"") | AD18: Bobby Brink (MIN RW) | AE18: =IFERROR(IF(INDEX('Player Pool'!$D$2:$D$8725,MATCH($AD18,'Player Pool'!$Z$2:$Z$8725,0))="","",INDEX('Player Pool'!$D$2:$D$8725,MATCH($AD18,'Player Pool'!$Z$2:$Z$8725,0))),"") | AF18: =IFERROR(IF(INDEX('Player Pool'!$E$2:$E$8725,MATCH($AD18,'Player Pool'!$Z$2:$Z$8725,0))="","",INDEX('Player Pool'!$E$2:$E$8725,MATCH($AD18,'Player Pool'!$Z$2:$Z$8725,0))),"") | AG18: =IFERROR(IF($AD18="","",IF(ISNUMBER(IFERROR(INDEX(Rosters!$I$2:$I$516,MATCH(INDEX('Player Pool'!$V$2:$V$8725,MATCH($AD18,'Player Pool'!$Z$2:$Z$8725,0)),Rosters!$W$2:$W$516,0)),"")),IFERROR(INDEX(Rosters!$I$2:$I$516,MATCH(INDEX('Player Pool'!$V$2:$V$8725,MATCH($AD18,'Player Pool'!$Z$2:$Z$8725,0)),Rosters!$W$2:$W$516,0)),""),INDEX('Player Pool'!$H$2:$H$8725,MATCH($AD18,'Player Pool'!$Z$2:$Z$8725,0)))),"") | AH18: =IFERROR(IF(INDEX('Player Pool'!$I$2:$I$8725,MATCH($AD18,'Player Pool'!$Z$2:$Z$8725,0))="","",INDEX('Player Pool'!$I$2:$I$8725,MATCH($AD18,'Player Pool'!$Z$2:$Z$8725,0))),"") | AI18: =IFERROR(IF(INDEX('Player Pool'!$P$2:$P$8725,MATCH($AD18,'Player Pool'!$Z$2:$Z$8725,0))="","",INDEX('Player Pool'!$P$2:$P$8725,MATCH($AD18,'Player Pool'!$Z$2:$Z$8725,0))),"") | AJ18: =IFERROR(IF(INDEX('Player Pool'!$R$2:$R$8725,MATCH($AD18,'Player Pool'!$Z$2:$Z$8725,0))="","",INDEX('Player Pool'!$R$2:$R$8725,MATCH($AD18,'Player Pool'!$Z$2:$Z$8725,0))),"") | AK18: =IFERROR(IF(INDEX('Player Pool'!$U$2:$U$8725,MATCH($AD18,'Player Pool'!$Z$2:$Z$8725,0))="","",INDEX('Player Pool'!$U$2:$U$8725,MATCH($AD18,'Player Pool'!$Z$2:$Z$8725,0))),"") | AL18: =IFERROR(IF($AD18="","",IF(INDEX('Player Pool'!$G$2:$G$8725,MATCH($AD18,'Player Pool'!$Z$2:$Z$8725,0))="FA","FA",IF(INDEX('Player Pool'!$G$2:$G$8725,MATCH($AD18,'Player Pool'!$Z$2:$Z$8725,0))='League Settings'!$B$2,"MINE","TAKEN"))),"") | AN18: Bobby Brink (MIN RW) | AO18: =IFERROR(IF(INDEX('Player Pool'!$D$2:$D$8725,MATCH($AN18,'Player Pool'!$Z$2:$Z$8725,0))="","",INDEX('Player Pool'!$D$2:$D$8725,MATCH($AN18,'Player Pool'!$Z$2:$Z$8725,0))),"") | AP18: =IFERROR(IF(INDEX('Player Pool'!$E$2:$E$8725,MATCH($AN18,'Player Pool'!$Z$2:$Z$8725,0))="","",INDEX('Player Pool'!$E$2:$E$8725,MATCH($AN18,'Player Pool'!$Z$2:$Z$8725,0))),"") | AQ18: =IFERROR(IF($AN18="","",IF(ISNUMBER(IFERROR(INDEX(Rosters!$I$2:$I$516,MATCH(INDEX('Player Pool'!$V$2:$V$8725,MATCH($AN18,'Player Pool'!$Z$2:$Z$8725,0)),Rosters!$W$2:$W$516,0)),"")),IFERROR(INDEX(Rosters!$I$2:$I$516,MATCH(INDEX('Player Pool'!$V$2:$V$8725,MATCH($AN18,'Player Pool'!$Z$2:$Z$8725,0)),Rosters!$W$2:$W$516,0)),""),INDEX('Player Pool'!$H$2:$H$8725,MATCH($AN18,'Player Pool'!$Z$2:$Z$8725,0)))),"") | AR18: =IFERROR(IF(INDEX('Player Pool'!$I$2:$I$8725,MATCH($AN18,'Player Pool'!$Z$2:$Z$8725,0))="","",INDEX('Player Pool'!$I$2:$I$8725,MATCH($AN18,'Player Pool'!$Z$2:$Z$8725,0))),"") | AS18: =IFERROR(IF(INDEX('Player Pool'!$P$2:$P$8725,MATCH($AN18,'Player Pool'!$Z$2:$Z$8725,0))="","",INDEX('Player Pool'!$P$2:$P$8725,MATCH($AN18,'Player Pool'!$Z$2:$Z$8725,0))),"") | AT18: =IFERROR(IF(INDEX('Player Pool'!$R$2:$R$8725,MATCH($AN18,'Player Pool'!$Z$2:$Z$8725,0))="","",INDEX('Player Pool'!$R$2:$R$8725,MATCH($AN18,'Player Pool'!$Z$2:$Z$8725,0))),"") | AU18: =IFERROR(IF(INDEX('Player Pool'!$U$2:$U$8725,MATCH($AN18,'Player Pool'!$Z$2:$Z$8725,0))="","",INDEX('Player Pool'!$U$2:$U$8725,MATCH($AN18,'Player Pool'!$Z$2:$Z$8725,0))),"") | AV18: =IFERROR(IF($AN18="","",IF(INDEX('Player Pool'!$G$2:$G$8725,MATCH($AN18,'Player Pool'!$Z$2:$Z$8725,0))="FA","FA",IF(INDEX('Player Pool'!$G$2:$G$8725,MATCH($AN18,'Player Pool'!$Z$2:$Z$8725,0))='League Settings'!$B$2,"MINE","TAKEN"))),"")
A19: =IFERROR(IF(INDEX(Rosters!$B$2:$B$516,$S19)="","",INDEX(Rosters!$B$2:$B$516,$S19)),"") | B19: =IFERROR(IF(INDEX(Rosters!$C$2:$C$516,$S19)="","",INDEX(Rosters!$C$2:$C$516,$S19)),"") | C19: =IFERROR(IF(INDEX(Rosters!$D$2:$D$516,$S19)="","",INDEX(Rosters!$D$2:$D$516,$S19)),"") | D19: =IFERROR(IF(INDEX(Rosters!$E$2:$E$516,$S19)="","",INDEX(Rosters!$E$2:$E$516,$S19)),"") | E19: =IFERROR(IF(INDEX(Rosters!$F$2:$F$516,$S19)="","",INDEX(Rosters!$F$2:$F$516,$S19)),"") | F19: =IFERROR(IF(INDEX(Rosters!$G$2:$G$516,$S19)="","",INDEX(Rosters!$G$2:$G$516,$S19)),"") | G19: =IFERROR(IF(INDEX(Rosters!$H$2:$H$516,$S19)="","",INDEX(Rosters!$H$2:$H$516,$S19)),"") | H19: =IFERROR(IF(INDEX(Rosters!$I$2:$I$516,$S19)="","",INDEX(Rosters!$I$2:$I$516,$S19)),"") | I19: =IFERROR(IF(INDEX(Rosters!$J$2:$J$516,$S19)="","",INDEX(Rosters!$J$2:$J$516,$S19)),"") | J19: =IFERROR(IF(INDEX(Rosters!$S$2:$S$516,$S19)="","",INDEX(Rosters!$S$2:$S$516,$S19)),"") | K19: =IFERROR(IF(INDEX(Rosters!$K$2:$K$516,$S19)="","",INDEX(Rosters!$K$2:$K$516,$S19)),"") | L19: =IFERROR(IF(INDEX(Rosters!$T$2:$T$516,$S19)="","",INDEX(Rosters!$T$2:$T$516,$S19)),"") | M19: =IFERROR(IF(INDEX(Rosters!$L$2:$L$516,$S19)="","",INDEX(Rosters!$L$2:$L$516,$S19)),"") | N19: =IFERROR(IF(INDEX(Rosters!$Q$2:$Q$516,$S19)="","",INDEX(Rosters!$Q$2:$Q$516,$S19)),"") | O19: =IFERROR(IF(INDEX(Rosters!$R$2:$R$516,$S19)="","",INDEX(Rosters!$R$2:$R$516,$S19)),"") | P19: =IFERROR(IF(INDEX(Rosters!$N$2:$N$516,$S19)="","",INDEX(Rosters!$N$2:$N$516,$S19)),"") | Q19: =IFERROR(IF(INDEX(Rosters!$O$2:$O$516,$S19)="","",INDEX(Rosters!$O$2:$O$516,$S19)),"") | R19: =IFERROR(IF(INDEX(Rosters!$P$2:$P$516,$S19)="","",INDEX(Rosters!$P$2:$P$516,$S19)),"") | S19: =IFERROR(MATCH('League Settings'!$B$2&"|ACTIVE|"&16,Rosters!$AD$2:$AD$516,0),"") | T19: Roman Kantserov (CHI RW) | U19: =IFERROR(IF(INDEX('Player Pool'!$D$2:$D$8725,MATCH($T19,'Player Pool'!$Z$2:$Z$8725,0))="","",INDEX('Player Pool'!$D$2:$D$8725,MATCH($T19,'Player Pool'!$Z$2:$Z$8725,0))),"") | V19: =IFERROR(IF(INDEX('Player Pool'!$E$2:$E$8725,MATCH($T19,'Player Pool'!$Z$2:$Z$8725,0))="","",INDEX('Player Pool'!$E$2:$E$8725,MATCH($T19,'Player Pool'!$Z$2:$Z$8725,0))),"") | W19: =IFERROR(IF($T19="","",IF(ISNUMBER(IFERROR(INDEX(Rosters!$I$2:$I$516,MATCH(INDEX('Player Pool'!$V$2:$V$8725,MATCH($T19,'Player Pool'!$Z$2:$Z$8725,0)),Rosters!$W$2:$W$516,0)),"")),IFERROR(INDEX(Rosters!$I$2:$I$516,MATCH(INDEX('Player Pool'!$V$2:$V$8725,MATCH($T19,'Player Pool'!$Z$2:$Z$8725,0)),Rosters!$W$2:$W$516,0)),""),INDEX('Player Pool'!$H$2:$H$8725,MATCH($T19,'Player Pool'!$Z$2:$Z$8725,0)))),"") | X19: =IFERROR(IF(INDEX('Player Pool'!$I$2:$I$8725,MATCH($T19,'Player Pool'!$Z$2:$Z$8725,0))="","",INDEX('Player Pool'!$I$2:$I$8725,MATCH($T19,'Player Pool'!$Z$2:$Z$8725,0))),"") | Y19: =IFERROR(IF(INDEX('Player Pool'!$P$2:$P$8725,MATCH($T19,'Player Pool'!$Z$2:$Z$8725,0))="","",INDEX('Player Pool'!$P$2:$P$8725,MATCH($T19,'Player Pool'!$Z$2:$Z$8725,0))),"") | Z19: =IFERROR(IF(INDEX('Player Pool'!$R$2:$R$8725,MATCH($T19,'Player Pool'!$Z$2:$Z$8725,0))="","",INDEX('Player Pool'!$R$2:$R$8725,MATCH($T19,'Player Pool'!$Z$2:$Z$8725,0))),"") | AA19: =IFERROR(IF(INDEX('Player Pool'!$U$2:$U$8725,MATCH($T19,'Player Pool'!$Z$2:$Z$8725,0))="","",INDEX('Player Pool'!$U$2:$U$8725,MATCH($T19,'Player Pool'!$Z$2:$Z$8725,0))),"") | AB19: =IFERROR(IF($T19="","",IF(INDEX('Player Pool'!$G$2:$G$8725,MATCH($T19,'Player Pool'!$Z$2:$Z$8725,0))="FA","FA",IF(INDEX('Player Pool'!$G$2:$G$8725,MATCH($T19,'Player Pool'!$Z$2:$Z$8725,0))='League Settings'!$B$2,"MINE","TAKEN"))),"") | AD19: Roman Kantserov (CHI RW) | AE19: =IFERROR(IF(INDEX('Player Pool'!$D$2:$D$8725,MATCH($AD19,'Player Pool'!$Z$2:$Z$8725,0))="","",INDEX('Player Pool'!$D$2:$D$8725,MATCH($AD19,'Player Pool'!$Z$2:$Z$8725,0))),"") | AF19: =IFERROR(IF(INDEX('Player Pool'!$E$2:$E$8725,MATCH($AD19,'Player Pool'!$Z$2:$Z$8725,0))="","",INDEX('Player Pool'!$E$2:$E$8725,MATCH($AD19,'Player Pool'!$Z$2:$Z$8725,0))),"") | AG19: =IFERROR(IF($AD19="","",IF(ISNUMBER(IFERROR(INDEX(Rosters!$I$2:$I$516,MATCH(INDEX('Player Pool'!$V$2:$V$8725,MATCH($AD19,'Player Pool'!$Z$2:$Z$8725,0)),Rosters!$W$2:$W$516,0)),"")),IFERROR(INDEX(Rosters!$I$2:$I$516,MATCH(INDEX('Player Pool'!$V$2:$V$8725,MATCH($AD19,'Player Pool'!$Z$2:$Z$8725,0)),Rosters!$W$2:$W$516,0)),""),INDEX('Player Pool'!$H$2:$H$8725,MATCH($AD19,'Player Pool'!$Z$2:$Z$8725,0)))),"") | AH19: =IFERROR(IF(INDEX('Player Pool'!$I$2:$I$8725,MATCH($AD19,'Player Pool'!$Z$2:$Z$8725,0))="","",INDEX('Player Pool'!$I$2:$I$8725,MATCH($AD19,'Player Pool'!$Z$2:$Z$8725,0))),"") | AI19: =IFERROR(IF(INDEX('Player Pool'!$P$2:$P$8725,MATCH($AD19,'Player Pool'!$Z$2:$Z$8725,0))="","",INDEX('Player Pool'!$P$2:$P$8725,MATCH($AD19,'Player Pool'!$Z$2:$Z$8725,0))),"") | AJ19: =IFERROR(IF(INDEX('Player Pool'!$R$2:$R$8725,MATCH($AD19,'Player Pool'!$Z$2:$Z$8725,0))="","",INDEX('Player Pool'!$R$2:$R$8725,MATCH($AD19,'Player Pool'!$Z$2:$Z$8725,0))),"") | AK19: =IFERROR(IF(INDEX('Player Pool'!$U$2:$U$8725,MATCH($AD19,'Player Pool'!$Z$2:$Z$8725,0))="","",INDEX('Player Pool'!$U$2:$U$8725,MATCH($AD19,'Player Pool'!$Z$2:$Z$8725,0))),"") | AL19: =IFERROR(IF($AD19="","",IF(INDEX('Player Pool'!$G$2:$G$8725,MATCH($AD19,'Player Pool'!$Z$2:$Z$8725,0))="FA","FA",IF(INDEX('Player Pool'!$G$2:$G$8725,MATCH($AD19,'Player Pool'!$Z$2:$Z$8725,0))='League Settings'!$B$2,"MINE","TAKEN"))),"") | AN19: Roman Kantserov (CHI RW) | AO19: =IFERROR(IF(INDEX('Player Pool'!$D$2:$D$8725,MATCH($AN19,'Player Pool'!$Z$2:$Z$8725,0))="","",INDEX('Player Pool'!$D$2:$D$8725,MATCH($AN19,'Player Pool'!$Z$2:$Z$8725,0))),"") | AP19: =IFERROR(IF(INDEX('Player Pool'!$E$2:$E$8725,MATCH($AN19,'Player Pool'!$Z$2:$Z$8725,0))="","",INDEX('Player Pool'!$E$2:$E$8725,MATCH($AN19,'Player Pool'!$Z$2:$Z$8725,0))),"") | AQ19: =IFERROR(IF($AN19="","",IF(ISNUMBER(IFERROR(INDEX(Rosters!$I$2:$I$516,MATCH(INDEX('Player Pool'!$V$2:$V$8725,MATCH($AN19,'Player Pool'!$Z$2:$Z$8725,0)),Rosters!$W$2:$W$516,0)),"")),IFERROR(INDEX(Rosters!$I$2:$I$516,MATCH(INDEX('Player Pool'!$V$2:$V$8725,MATCH($AN19,'Player Pool'!$Z$2:$Z$8725,0)),Rosters!$W$2:$W$516,0)),""),INDEX('Player Pool'!$H$2:$H$8725,MATCH($AN19,'Player Pool'!$Z$2:$Z$8725,0)))),"") | AR19: =IFERROR(IF(INDEX('Player Pool'!$I$2:$I$8725,MATCH($AN19,'Player Pool'!$Z$2:$Z$8725,0))="","",INDEX('Player Pool'!$I$2:$I$8725,MATCH($AN19,'Player Pool'!$Z$2:$Z$8725,0))),"") | AS19: =IFERROR(IF(INDEX('Player Pool'!$P$2:$P$8725,MATCH($AN19,'Player Pool'!$Z$2:$Z$8725,0))="","",INDEX('Player Pool'!$P$2:$P$8725,MATCH($AN19,'Player Pool'!$Z$2:$Z$8725,0))),"") | AT19: =IFERROR(IF(INDEX('Player Pool'!$R$2:$R$8725,MATCH($AN19,'Player Pool'!$Z$2:$Z$8725,0))="","",INDEX('Player Pool'!$R$2:$R$8725,MATCH($AN19,'Player Pool'!$Z$2:$Z$8725,0))),"") | AU19: =IFERROR(IF(INDEX('Player Pool'!$U$2:$U$8725,MATCH($AN19,'Player Pool'!$Z$2:$Z$8725,0))="","",INDEX('Player Pool'!$U$2:$U$8725,MATCH($AN19,'Player Pool'!$Z$2:$Z$8725,0))),"") | AV19: =IFERROR(IF($AN19="","",IF(INDEX('Player Pool'!$G$2:$G$8725,MATCH($AN19,'Player Pool'!$Z$2:$Z$8725,0))="FA","FA",IF(INDEX('Player Pool'!$G$2:$G$8725,MATCH($AN19,'Player Pool'!$Z$2:$Z$8725,0))='League Settings'!$B$2,"MINE","TAKEN"))),"")
A20: =IFERROR(IF(INDEX(Rosters!$B$2:$B$516,$S20)="","",INDEX(Rosters!$B$2:$B$516,$S20)),"") | B20: =IFERROR(IF(INDEX(Rosters!$C$2:$C$516,$S20)="","",INDEX(Rosters!$C$2:$C$516,$S20)),"") | C20: =IFERROR(IF(INDEX(Rosters!$D$2:$D$516,$S20)="","",INDEX(Rosters!$D$2:$D$516,$S20)),"") | D20: =IFERROR(IF(INDEX(Rosters!$E$2:$E$516,$S20)="","",INDEX(Rosters!$E$2:$E$516,$S20)),"") | E20: =IFERROR(IF(INDEX(Rosters!$F$2:$F$516,$S20)="","",INDEX(Rosters!$F$2:$F$516,$S20)),"") | F20: =IFERROR(IF(INDEX(Rosters!$G$2:$G$516,$S20)="","",INDEX(Rosters!$G$2:$G$516,$S20)),"") | G20: =IFERROR(IF(INDEX(Rosters!$H$2:$H$516,$S20)="","",INDEX(Rosters!$H$2:$H$516,$S20)),"") | H20: =IFERROR(IF(INDEX(Rosters!$I$2:$I$516,$S20)="","",INDEX(Rosters!$I$2:$I$516,$S20)),"") | I20: =IFERROR(IF(INDEX(Rosters!$J$2:$J$516,$S20)="","",INDEX(Rosters!$J$2:$J$516,$S20)),"") | J20: =IFERROR(IF(INDEX(Rosters!$S$2:$S$516,$S20)="","",INDEX(Rosters!$S$2:$S$516,$S20)),"") | K20: =IFERROR(IF(INDEX(Rosters!$K$2:$K$516,$S20)="","",INDEX(Rosters!$K$2:$K$516,$S20)),"") | L20: =IFERROR(IF(INDEX(Rosters!$T$2:$T$516,$S20)="","",INDEX(Rosters!$T$2:$T$516,$S20)),"") | M20: =IFERROR(IF(INDEX(Rosters!$L$2:$L$516,$S20)="","",INDEX(Rosters!$L$2:$L$516,$S20)),"") | N20: =IFERROR(IF(INDEX(Rosters!$Q$2:$Q$516,$S20)="","",INDEX(Rosters!$Q$2:$Q$516,$S20)),"") | O20: =IFERROR(IF(INDEX(Rosters!$R$2:$R$516,$S20)="","",INDEX(Rosters!$R$2:$R$516,$S20)),"") | P20: =IFERROR(IF(INDEX(Rosters!$N$2:$N$516,$S20)="","",INDEX(Rosters!$N$2:$N$516,$S20)),"") | Q20: =IFERROR(IF(INDEX(Rosters!$O$2:$O$516,$S20)="","",INDEX(Rosters!$O$2:$O$516,$S20)),"") | R20: =IFERROR(IF(INDEX(Rosters!$P$2:$P$516,$S20)="","",INDEX(Rosters!$P$2:$P$516,$S20)),"") | S20: =IFERROR(MATCH('League Settings'!$B$2&"|ACTIVE|"&17,Rosters!$AD$2:$AD$516,0),"") | T20: Arseny Gritsyuk (NJD RW) | U20: =IFERROR(IF(INDEX('Player Pool'!$D$2:$D$8725,MATCH($T20,'Player Pool'!$Z$2:$Z$8725,0))="","",INDEX('Player Pool'!$D$2:$D$8725,MATCH($T20,'Player Pool'!$Z$2:$Z$8725,0))),"") | V20: =IFERROR(IF(INDEX('Player Pool'!$E$2:$E$8725,MATCH($T20,'Player Pool'!$Z$2:$Z$8725,0))="","",INDEX('Player Pool'!$E$2:$E$8725,MATCH($T20,'Player Pool'!$Z$2:$Z$8725,0))),"") | W20: =IFERROR(IF($T20="","",IF(ISNUMBER(IFERROR(INDEX(Rosters!$I$2:$I$516,MATCH(INDEX('Player Pool'!$V$2:$V$8725,MATCH($T20,'Player Pool'!$Z$2:$Z$8725,0)),Rosters!$W$2:$W$516,0)),"")),IFERROR(INDEX(Rosters!$I$2:$I$516,MATCH(INDEX('Player Pool'!$V$2:$V$8725,MATCH($T20,'Player Pool'!$Z$2:$Z$8725,0)),Rosters!$W$2:$W$516,0)),""),INDEX('Player Pool'!$H$2:$H$8725,MATCH($T20,'Player Pool'!$Z$2:$Z$8725,0)))),"") | X20: =IFERROR(IF(INDEX('Player Pool'!$I$2:$I$8725,MATCH($T20,'Player Pool'!$Z$2:$Z$8725,0))="","",INDEX('Player Pool'!$I$2:$I$8725,MATCH($T20,'Player Pool'!$Z$2:$Z$8725,0))),"") | Y20: =IFERROR(IF(INDEX('Player Pool'!$P$2:$P$8725,MATCH($T20,'Player Pool'!$Z$2:$Z$8725,0))="","",INDEX('Player Pool'!$P$2:$P$8725,MATCH($T20,'Player Pool'!$Z$2:$Z$8725,0))),"") | Z20: =IFERROR(IF(INDEX('Player Pool'!$R$2:$R$8725,MATCH($T20,'Player Pool'!$Z$2:$Z$8725,0))="","",INDEX('Player Pool'!$R$2:$R$8725,MATCH($T20,'Player Pool'!$Z$2:$Z$8725,0))),"") | AA20: =IFERROR(IF(INDEX('Player Pool'!$U$2:$U$8725,MATCH($T20,'Player Pool'!$Z$2:$Z$8725,0))="","",INDEX('Player Pool'!$U$2:$U$8725,MATCH($T20,'Player Pool'!$Z$2:$Z$8725,0))),"") | AB20: =IFERROR(IF($T20="","",IF(INDEX('Player Pool'!$G$2:$G$8725,MATCH($T20,'Player Pool'!$Z$2:$Z$8725,0))="FA","FA",IF(INDEX('Player Pool'!$G$2:$G$8725,MATCH($T20,'Player Pool'!$Z$2:$Z$8725,0))='League Settings'!$B$2,"MINE","TAKEN"))),"") | AD20: Arseny Gritsyuk (NJD RW) | AE20: =IFERROR(IF(INDEX('Player Pool'!$D$2:$D$8725,MATCH($AD20,'Player Pool'!$Z$2:$Z$8725,0))="","",INDEX('Player Pool'!$D$2:$D$8725,MATCH($AD20,'Player Pool'!$Z$2:$Z$8725,0))),"") | AF20: =IFERROR(IF(INDEX('Player Pool'!$E$2:$E$8725,MATCH($AD20,'Player Pool'!$Z$2:$Z$8725,0))="","",INDEX('Player Pool'!$E$2:$E$8725,MATCH($AD20,'Player Pool'!$Z$2:$Z$8725,0))),"") | AG20: =IFERROR(IF($AD20="","",IF(ISNUMBER(IFERROR(INDEX(Rosters!$I$2:$I$516,MATCH(INDEX('Player Pool'!$V$2:$V$8725,MATCH($AD20,'Player Pool'!$Z$2:$Z$8725,0)),Rosters!$W$2:$W$516,0)),"")),IFERROR(INDEX(Rosters!$I$2:$I$516,MATCH(INDEX('Player Pool'!$V$2:$V$8725,MATCH($AD20,'Player Pool'!$Z$2:$Z$8725,0)),Rosters!$W$2:$W$516,0)),""),INDEX('Player Pool'!$H$2:$H$8725,MATCH($AD20,'Player Pool'!$Z$2:$Z$8725,0)))),"") | AH20: =IFERROR(IF(INDEX('Player Pool'!$I$2:$I$8725,MATCH($AD20,'Player Pool'!$Z$2:$Z$8725,0))="","",INDEX('Player Pool'!$I$2:$I$8725,MATCH($AD20,'Player Pool'!$Z$2:$Z$8725,0))),"") | AI20: =IFERROR(IF(INDEX('Player Pool'!$P$2:$P$8725,MATCH($AD20,'Player Pool'!$Z$2:$Z$8725,0))="","",INDEX('Player Pool'!$P$2:$P$8725,MATCH($AD20,'Player Pool'!$Z$2:$Z$8725,0))),"") | AJ20: =IFERROR(IF(INDEX('Player Pool'!$R$2:$R$8725,MATCH($AD20,'Player Pool'!$Z$2:$Z$8725,0))="","",INDEX('Player Pool'!$R$2:$R$8725,MATCH($AD20,'Player Pool'!$Z$2:$Z$8725,0))),"") | AK20: =IFERROR(IF(INDEX('Player Pool'!$U$2:$U$8725,MATCH($AD20,'Player Pool'!$Z$2:$Z$8725,0))="","",INDEX('Player Pool'!$U$2:$U$8725,MATCH($AD20,'Player Pool'!$Z$2:$Z$8725,0))),"") | AL20: =IFERROR(IF($AD20="","",IF(INDEX('Player Pool'!$G$2:$G$8725,MATCH($AD20,'Player Pool'!$Z$2:$Z$8725,0))="FA","FA",IF(INDEX('Player Pool'!$G$2:$G$8725,MATCH($AD20,'Player Pool'!$Z$2:$Z$8725,0))='League Settings'!$B$2,"MINE","TAKEN"))),"") | AN20: Arseny Gritsyuk (NJD RW) | AO20: =IFERROR(IF(INDEX('Player Pool'!$D$2:$D$8725,MATCH($AN20,'Player Pool'!$Z$2:$Z$8725,0))="","",INDEX('Player Pool'!$D$2:$D$8725,MATCH($AN20,'Player Pool'!$Z$2:$Z$8725,0))),"") | AP20: =IFERROR(IF(INDEX('Player Pool'!$E$2:$E$8725,MATCH($AN20,'Player Pool'!$Z$2:$Z$8725,0))="","",INDEX('Player Pool'!$E$2:$E$8725,MATCH($AN20,'Player Pool'!$Z$2:$Z$8725,0))),"") | AQ20: =IFERROR(IF($AN20="","",IF(ISNUMBER(IFERROR(INDEX(Rosters!$I$2:$I$516,MATCH(INDEX('Player Pool'!$V$2:$V$8725,MATCH($AN20,'Player Pool'!$Z$2:$Z$8725,0)),Rosters!$W$2:$W$516,0)),"")),IFERROR(INDEX(Rosters!$I$2:$I$516,MATCH(INDEX('Player Pool'!$V$2:$V$8725,MATCH($AN20,'Player Pool'!$Z$2:$Z$8725,0)),Rosters!$W$2:$W$516,0)),""),INDEX('Player Pool'!$H$2:$H$8725,MATCH($AN20,'Player Pool'!$Z$2:$Z$8725,0)))),"") | AR20: =IFERROR(IF(INDEX('Player Pool'!$I$2:$I$8725,MATCH($AN20,'Player Pool'!$Z$2:$Z$8725,0))="","",INDEX('Player Pool'!$I$2:$I$8725,MATCH($AN20,'Player Pool'!$Z$2:$Z$8725,0))),"") | AS20: =IFERROR(IF(INDEX('Player Pool'!$P$2:$P$8725,MATCH($AN20,'Player Pool'!$Z$2:$Z$8725,0))="","",INDEX('Player Pool'!$P$2:$P$8725,MATCH($AN20,'Player Pool'!$Z$2:$Z$8725,0))),"") | AT20: =IFERROR(IF(INDEX('Player Pool'!$R$2:$R$8725,MATCH($AN20,'Player Pool'!$Z$2:$Z$8725,0))="","",INDEX('Player Pool'!$R$2:$R$8725,MATCH($AN20,'Player Pool'!$Z$2:$Z$8725,0))),"") | AU20: =IFERROR(IF(INDEX('Player Pool'!$U$2:$U$8725,MATCH($AN20,'Player Pool'!$Z$2:$Z$8725,0))="","",INDEX('Player Pool'!$U$2:$U$8725,MATCH($AN20,'Player Pool'!$Z$2:$Z$8725,0))),"") | AV20: =IFERROR(IF($AN20="","",IF(INDEX('Player Pool'!$G$2:$G$8725,MATCH($AN20,'Player Pool'!$Z$2:$Z$8725,0))="FA","FA",IF(INDEX('Player Pool'!$G$2:$G$8725,MATCH($AN20,'Player Pool'!$Z$2:$Z$8725,0))='League Settings'!$B$2,"MINE","TAKEN"))),"")
A21: =IFERROR(IF(INDEX(Rosters!$B$2:$B$516,$S21)="","",INDEX(Rosters!$B$2:$B$516,$S21)),"") | B21: =IFERROR(IF(INDEX(Rosters!$C$2:$C$516,$S21)="","",INDEX(Rosters!$C$2:$C$516,$S21)),"") | C21: =IFERROR(IF(INDEX(Rosters!$D$2:$D$516,$S21)="","",INDEX(Rosters!$D$2:$D$516,$S21)),"") | D21: =IFERROR(IF(INDEX(Rosters!$E$2:$E$516,$S21)="","",INDEX(Rosters!$E$2:$E$516,$S21)),"") | E21: =IFERROR(IF(INDEX(Rosters!$F$2:$F$516,$S21)="","",INDEX(Rosters!$F$2:$F$516,$S21)),"") | F21: =IFERROR(IF(INDEX(Rosters!$G$2:$G$516,$S21)="","",INDEX(Rosters!$G$2:$G$516,$S21)),"") | G21: =IFERROR(IF(INDEX(Rosters!$H$2:$H$516,$S21)="","",INDEX(Rosters!$H$2:$H$516,$S21)),"") | H21: =IFERROR(IF(INDEX(Rosters!$I$2:$I$516,$S21)="","",INDEX(Rosters!$I$2:$I$516,$S21)),"") | I21: =IFERROR(IF(INDEX(Rosters!$J$2:$J$516,$S21)="","",INDEX(Rosters!$J$2:$J$516,$S21)),"") | J21: =IFERROR(IF(INDEX(Rosters!$S$2:$S$516,$S21)="","",INDEX(Rosters!$S$2:$S$516,$S21)),"") | K21: =IFERROR(IF(INDEX(Rosters!$K$2:$K$516,$S21)="","",INDEX(Rosters!$K$2:$K$516,$S21)),"") | L21: =IFERROR(IF(INDEX(Rosters!$T$2:$T$516,$S21)="","",INDEX(Rosters!$T$2:$T$516,$S21)),"") | M21: =IFERROR(IF(INDEX(Rosters!$L$2:$L$516,$S21)="","",INDEX(Rosters!$L$2:$L$516,$S21)),"") | N21: =IFERROR(IF(INDEX(Rosters!$Q$2:$Q$516,$S21)="","",INDEX(Rosters!$Q$2:$Q$516,$S21)),"") | O21: =IFERROR(IF(INDEX(Rosters!$R$2:$R$516,$S21)="","",INDEX(Rosters!$R$2:$R$516,$S21)),"") | P21: =IFERROR(IF(INDEX(Rosters!$N$2:$N$516,$S21)="","",INDEX(Rosters!$N$2:$N$516,$S21)),"") | Q21: =IFERROR(IF(INDEX(Rosters!$O$2:$O$516,$S21)="","",INDEX(Rosters!$O$2:$O$516,$S21)),"") | R21: =IFERROR(IF(INDEX(Rosters!$P$2:$P$516,$S21)="","",INDEX(Rosters!$P$2:$P$516,$S21)),"") | S21: =IFERROR(MATCH('League Settings'!$B$2&"|ACTIVE|"&18,Rosters!$AD$2:$AD$516,0),"") | T21: Dalibor Dvorsky (STL C) | U21: =IFERROR(IF(INDEX('Player Pool'!$D$2:$D$8725,MATCH($T21,'Player Pool'!$Z$2:$Z$8725,0))="","",INDEX('Player Pool'!$D$2:$D$8725,MATCH($T21,'Player Pool'!$Z$2:$Z$8725,0))),"") | V21: =IFERROR(IF(INDEX('Player Pool'!$E$2:$E$8725,MATCH($T21,'Player Pool'!$Z$2:$Z$8725,0))="","",INDEX('Player Pool'!$E$2:$E$8725,MATCH($T21,'Player Pool'!$Z$2:$Z$8725,0))),"") | W21: =IFERROR(IF($T21="","",IF(ISNUMBER(IFERROR(INDEX(Rosters!$I$2:$I$516,MATCH(INDEX('Player Pool'!$V$2:$V$8725,MATCH($T21,'Player Pool'!$Z$2:$Z$8725,0)),Rosters!$W$2:$W$516,0)),"")),IFERROR(INDEX(Rosters!$I$2:$I$516,MATCH(INDEX('Player Pool'!$V$2:$V$8725,MATCH($T21,'Player Pool'!$Z$2:$Z$8725,0)),Rosters!$W$2:$W$516,0)),""),INDEX('Player Pool'!$H$2:$H$8725,MATCH($T21,'Player Pool'!$Z$2:$Z$8725,0)))),"") | X21: =IFERROR(IF(INDEX('Player Pool'!$I$2:$I$8725,MATCH($T21,'Player Pool'!$Z$2:$Z$8725,0))="","",INDEX('Player Pool'!$I$2:$I$8725,MATCH($T21,'Player Pool'!$Z$2:$Z$8725,0))),"") | Y21: =IFERROR(IF(INDEX('Player Pool'!$P$2:$P$8725,MATCH($T21,'Player Pool'!$Z$2:$Z$8725,0))="","",INDEX('Player Pool'!$P$2:$P$8725,MATCH($T21,'Player Pool'!$Z$2:$Z$8725,0))),"") | Z21: =IFERROR(IF(INDEX('Player Pool'!$R$2:$R$8725,MATCH($T21,'Player Pool'!$Z$2:$Z$8725,0))="","",INDEX('Player Pool'!$R$2:$R$8725,MATCH($T21,'Player Pool'!$Z$2:$Z$8725,0))),"") | AA21: =IFERROR(IF(INDEX('Player Pool'!$U$2:$U$8725,MATCH($T21,'Player Pool'!$Z$2:$Z$8725,0))="","",INDEX('Player Pool'!$U$2:$U$8725,MATCH($T21,'Player Pool'!$Z$2:$Z$8725,0))),"") | AB21: =IFERROR(IF($T21="","",IF(INDEX('Player Pool'!$G$2:$G$8725,MATCH($T21,'Player Pool'!$Z$2:$Z$8725,0))="FA","FA",IF(INDEX('Player Pool'!$G$2:$G$8725,MATCH($T21,'Player Pool'!$Z$2:$Z$8725,0))='League Settings'!$B$2,"MINE","TAKEN"))),"") | AD21: Dalibor Dvorsky (STL C) | AE21: =IFERROR(IF(INDEX('Player Pool'!$D$2:$D$8725,MATCH($AD21,'Player Pool'!$Z$2:$Z$8725,0))="","",INDEX('Player Pool'!$D$2:$D$8725,MATCH($AD21,'Player Pool'!$Z$2:$Z$8725,0))),"") | AF21: =IFERROR(IF(INDEX('Player Pool'!$E$2:$E$8725,MATCH($AD21,'Player Pool'!$Z$2:$Z$8725,0))="","",INDEX('Player Pool'!$E$2:$E$8725,MATCH($AD21,'Player Pool'!$Z$2:$Z$8725,0))),"") | AG21: =IFERROR(IF($AD21="","",IF(ISNUMBER(IFERROR(INDEX(Rosters!$I$2:$I$516,MATCH(INDEX('Player Pool'!$V$2:$V$8725,MATCH($AD21,'Player Pool'!$Z$2:$Z$8725,0)),Rosters!$W$2:$W$516,0)),"")),IFERROR(INDEX(Rosters!$I$2:$I$516,MATCH(INDEX('Player Pool'!$V$2:$V$8725,MATCH($AD21,'Player Pool'!$Z$2:$Z$8725,0)),Rosters!$W$2:$W$516,0)),""),INDEX('Player Pool'!$H$2:$H$8725,MATCH($AD21,'Player Pool'!$Z$2:$Z$8725,0)))),"") | AH21: =IFERROR(IF(INDEX('Player Pool'!$I$2:$I$8725,MATCH($AD21,'Player Pool'!$Z$2:$Z$8725,0))="","",INDEX('Player Pool'!$I$2:$I$8725,MATCH($AD21,'Player Pool'!$Z$2:$Z$8725,0))),"") | AI21: =IFERROR(IF(INDEX('Player Pool'!$P$2:$P$8725,MATCH($AD21,'Player Pool'!$Z$2:$Z$8725,0))="","",INDEX('Player Pool'!$P$2:$P$8725,MATCH($AD21,'Player Pool'!$Z$2:$Z$8725,0))),"") | AJ21: =IFERROR(IF(INDEX('Player Pool'!$R$2:$R$8725,MATCH($AD21,'Player Pool'!$Z$2:$Z$8725,0))="","",INDEX('Player Pool'!$R$2:$R$8725,MATCH($AD21,'Player Pool'!$Z$2:$Z$8725,0))),"") | AK21: =IFERROR(IF(INDEX('Player Pool'!$U$2:$U$8725,MATCH($AD21,'Player Pool'!$Z$2:$Z$8725,0))="","",INDEX('Player Pool'!$U$2:$U$8725,MATCH($AD21,'Player Pool'!$Z$2:$Z$8725,0))),"") | AL21: =IFERROR(IF($AD21="","",IF(INDEX('Player Pool'!$G$2:$G$8725,MATCH($AD21,'Player Pool'!$Z$2:$Z$8725,0))="FA","FA",IF(INDEX('Player Pool'!$G$2:$G$8725,MATCH($AD21,'Player Pool'!$Z$2:$Z$8725,0))='League Settings'!$B$2,"MINE","TAKEN"))),"") | AN21: Dalibor Dvorsky (STL C) | AO21: =IFERROR(IF(INDEX('Player Pool'!$D$2:$D$8725,MATCH($AN21,'Player Pool'!$Z$2:$Z$8725,0))="","",INDEX('Player Pool'!$D$2:$D$8725,MATCH($AN21,'Player Pool'!$Z$2:$Z$8725,0))),"") | AP21: =IFERROR(IF(INDEX('Player Pool'!$E$2:$E$8725,MATCH($AN21,'Player Pool'!$Z$2:$Z$8725,0))="","",INDEX('Player Pool'!$E$2:$E$8725,MATCH($AN21,'Player Pool'!$Z$2:$Z$8725,0))),"") | AQ21: =IFERROR(IF($AN21="","",IF(ISNUMBER(IFERROR(INDEX(Rosters!$I$2:$I$516,MATCH(INDEX('Player Pool'!$V$2:$V$8725,MATCH($AN21,'Player Pool'!$Z$2:$Z$8725,0)),Rosters!$W$2:$W$516,0)),"")),IFERROR(INDEX(Rosters!$I$2:$I$516,MATCH(INDEX('Player Pool'!$V$2:$V$8725,MATCH($AN21,'Player Pool'!$Z$2:$Z$8725,0)),Rosters!$W$2:$W$516,0)),""),INDEX('Player Pool'!$H$2:$H$8725,MATCH($AN21,'Player Pool'!$Z$2:$Z$8725,0)))),"") | AR21: =IFERROR(IF(INDEX('Player Pool'!$I$2:$I$8725,MATCH($AN21,'Player Pool'!$Z$2:$Z$8725,0))="","",INDEX('Player Pool'!$I$2:$I$8725,MATCH($AN21,'Player Pool'!$Z$2:$Z$8725,0))),"") | AS21: =IFERROR(IF(INDEX('Player Pool'!$P$2:$P$8725,MATCH($AN21,'Player Pool'!$Z$2:$Z$8725,0))="","",INDEX('Player Pool'!$P$2:$P$8725,MATCH($AN21,'Player Pool'!$Z$2:$Z$8725,0))),"") | AT21: =IFERROR(IF(INDEX('Player Pool'!$R$2:$R$8725,MATCH($AN21,'Player Pool'!$Z$2:$Z$8725,0))="","",INDEX('Player Pool'!$R$2:$R$8725,MATCH($AN21,'Player Pool'!$Z$2:$Z$8725,0))),"") | AU21: =IFERROR(IF(INDEX('Player Pool'!$U$2:$U$8725,MATCH($AN21,'Player Pool'!$Z$2:$Z$8725,0))="","",INDEX('Player Pool'!$U$2:$U$8725,MATCH($AN21,'Player Pool'!$Z$2:$Z$8725,0))),"") | AV21: =IFERROR(IF($AN21="","",IF(INDEX('Player Pool'!$G$2:$G$8725,MATCH($AN21,'Player Pool'!$Z$2:$Z$8725,0))="FA","FA",IF(INDEX('Player Pool'!$G$2:$G$8725,MATCH($AN21,'Player Pool'!$Z$2:$Z$8725,0))='League Settings'!$B$2,"MINE","TAKEN"))),"")
A22: =IFERROR(IF(INDEX(Rosters!$B$2:$B$516,$S22)="","",INDEX(Rosters!$B$2:$B$516,$S22)),"") | B22: =IFERROR(IF(INDEX(Rosters!$C$2:$C$516,$S22)="","",INDEX(Rosters!$C$2:$C$516,$S22)),"") | C22: =IFERROR(IF(INDEX(Rosters!$D$2:$D$516,$S22)="","",INDEX(Rosters!$D$2:$D$516,$S22)),"") | D22: =IFERROR(IF(INDEX(Rosters!$E$2:$E$516,$S22)="","",INDEX(Rosters!$E$2:$E$516,$S22)),"") | E22: =IFERROR(IF(INDEX(Rosters!$F$2:$F$516,$S22)="","",INDEX(Rosters!$F$2:$F$516,$S22)),"") | F22: =IFERROR(IF(INDEX(Rosters!$G$2:$G$516,$S22)="","",INDEX(Rosters!$G$2:$G$516,$S22)),"") | G22: =IFERROR(IF(INDEX(Rosters!$H$2:$H$516,$S22)="","",INDEX(Rosters!$H$2:$H$516,$S22)),"") | H22: =IFERROR(IF(INDEX(Rosters!$I$2:$I$516,$S22)="","",INDEX(Rosters!$I$2:$I$516,$S22)),"") | I22: =IFERROR(IF(INDEX(Rosters!$J$2:$J$516,$S22)="","",INDEX(Rosters!$J$2:$J$516,$S22)),"") | J22: =IFERROR(IF(INDEX(Rosters!$S$2:$S$516,$S22)="","",INDEX(Rosters!$S$2:$S$516,$S22)),"") | K22: =IFERROR(IF(INDEX(Rosters!$K$2:$K$516,$S22)="","",INDEX(Rosters!$K$2:$K$516,$S22)),"") | L22: =IFERROR(IF(INDEX(Rosters!$T$2:$T$516,$S22)="","",INDEX(Rosters!$T$2:$T$516,$S22)),"") | M22: =IFERROR(IF(INDEX(Rosters!$L$2:$L$516,$S22)="","",INDEX(Rosters!$L$2:$L$516,$S22)),"") | N22: =IFERROR(IF(INDEX(Rosters!$Q$2:$Q$516,$S22)="","",INDEX(Rosters!$Q$2:$Q$516,$S22)),"") | O22: =IFERROR(IF(INDEX(Rosters!$R$2:$R$516,$S22)="","",INDEX(Rosters!$R$2:$R$516,$S22)),"") | P22: =IFERROR(IF(INDEX(Rosters!$N$2:$N$516,$S22)="","",INDEX(Rosters!$N$2:$N$516,$S22)),"") | Q22: =IFERROR(IF(INDEX(Rosters!$O$2:$O$516,$S22)="","",INDEX(Rosters!$O$2:$O$516,$S22)),"") | R22: =IFERROR(IF(INDEX(Rosters!$P$2:$P$516,$S22)="","",INDEX(Rosters!$P$2:$P$516,$S22)),"") | S22: =IFERROR(MATCH('League Settings'!$B$2&"|ACTIVE|"&19,Rosters!$AD$2:$AD$516,0),"") | T22: Oliver Moore (CHI C) | U22: =IFERROR(IF(INDEX('Player Pool'!$D$2:$D$8725,MATCH($T22,'Player Pool'!$Z$2:$Z$8725,0))="","",INDEX('Player Pool'!$D$2:$D$8725,MATCH($T22,'Player Pool'!$Z$2:$Z$8725,0))),"") | V22: =IFERROR(IF(INDEX('Player Pool'!$E$2:$E$8725,MATCH($T22,'Player Pool'!$Z$2:$Z$8725,0))="","",INDEX('Player Pool'!$E$2:$E$8725,MATCH($T22,'Player Pool'!$Z$2:$Z$8725,0))),"") | W22: =IFERROR(IF($T22="","",IF(ISNUMBER(IFERROR(INDEX(Rosters!$I$2:$I$516,MATCH(INDEX('Player Pool'!$V$2:$V$8725,MATCH($T22,'Player Pool'!$Z$2:$Z$8725,0)),Rosters!$W$2:$W$516,0)),"")),IFERROR(INDEX(Rosters!$I$2:$I$516,MATCH(INDEX('Player Pool'!$V$2:$V$8725,MATCH($T22,'Player Pool'!$Z$2:$Z$8725,0)),Rosters!$W$2:$W$516,0)),""),INDEX('Player Pool'!$H$2:$H$8725,MATCH($T22,'Player Pool'!$Z$2:$Z$8725,0)))),"") | X22: =IFERROR(IF(INDEX('Player Pool'!$I$2:$I$8725,MATCH($T22,'Player Pool'!$Z$2:$Z$8725,0))="","",INDEX('Player Pool'!$I$2:$I$8725,MATCH($T22,'Player Pool'!$Z$2:$Z$8725,0))),"") | Y22: =IFERROR(IF(INDEX('Player Pool'!$P$2:$P$8725,MATCH($T22,'Player Pool'!$Z$2:$Z$8725,0))="","",INDEX('Player Pool'!$P$2:$P$8725,MATCH($T22,'Player Pool'!$Z$2:$Z$8725,0))),"") | Z22: =IFERROR(IF(INDEX('Player Pool'!$R$2:$R$8725,MATCH($T22,'Player Pool'!$Z$2:$Z$8725,0))="","",INDEX('Player Pool'!$R$2:$R$8725,MATCH($T22,'Player Pool'!$Z$2:$Z$8725,0))),"") | AA22: =IFERROR(IF(INDEX('Player Pool'!$U$2:$U$8725,MATCH($T22,'Player Pool'!$Z$2:$Z$8725,0))="","",INDEX('Player Pool'!$U$2:$U$8725,MATCH($T22,'Player Pool'!$Z$2:$Z$8725,0))),"") | AB22: =IFERROR(IF($T22="","",IF(INDEX('Player Pool'!$G$2:$G$8725,MATCH($T22,'Player Pool'!$Z$2:$Z$8725,0))="FA","FA",IF(INDEX('Player Pool'!$G$2:$G$8725,MATCH($T22,'Player Pool'!$Z$2:$Z$8725,0))='League Settings'!$B$2,"MINE","TAKEN"))),"") | AD22: Oliver Moore (CHI C) | AE22: =IFERROR(IF(INDEX('Player Pool'!$D$2:$D$8725,MATCH($AD22,'Player Pool'!$Z$2:$Z$8725,0))="","",INDEX('Player Pool'!$D$2:$D$8725,MATCH($AD22,'Player Pool'!$Z$2:$Z$8725,0))),"") | AF22: =IFERROR(IF(INDEX('Player Pool'!$E$2:$E$8725,MATCH($AD22,'Player Pool'!$Z$2:$Z$8725,0))="","",INDEX('Player Pool'!$E$2:$E$8725,MATCH($AD22,'Player Pool'!$Z$2:$Z$8725,0))),"") | AG22: =IFERROR(IF($AD22="","",IF(ISNUMBER(IFERROR(INDEX(Rosters!$I$2:$I$516,MATCH(INDEX('Player Pool'!$V$2:$V$8725,MATCH($AD22,'Player Pool'!$Z$2:$Z$8725,0)),Rosters!$W$2:$W$516,0)),"")),IFERROR(INDEX(Rosters!$I$2:$I$516,MATCH(INDEX('Player Pool'!$V$2:$V$8725,MATCH($AD22,'Player Pool'!$Z$2:$Z$8725,0)),Rosters!$W$2:$W$516,0)),""),INDEX('Player Pool'!$H$2:$H$8725,MATCH($AD22,'Player Pool'!$Z$2:$Z$8725,0)))),"") | AH22: =IFERROR(IF(INDEX('Player Pool'!$I$2:$I$8725,MATCH($AD22,'Player Pool'!$Z$2:$Z$8725,0))="","",INDEX('Player Pool'!$I$2:$I$8725,MATCH($AD22,'Player Pool'!$Z$2:$Z$8725,0))),"") | AI22: =IFERROR(IF(INDEX('Player Pool'!$P$2:$P$8725,MATCH($AD22,'Player Pool'!$Z$2:$Z$8725,0))="","",INDEX('Player Pool'!$P$2:$P$8725,MATCH($AD22,'Player Pool'!$Z$2:$Z$8725,0))),"") | AJ22: =IFERROR(IF(INDEX('Player Pool'!$R$2:$R$8725,MATCH($AD22,'Player Pool'!$Z$2:$Z$8725,0))="","",INDEX('Player Pool'!$R$2:$R$8725,MATCH($AD22,'Player Pool'!$Z$2:$Z$8725,0))),"") | AK22: =IFERROR(IF(INDEX('Player Pool'!$U$2:$U$8725,MATCH($AD22,'Player Pool'!$Z$2:$Z$8725,0))="","",INDEX('Player Pool'!$U$2:$U$8725,MATCH($AD22,'Player Pool'!$Z$2:$Z$8725,0))),"") | AL22: =IFERROR(IF($AD22="","",IF(INDEX('Player Pool'!$G$2:$G$8725,MATCH($AD22,'Player Pool'!$Z$2:$Z$8725,0))="FA","FA",IF(INDEX('Player Pool'!$G$2:$G$8725,MATCH($AD22,'Player Pool'!$Z$2:$Z$8725,0))='League Settings'!$B$2,"MINE","TAKEN"))),"") | AN22: Oliver Moore (CHI C) | AO22: =IFERROR(IF(INDEX('Player Pool'!$D$2:$D$8725,MATCH($AN22,'Player Pool'!$Z$2:$Z$8725,0))="","",INDEX('Player Pool'!$D$2:$D$8725,MATCH($AN22,'Player Pool'!$Z$2:$Z$8725,0))),"") | AP22: =IFERROR(IF(INDEX('Player Pool'!$E$2:$E$8725,MATCH($AN22,'Player Pool'!$Z$2:$Z$8725,0))="","",INDEX('Player Pool'!$E$2:$E$8725,MATCH($AN22,'Player Pool'!$Z$2:$Z$8725,0))),"") | AQ22: =IFERROR(IF($AN22="","",IF(ISNUMBER(IFERROR(INDEX(Rosters!$I$2:$I$516,MATCH(INDEX('Player Pool'!$V$2:$V$8725,MATCH($AN22,'Player Pool'!$Z$2:$Z$8725,0)),Rosters!$W$2:$W$516,0)),"")),IFERROR(INDEX(Rosters!$I$2:$I$516,MATCH(INDEX('Player Pool'!$V$2:$V$8725,MATCH($AN22,'Player Pool'!$Z$2:$Z$8725,0)),Rosters!$W$2:$W$516,0)),""),INDEX('Player Pool'!$H$2:$H$8725,MATCH($AN22,'Player Pool'!$Z$2:$Z$8725,0)))),"") | AR22: =IFERROR(IF(INDEX('Player Pool'!$I$2:$I$8725,MATCH($AN22,'Player Pool'!$Z$2:$Z$8725,0))="","",INDEX('Player Pool'!$I$2:$I$8725,MATCH($AN22,'Player Pool'!$Z$2:$Z$8725,0))),"") | AS22: =IFERROR(IF(INDEX('Player Pool'!$P$2:$P$8725,MATCH($AN22,'Player Pool'!$Z$2:$Z$8725,0))="","",INDEX('Player Pool'!$P$2:$P$8725,MATCH($AN22,'Player Pool'!$Z$2:$Z$8725,0))),"") | AT22: =IFERROR(IF(INDEX('Player Pool'!$R$2:$R$8725,MATCH($AN22,'Player Pool'!$Z$2:$Z$8725,0))="","",INDEX('Player Pool'!$R$2:$R$8725,MATCH($AN22,'Player Pool'!$Z$2:$Z$8725,0))),"") | AU22: =IFERROR(IF(INDEX('Player Pool'!$U$2:$U$8725,MATCH($AN22,'Player Pool'!$Z$2:$Z$8725,0))="","",INDEX('Player Pool'!$U$2:$U$8725,MATCH($AN22,'Player Pool'!$Z$2:$Z$8725,0))),"") | AV22: =IFERROR(IF($AN22="","",IF(INDEX('Player Pool'!$G$2:$G$8725,MATCH($AN22,'Player Pool'!$Z$2:$Z$8725,0))="FA","FA",IF(INDEX('Player Pool'!$G$2:$G$8725,MATCH($AN22,'Player Pool'!$Z$2:$Z$8725,0))='League Settings'!$B$2,"MINE","TAKEN"))),"")
A23: =IFERROR(IF(INDEX(Rosters!$B$2:$B$516,$S23)="","",INDEX(Rosters!$B$2:$B$516,$S23)),"") | B23: =IFERROR(IF(INDEX(Rosters!$C$2:$C$516,$S23)="","",INDEX(Rosters!$C$2:$C$516,$S23)),"") | C23: =IFERROR(IF(INDEX(Rosters!$D$2:$D$516,$S23)="","",INDEX(Rosters!$D$2:$D$516,$S23)),"") | D23: =IFERROR(IF(INDEX(Rosters!$E$2:$E$516,$S23)="","",INDEX(Rosters!$E$2:$E$516,$S23)),"") | E23: =IFERROR(IF(INDEX(Rosters!$F$2:$F$516,$S23)="","",INDEX(Rosters!$F$2:$F$516,$S23)),"") | F23: =IFERROR(IF(INDEX(Rosters!$G$2:$G$516,$S23)="","",INDEX(Rosters!$G$2:$G$516,$S23)),"") | G23: =IFERROR(IF(INDEX(Rosters!$H$2:$H$516,$S23)="","",INDEX(Rosters!$H$2:$H$516,$S23)),"") | H23: =IFERROR(IF(INDEX(Rosters!$I$2:$I$516,$S23)="","",INDEX(Rosters!$I$2:$I$516,$S23)),"") | I23: =IFERROR(IF(INDEX(Rosters!$J$2:$J$516,$S23)="","",INDEX(Rosters!$J$2:$J$516,$S23)),"") | J23: =IFERROR(IF(INDEX(Rosters!$S$2:$S$516,$S23)="","",INDEX(Rosters!$S$2:$S$516,$S23)),"") | K23: =IFERROR(IF(INDEX(Rosters!$K$2:$K$516,$S23)="","",INDEX(Rosters!$K$2:$K$516,$S23)),"") | L23: =IFERROR(IF(INDEX(Rosters!$T$2:$T$516,$S23)="","",INDEX(Rosters!$T$2:$T$516,$S23)),"") | M23: =IFERROR(IF(INDEX(Rosters!$L$2:$L$516,$S23)="","",INDEX(Rosters!$L$2:$L$516,$S23)),"") | N23: =IFERROR(IF(INDEX(Rosters!$Q$2:$Q$516,$S23)="","",INDEX(Rosters!$Q$2:$Q$516,$S23)),"") | O23: =IFERROR(IF(INDEX(Rosters!$R$2:$R$516,$S23)="","",INDEX(Rosters!$R$2:$R$516,$S23)),"") | P23: =IFERROR(IF(INDEX(Rosters!$N$2:$N$516,$S23)="","",INDEX(Rosters!$N$2:$N$516,$S23)),"") | Q23: =IFERROR(IF(INDEX(Rosters!$O$2:$O$516,$S23)="","",INDEX(Rosters!$O$2:$O$516,$S23)),"") | R23: =IFERROR(IF(INDEX(Rosters!$P$2:$P$516,$S23)="","",INDEX(Rosters!$P$2:$P$516,$S23)),"") | S23: =IFERROR(MATCH('League Settings'!$B$2&"|ACTIVE|"&20,Rosters!$AD$2:$AD$516,0),"") | U23: =IFERROR(IF(INDEX('Player Pool'!$D$2:$D$8725,MATCH($T23,'Player Pool'!$Z$2:$Z$8725,0))="","",INDEX('Player Pool'!$D$2:$D$8725,MATCH($T23,'Player Pool'!$Z$2:$Z$8725,0))),"") | V23: =IFERROR(IF(INDEX('Player Pool'!$E$2:$E$8725,MATCH($T23,'Player Pool'!$Z$2:$Z$8725,0))="","",INDEX('Player Pool'!$E$2:$E$8725,MATCH($T23,'Player Pool'!$Z$2:$Z$8725,0))),"") | W23: =IFERROR(IF($T23="","",IF(ISNUMBER(IFERROR(INDEX(Rosters!$I$2:$I$516,MATCH(INDEX('Player Pool'!$V$2:$V$8725,MATCH($T23,'Player Pool'!$Z$2:$Z$8725,0)),Rosters!$W$2:$W$516,0)),"")),IFERROR(INDEX(Rosters!$I$2:$I$516,MATCH(INDEX('Player Pool'!$V$2:$V$8725,MATCH($T23,'Player Pool'!$Z$2:$Z$8725,0)),Rosters!$W$2:$W$516,0)),""),INDEX('Player Pool'!$H$2:$H$8725,MATCH($T23,'Player Pool'!$Z$2:$Z$8725,0)))),"") | X23: =IFERROR(IF(INDEX('Player Pool'!$I$2:$I$8725,MATCH($T23,'Player Pool'!$Z$2:$Z$8725,0))="","",INDEX('Player Pool'!$I$2:$I$8725,MATCH($T23,'Player Pool'!$Z$2:$Z$8725,0))),"") | Y23: =IFERROR(IF(INDEX('Player Pool'!$P$2:$P$8725,MATCH($T23,'Player Pool'!$Z$2:$Z$8725,0))="","",INDEX('Player Pool'!$P$2:$P$8725,MATCH($T23,'Player Pool'!$Z$2:$Z$8725,0))),"") | Z23: =IFERROR(IF(INDEX('Player Pool'!$R$2:$R$8725,MATCH($T23,'Player Pool'!$Z$2:$Z$8725,0))="","",INDEX('Player Pool'!$R$2:$R$8725,MATCH($T23,'Player Pool'!$Z$2:$Z$8725,0))),"") | AA23: =IFERROR(IF(INDEX('Player Pool'!$U$2:$U$8725,MATCH($T23,'Player Pool'!$Z$2:$Z$8725,0))="","",INDEX('Player Pool'!$U$2:$U$8725,MATCH($T23,'Player Pool'!$Z$2:$Z$8725,0))),"") | AB23: =IFERROR(IF($T23="","",IF(INDEX('Player Pool'!$G$2:$G$8725,MATCH($T23,'Player Pool'!$Z$2:$Z$8725,0))="FA","FA",IF(INDEX('Player Pool'!$G$2:$G$8725,MATCH($T23,'Player Pool'!$Z$2:$Z$8725,0))='League Settings'!$B$2,"MINE","TAKEN"))),"") | AE23: =IFERROR(IF(INDEX('Player Pool'!$D$2:$D$8725,MATCH($AD23,'Player Pool'!$Z$2:$Z$8725,0))="","",INDEX('Player Pool'!$D$2:$D$8725,MATCH($AD23,'Player Pool'!$Z$2:$Z$8725,0))),"") | AF23: =IFERROR(IF(INDEX('Player Pool'!$E$2:$E$8725,MATCH($AD23,'Player Pool'!$Z$2:$Z$8725,0))="","",INDEX('Player Pool'!$E$2:$E$8725,MATCH($AD23,'Player Pool'!$Z$2:$Z$8725,0))),"") | AG23: =IFERROR(IF($AD23="","",IF(ISNUMBER(IFERROR(INDEX(Rosters!$I$2:$I$516,MATCH(INDEX('Player Pool'!$V$2:$V$8725,MATCH($AD23,'Player Pool'!$Z$2:$Z$8725,0)),Rosters!$W$2:$W$516,0)),"")),IFERROR(INDEX(Rosters!$I$2:$I$516,MATCH(INDEX('Player Pool'!$V$2:$V$8725,MATCH($AD23,'Player Pool'!$Z$2:$Z$8725,0)),Rosters!$W$2:$W$516,0)),""),INDEX('Player Pool'!$H$2:$H$8725,MATCH($AD23,'Player Pool'!$Z$2:$Z$8725,0)))),"") | AH23: =IFERROR(IF(INDEX('Player Pool'!$I$2:$I$8725,MATCH($AD23,'Player Pool'!$Z$2:$Z$8725,0))="","",INDEX('Player Pool'!$I$2:$I$8725,MATCH($AD23,'Player Pool'!$Z$2:$Z$8725,0))),"") | AI23: =IFERROR(IF(INDEX('Player Pool'!$P$2:$P$8725,MATCH($AD23,'Player Pool'!$Z$2:$Z$8725,0))="","",INDEX('Player Pool'!$P$2:$P$8725,MATCH($AD23,'Player Pool'!$Z$2:$Z$8725,0))),"") | AJ23: =IFERROR(IF(INDEX('Player Pool'!$R$2:$R$8725,MATCH($AD23,'Player Pool'!$Z$2:$Z$8725,0))="","",INDEX('Player Pool'!$R$2:$R$8725,MATCH($AD23,'Player Pool'!$Z$2:$Z$8725,0))),"") | AK23: =IFERROR(IF(INDEX('Player Pool'!$U$2:$U$8725,MATCH($AD23,'Player Pool'!$Z$2:$Z$8725,0))="","",INDEX('Player Pool'!$U$2:$U$8725,MATCH($AD23,'Player Pool'!$Z$2:$Z$8725,0))),"") | AL23: =IFERROR(IF($AD23="","",IF(INDEX('Player Pool'!$G$2:$G$8725,MATCH($AD23,'Player Pool'!$Z$2:$Z$8725,0))="FA","FA",IF(INDEX('Player Pool'!$G$2:$G$8725,MATCH($AD23,'Player Pool'!$Z$2:$Z$8725,0))='League Settings'!$B$2,"MINE","TAKEN"))),"") | AO23: =IFERROR(IF(INDEX('Player Pool'!$D$2:$D$8725,MATCH($AN23,'Player Pool'!$Z$2:$Z$8725,0))="","",INDEX('Player Pool'!$D$2:$D$8725,MATCH($AN23,'Player Pool'!$Z$2:$Z$8725,0))),"") | AP23: =IFERROR(IF(INDEX('Player Pool'!$E$2:$E$8725,MATCH($AN23,'Player Pool'!$Z$2:$Z$8725,0))="","",INDEX('Player Pool'!$E$2:$E$8725,MATCH($AN23,'Player Pool'!$Z$2:$Z$8725,0))),"") | AQ23: =IFERROR(IF($AN23="","",IF(ISNUMBER(IFERROR(INDEX(Rosters!$I$2:$I$516,MATCH(INDEX('Player Pool'!$V$2:$V$8725,MATCH($AN23,'Player Pool'!$Z$2:$Z$8725,0)),Rosters!$W$2:$W$516,0)),"")),IFERROR(INDEX(Rosters!$I$2:$I$516,MATCH(INDEX('Player Pool'!$V$2:$V$8725,MATCH($AN23,'Player Pool'!$Z$2:$Z$8725,0)),Rosters!$W$2:$W$516,0)),""),INDEX('Player Pool'!$H$2:$H$8725,MATCH($AN23,'Player Pool'!$Z$2:$Z$8725,0)))),"") | AR23: =IFERROR(IF(INDEX('Player Pool'!$I$2:$I$8725,MATCH($AN23,'Player Pool'!$Z$2:$Z$8725,0))="","",INDEX('Player Pool'!$I$2:$I$8725,MATCH($AN23,'Player Pool'!$Z$2:$Z$8725,0))),"") | AS23: =IFERROR(IF(INDEX('Player Pool'!$P$2:$P$8725,MATCH($AN23,'Player Pool'!$Z$2:$Z$8725,0))="","",INDEX('Player Pool'!$P$2:$P$8725,MATCH($AN23,'Player Pool'!$Z$2:$Z$8725,0))),"") | AT23: =IFERROR(IF(INDEX('Player Pool'!$R$2:$R$8725,MATCH($AN23,'Player Pool'!$Z$2:$Z$8725,0))="","",INDEX('Player Pool'!$R$2:$R$8725,MATCH($AN23,'Player Pool'!$Z$2:$Z$8725,0))),"") | AU23: =IFERROR(IF(INDEX('Player Pool'!$U$2:$U$8725,MATCH($AN23,'Player Pool'!$Z$2:$Z$8725,0))="","",INDEX('Player Pool'!$U$2:$U$8725,MATCH($AN23,'Player Pool'!$Z$2:$Z$8725,0))),"") | AV23: =IFERROR(IF($AN23="","",IF(INDEX('Player Pool'!$G$2:$G$8725,MATCH($AN23,'Player Pool'!$Z$2:$Z$8725,0))="FA","FA",IF(INDEX('Player Pool'!$G$2:$G$8725,MATCH($AN23,'Player Pool'!$Z$2:$Z$8725,0))='League Settings'!$B$2,"MINE","TAKEN"))),"")
A24: ="ROSTER subtotal ("&COUNTIF(A4:A23,"?*")&")" | H24: =SUM(H4:H23) | I24: =SUM(I4:I23) | M24: =SUM(M4:M23) | N24: =SUM(N4:N23) | O24: =SUM(O4:O23) | T24: ="ROSTER ("&COUNTIF(T4:T23,"?*")&")" | W24: =SUM(W4:W23) | X24: =SUM(X4:X23) | Y24: =SUM(Y4:Y23) | AD24: ="ROSTER ("&COUNTIF(AD4:AD23,"?*")&")" | AG24: =SUM(AG4:AG23) | AH24: =SUM(AH4:AH23) | AI24: =SUM(AI4:AI23) | AN24: ="ROSTER ("&COUNTIF(AN4:AN23,"?*")&")" | AQ24: =SUM(AQ4:AQ23) | AR24: =SUM(AR4:AR23) | AS24: =SUM(AS4:AS23)
A26: RESERVE - counts toward the cap, does NOT score | T26: RESERVE - counts toward the cap, does NOT score | AD26: RESERVE - counts toward the cap, does NOT score | AN26: RESERVE - counts toward the cap, does NOT score
A27: =IFERROR(IF(INDEX(Rosters!$B$2:$B$516,$S27)="","",INDEX(Rosters!$B$2:$B$516,$S27)),"") | B27: =IFERROR(IF(INDEX(Rosters!$C$2:$C$516,$S27)="","",INDEX(Rosters!$C$2:$C$516,$S27)),"") | C27: =IFERROR(IF(INDEX(Rosters!$D$2:$D$516,$S27)="","",INDEX(Rosters!$D$2:$D$516,$S27)),"") | D27: =IFERROR(IF(INDEX(Rosters!$E$2:$E$516,$S27)="","",INDEX(Rosters!$E$2:$E$516,$S27)),"") | E27: =IFERROR(IF(INDEX(Rosters!$F$2:$F$516,$S27)="","",INDEX(Rosters!$F$2:$F$516,$S27)),"") | F27: =IFERROR(IF(INDEX(Rosters!$G$2:$G$516,$S27)="","",INDEX(Rosters!$G$2:$G$516,$S27)),"") | G27: =IFERROR(IF(INDEX(Rosters!$H$2:$H$516,$S27)="","",INDEX(Rosters!$H$2:$H$516,$S27)),"") | H27: =IFERROR(IF(INDEX(Rosters!$I$2:$I$516,$S27)="","",INDEX(Rosters!$I$2:$I$516,$S27)),"") | I27: =IFERROR(IF(INDEX(Rosters!$J$2:$J$516,$S27)="","",INDEX(Rosters!$J$2:$J$516,$S27)),"") | J27: =IFERROR(IF(INDEX(Rosters!$S$2:$S$516,$S27)="","",INDEX(Rosters!$S$2:$S$516,$S27)),"") | K27: =IFERROR(IF(INDEX(Rosters!$K$2:$K$516,$S27)="","",INDEX(Rosters!$K$2:$K$516,$S27)),"") | L27: =IFERROR(IF(INDEX(Rosters!$T$2:$T$516,$S27)="","",INDEX(Rosters!$T$2:$T$516,$S27)),"") | M27: =IFERROR(IF(INDEX(Rosters!$L$2:$L$516,$S27)="","",INDEX(Rosters!$L$2:$L$516,$S27)),"") | N27: =IFERROR(IF(INDEX(Rosters!$Q$2:$Q$516,$S27)="","",INDEX(Rosters!$Q$2:$Q$516,$S27)),"") | O27: =IFERROR(IF(INDEX(Rosters!$R$2:$R$516,$S27)="","",INDEX(Rosters!$R$2:$R$516,$S27)),"") | P27: =IFERROR(IF(INDEX(Rosters!$N$2:$N$516,$S27)="","",INDEX(Rosters!$N$2:$N$516,$S27)),"") | Q27: =IFERROR(IF(INDEX(Rosters!$O$2:$O$516,$S27)="","",INDEX(Rosters!$O$2:$O$516,$S27)),"") | R27: =IFERROR(IF(INDEX(Rosters!$P$2:$P$516,$S27)="","",INDEX(Rosters!$P$2:$P$516,$S27)),"") | S27: =IFERROR(MATCH('League Settings'!$B$2&"|RESERVE|"&1,Rosters!$AD$2:$AD$516,0),"") | T27: Joseph Woll (PHI G) | U27: =IFERROR(IF(INDEX('Player Pool'!$D$2:$D$8725,MATCH($T27,'Player Pool'!$Z$2:$Z$8725,0))="","",INDEX('Player Pool'!$D$2:$D$8725,MATCH($T27,'Player Pool'!$Z$2:$Z$8725,0))),"") | V27: =IFERROR(IF(INDEX('Player Pool'!$E$2:$E$8725,MATCH($T27,'Player Pool'!$Z$2:$Z$8725,0))="","",INDEX('Player Pool'!$E$2:$E$8725,MATCH($T27,'Player Pool'!$Z$2:$Z$8725,0))),"") | W27: =IFERROR(IF($T27="","",IF(ISNUMBER(IFERROR(INDEX(Rosters!$I$2:$I$516,MATCH(INDEX('Player Pool'!$V$2:$V$8725,MATCH($T27,'Player Pool'!$Z$2:$Z$8725,0)),Rosters!$W$2:$W$516,0)),"")),IFERROR(INDEX(Rosters!$I$2:$I$516,MATCH(INDEX('Player Pool'!$V$2:$V$8725,MATCH($T27,'Player Pool'!$Z$2:$Z$8725,0)),Rosters!$W$2:$W$516,0)),""),INDEX('Player Pool'!$H$2:$H$8725,MATCH($T27,'Player Pool'!$Z$2:$Z$8725,0)))),"") | X27: =IFERROR(IF(INDEX('Player Pool'!$I$2:$I$8725,MATCH($T27,'Player Pool'!$Z$2:$Z$8725,0))="","",INDEX('Player Pool'!$I$2:$I$8725,MATCH($T27,'Player Pool'!$Z$2:$Z$8725,0))),"") | Y27: =IFERROR(IF(INDEX('Player Pool'!$P$2:$P$8725,MATCH($T27,'Player Pool'!$Z$2:$Z$8725,0))="","",INDEX('Player Pool'!$P$2:$P$8725,MATCH($T27,'Player Pool'!$Z$2:$Z$8725,0))),"") | Z27: =IFERROR(IF(INDEX('Player Pool'!$R$2:$R$8725,MATCH($T27,'Player Pool'!$Z$2:$Z$8725,0))="","",INDEX('Player Pool'!$R$2:$R$8725,MATCH($T27,'Player Pool'!$Z$2:$Z$8725,0))),"") | AA27: =IFERROR(IF(INDEX('Player Pool'!$U$2:$U$8725,MATCH($T27,'Player Pool'!$Z$2:$Z$8725,0))="","",INDEX('Player Pool'!$U$2:$U$8725,MATCH($T27,'Player Pool'!$Z$2:$Z$8725,0))),"") | AB27: =IFERROR(IF($T27="","",IF(INDEX('Player Pool'!$G$2:$G$8725,MATCH($T27,'Player Pool'!$Z$2:$Z$8725,0))="FA","FA",IF(INDEX('Player Pool'!$G$2:$G$8725,MATCH($T27,'Player Pool'!$Z$2:$Z$8725,0))='League Settings'!$B$2,"MINE","TAKEN"))),"") | AD27: Joseph Woll (PHI G) | AE27: =IFERROR(IF(INDEX('Player Pool'!$D$2:$D$8725,MATCH($AD27,'Player Pool'!$Z$2:$Z$8725,0))="","",INDEX('Player Pool'!$D$2:$D$8725,MATCH($AD27,'Player Pool'!$Z$2:$Z$8725,0))),"") | AF27: =IFERROR(IF(INDEX('Player Pool'!$E$2:$E$8725,MATCH($AD27,'Player Pool'!$Z$2:$Z$8725,0))="","",INDEX('Player Pool'!$E$2:$E$8725,MATCH($AD27,'Player Pool'!$Z$2:$Z$8725,0))),"") | AG27: =IFERROR(IF($AD27="","",IF(ISNUMBER(IFERROR(INDEX(Rosters!$I$2:$I$516,MATCH(INDEX('Player Pool'!$V$2:$V$8725,MATCH($AD27,'Player Pool'!$Z$2:$Z$8725,0)),Rosters!$W$2:$W$516,0)),"")),IFERROR(INDEX(Rosters!$I$2:$I$516,MATCH(INDEX('Player Pool'!$V$2:$V$8725,MATCH($AD27,'Player Pool'!$Z$2:$Z$8725,0)),Rosters!$W$2:$W$516,0)),""),INDEX('Player Pool'!$H$2:$H$8725,MATCH($AD27,'Player Pool'!$Z$2:$Z$8725,0)))),"") | AH27: =IFERROR(IF(INDEX('Player Pool'!$I$2:$I$8725,MATCH($AD27,'Player Pool'!$Z$2:$Z$8725,0))="","",INDEX('Player Pool'!$I$2:$I$8725,MATCH($AD27,'Player Pool'!$Z$2:$Z$8725,0))),"") | AI27: =IFERROR(IF(INDEX('Player Pool'!$P$2:$P$8725,MATCH($AD27,'Player Pool'!$Z$2:$Z$8725,0))="","",INDEX('Player Pool'!$P$2:$P$8725,MATCH($AD27,'Player Pool'!$Z$2:$Z$8725,0))),"") | AJ27: =IFERROR(IF(INDEX('Player Pool'!$R$2:$R$8725,MATCH($AD27,'Player Pool'!$Z$2:$Z$8725,0))="","",INDEX('Player Pool'!$R$2:$R$8725,MATCH($AD27,'Player Pool'!$Z$2:$Z$8725,0))),"") | AK27: =IFERROR(IF(INDEX('Player Pool'!$U$2:$U$8725,MATCH($AD27,'Player Pool'!$Z$2:$Z$8725,0))="","",INDEX('Player Pool'!$U$2:$U$8725,MATCH($AD27,'Player Pool'!$Z$2:$Z$8725,0))),"") | AL27: =IFERROR(IF($AD27="","",IF(INDEX('Player Pool'!$G$2:$G$8725,MATCH($AD27,'Player Pool'!$Z$2:$Z$8725,0))="FA","FA",IF(INDEX('Player Pool'!$G$2:$G$8725,MATCH($AD27,'Player Pool'!$Z$2:$Z$8725,0))='League Settings'!$B$2,"MINE","TAKEN"))),"") | AN27: Joseph Woll (PHI G) | AO27: =IFERROR(IF(INDEX('Player Pool'!$D$2:$D$8725,MATCH($AN27,'Player Pool'!$Z$2:$Z$8725,0))="","",INDEX('Player Pool'!$D$2:$D$8725,MATCH($AN27,'Player Pool'!$Z$2:$Z$8725,0))),"") | AP27: =IFERROR(IF(INDEX('Player Pool'!$E$2:$E$8725,MATCH($AN27,'Player Pool'!$Z$2:$Z$8725,0))="","",INDEX('Player Pool'!$E$2:$E$8725,MATCH($AN27,'Player Pool'!$Z$2:$Z$8725,0))),"") | AQ27: =IFERROR(IF($AN27="","",IF(ISNUMBER(IFERROR(INDEX(Rosters!$I$2:$I$516,MATCH(INDEX('Player Pool'!$V$2:$V$8725,MATCH($AN27,'Player Pool'!$Z$2:$Z$8725,0)),Rosters!$W$2:$W$516,0)),"")),IFERROR(INDEX(Rosters!$I$2:$I$516,MATCH(INDEX('Player Pool'!$V$2:$V$8725,MATCH($AN27,'Player Pool'!$Z$2:$Z$8725,0)),Rosters!$W$2:$W$516,0)),""),INDEX('Player Pool'!$H$2:$H$8725,MATCH($AN27,'Player Pool'!$Z$2:$Z$8725,0)))),"") | AR27: =IFERROR(IF(INDEX('Player Pool'!$I$2:$I$8725,MATCH($AN27,'Player Pool'!$Z$2:$Z$8725,0))="","",INDEX('Player Pool'!$I$2:$I$8725,MATCH($AN27,'Player Pool'!$Z$2:$Z$8725,0))),"") | AS27: =IFERROR(IF(INDEX('Player Pool'!$P$2:$P$8725,MATCH($AN27,'Player Pool'!$Z$2:$Z$8725,0))="","",INDEX('Player Pool'!$P$2:$P$8725,MATCH($AN27,'Player Pool'!$Z$2:$Z$8725,0))),"") | AT27: =IFERROR(IF(INDEX('Player Pool'!$R$2:$R$8725,MATCH($AN27,'Player Pool'!$Z$2:$Z$8725,0))="","",INDEX('Player Pool'!$R$2:$R$8725,MATCH($AN27,'Player Pool'!$Z$2:$Z$8725,0))),"") | AU27: =IFERROR(IF(INDEX('Player Pool'!$U$2:$U$8725,MATCH($AN27,'Player Pool'!$Z$2:$Z$8725,0))="","",INDEX('Player Pool'!$U$2:$U$8725,MATCH($AN27,'Player Pool'!$Z$2:$Z$8725,0))),"") | AV27: =IFERROR(IF($AN27="","",IF(INDEX('Player Pool'!$G$2:$G$8725,MATCH($AN27,'Player Pool'!$Z$2:$Z$8725,0))="FA","FA",IF(INDEX('Player Pool'!$G$2:$G$8725,MATCH($AN27,'Player Pool'!$Z$2:$Z$8725,0))='League Settings'!$B$2,"MINE","TAKEN"))),"")
A28: =IFERROR(IF(INDEX(Rosters!$B$2:$B$516,$S28)="","",INDEX(Rosters!$B$2:$B$516,$S28)),"") | B28: =IFERROR(IF(INDEX(Rosters!$C$2:$C$516,$S28)="","",INDEX(Rosters!$C$2:$C$516,$S28)),"") | C28: =IFERROR(IF(INDEX(Rosters!$D$2:$D$516,$S28)="","",INDEX(Rosters!$D$2:$D$516,$S28)),"") | D28: =IFERROR(IF(INDEX(Rosters!$E$2:$E$516,$S28)="","",INDEX(Rosters!$E$2:$E$516,$S28)),"") | E28: =IFERROR(IF(INDEX(Rosters!$F$2:$F$516,$S28)="","",INDEX(Rosters!$F$2:$F$516,$S28)),"") | F28: =IFERROR(IF(INDEX(Rosters!$G$2:$G$516,$S28)="","",INDEX(Rosters!$G$2:$G$516,$S28)),"") | G28: =IFERROR(IF(INDEX(Rosters!$H$2:$H$516,$S28)="","",INDEX(Rosters!$H$2:$H$516,$S28)),"") | H28: =IFERROR(IF(INDEX(Rosters!$I$2:$I$516,$S28)="","",INDEX(Rosters!$I$2:$I$516,$S28)),"") | I28: =IFERROR(IF(INDEX(Rosters!$J$2:$J$516,$S28)="","",INDEX(Rosters!$J$2:$J$516,$S28)),"") | J28: =IFERROR(IF(INDEX(Rosters!$S$2:$S$516,$S28)="","",INDEX(Rosters!$S$2:$S$516,$S28)),"") | K28: =IFERROR(IF(INDEX(Rosters!$K$2:$K$516,$S28)="","",INDEX(Rosters!$K$2:$K$516,$S28)),"") | L28: =IFERROR(IF(INDEX(Rosters!$T$2:$T$516,$S28)="","",INDEX(Rosters!$T$2:$T$516,$S28)),"") | M28: =IFERROR(IF(INDEX(Rosters!$L$2:$L$516,$S28)="","",INDEX(Rosters!$L$2:$L$516,$S28)),"") | N28: =IFERROR(IF(INDEX(Rosters!$Q$2:$Q$516,$S28)="","",INDEX(Rosters!$Q$2:$Q$516,$S28)),"") | O28: =IFERROR(IF(INDEX(Rosters!$R$2:$R$516,$S28)="","",INDEX(Rosters!$R$2:$R$516,$S28)),"") | P28: =IFERROR(IF(INDEX(Rosters!$N$2:$N$516,$S28)="","",INDEX(Rosters!$N$2:$N$516,$S28)),"") | Q28: =IFERROR(IF(INDEX(Rosters!$O$2:$O$516,$S28)="","",INDEX(Rosters!$O$2:$O$516,$S28)),"") | R28: =IFERROR(IF(INDEX(Rosters!$P$2:$P$516,$S28)="","",INDEX(Rosters!$P$2:$P$516,$S28)),"") | S28: =IFERROR(MATCH('League Settings'!$B$2&"|RESERVE|"&2,Rosters!$AD$2:$AD$516,0),"") | U28: =IFERROR(IF(INDEX('Player Pool'!$D$2:$D$8725,MATCH($T28,'Player Pool'!$Z$2:$Z$8725,0))="","",INDEX('Player Pool'!$D$2:$D$8725,MATCH($T28,'Player Pool'!$Z$2:$Z$8725,0))),"") | V28: =IFERROR(IF(INDEX('Player Pool'!$E$2:$E$8725,MATCH($T28,'Player Pool'!$Z$2:$Z$8725,0))="","",INDEX('Player Pool'!$E$2:$E$8725,MATCH($T28,'Player Pool'!$Z$2:$Z$8725,0))),"") | W28: =IFERROR(IF($T28="","",IF(ISNUMBER(IFERROR(INDEX(Rosters!$I$2:$I$516,MATCH(INDEX('Player Pool'!$V$2:$V$8725,MATCH($T28,'Player Pool'!$Z$2:$Z$8725,0)),Rosters!$W$2:$W$516,0)),"")),IFERROR(INDEX(Rosters!$I$2:$I$516,MATCH(INDEX('Player Pool'!$V$2:$V$8725,MATCH($T28,'Player Pool'!$Z$2:$Z$8725,0)),Rosters!$W$2:$W$516,0)),""),INDEX('Player Pool'!$H$2:$H$8725,MATCH($T28,'Player Pool'!$Z$2:$Z$8725,0)))),"") | X28: =IFERROR(IF(INDEX('Player Pool'!$I$2:$I$8725,MATCH($T28,'Player Pool'!$Z$2:$Z$8725,0))="","",INDEX('Player Pool'!$I$2:$I$8725,MATCH($T28,'Player Pool'!$Z$2:$Z$8725,0))),"") | Y28: =IFERROR(IF(INDEX('Player Pool'!$P$2:$P$8725,MATCH($T28,'Player Pool'!$Z$2:$Z$8725,0))="","",INDEX('Player Pool'!$P$2:$P$8725,MATCH($T28,'Player Pool'!$Z$2:$Z$8725,0))),"") | Z28: =IFERROR(IF(INDEX('Player Pool'!$R$2:$R$8725,MATCH($T28,'Player Pool'!$Z$2:$Z$8725,0))="","",INDEX('Player Pool'!$R$2:$R$8725,MATCH($T28,'Player Pool'!$Z$2:$Z$8725,0))),"") | AA28: =IFERROR(IF(INDEX('Player Pool'!$U$2:$U$8725,MATCH($T28,'Player Pool'!$Z$2:$Z$8725,0))="","",INDEX('Player Pool'!$U$2:$U$8725,MATCH($T28,'Player Pool'!$Z$2:$Z$8725,0))),"") | AB28: =IFERROR(IF($T28="","",IF(INDEX('Player Pool'!$G$2:$G$8725,MATCH($T28,'Player Pool'!$Z$2:$Z$8725,0))="FA","FA",IF(INDEX('Player Pool'!$G$2:$G$8725,MATCH($T28,'Player Pool'!$Z$2:$Z$8725,0))='League Settings'!$B$2,"MINE","TAKEN"))),"") | AE28: =IFERROR(IF(INDEX('Player Pool'!$D$2:$D$8725,MATCH($AD28,'Player Pool'!$Z$2:$Z$8725,0))="","",INDEX('Player Pool'!$D$2:$D$8725,MATCH($AD28,'Player Pool'!$Z$2:$Z$8725,0))),"") | AF28: =IFERROR(IF(INDEX('Player Pool'!$E$2:$E$8725,MATCH($AD28,'Player Pool'!$Z$2:$Z$8725,0))="","",INDEX('Player Pool'!$E$2:$E$8725,MATCH($AD28,'Player Pool'!$Z$2:$Z$8725,0))),"") | AG28: =IFERROR(IF($AD28="","",IF(ISNUMBER(IFERROR(INDEX(Rosters!$I$2:$I$516,MATCH(INDEX('Player Pool'!$V$2:$V$8725,MATCH($AD28,'Player Pool'!$Z$2:$Z$8725,0)),Rosters!$W$2:$W$516,0)),"")),IFERROR(INDEX(Rosters!$I$2:$I$516,MATCH(INDEX('Player Pool'!$V$2:$V$8725,MATCH($AD28,'Player Pool'!$Z$2:$Z$8725,0)),Rosters!$W$2:$W$516,0)),""),INDEX('Player Pool'!$H$2:$H$8725,MATCH($AD28,'Player Pool'!$Z$2:$Z$8725,0)))),"") | AH28: =IFERROR(IF(INDEX('Player Pool'!$I$2:$I$8725,MATCH($AD28,'Player Pool'!$Z$2:$Z$8725,0))="","",INDEX('Player Pool'!$I$2:$I$8725,MATCH($AD28,'Player Pool'!$Z$2:$Z$8725,0))),"") | AI28: =IFERROR(IF(INDEX('Player Pool'!$P$2:$P$8725,MATCH($AD28,'Player Pool'!$Z$2:$Z$8725,0))="","",INDEX('Player Pool'!$P$2:$P$8725,MATCH($AD28,'Player Pool'!$Z$2:$Z$8725,0))),"") | AJ28: =IFERROR(IF(INDEX('Player Pool'!$R$2:$R$8725,MATCH($AD28,'Player Pool'!$Z$2:$Z$8725,0))="","",INDEX('Player Pool'!$R$2:$R$8725,MATCH($AD28,'Player Pool'!$Z$2:$Z$8725,0))),"") | AK28: =IFERROR(IF(INDEX('Player Pool'!$U$2:$U$8725,MATCH($AD28,'Player Pool'!$Z$2:$Z$8725,0))="","",INDEX('Player Pool'!$U$2:$U$8725,MATCH($AD28,'Player Pool'!$Z$2:$Z$8725,0))),"") | AL28: =IFERROR(IF($AD28="","",IF(INDEX('Player Pool'!$G$2:$G$8725,MATCH($AD28,'Player Pool'!$Z$2:$Z$8725,0))="FA","FA",IF(INDEX('Player Pool'!$G$2:$G$8725,MATCH($AD28,'Player Pool'!$Z$2:$Z$8725,0))='League Settings'!$B$2,"MINE","TAKEN"))),"") | AO28: =IFERROR(IF(INDEX('Player Pool'!$D$2:$D$8725,MATCH($AN28,'Player Pool'!$Z$2:$Z$8725,0))="","",INDEX('Player Pool'!$D$2:$D$8725,MATCH($AN28,'Player Pool'!$Z$2:$Z$8725,0))),"") | AP28: =IFERROR(IF(INDEX('Player Pool'!$E$2:$E$8725,MATCH($AN28,'Player Pool'!$Z$2:$Z$8725,0))="","",INDEX('Player Pool'!$E$2:$E$8725,MATCH($AN28,'Player Pool'!$Z$2:$Z$8725,0))),"") | AQ28: =IFERROR(IF($AN28="","",IF(ISNUMBER(IFERROR(INDEX(Rosters!$I$2:$I$516,MATCH(INDEX('Player Pool'!$V$2:$V$8725,MATCH($AN28,'Player Pool'!$Z$2:$Z$8725,0)),Rosters!$W$2:$W$516,0)),"")),IFERROR(INDEX(Rosters!$I$2:$I$516,MATCH(INDEX('Player Pool'!$V$2:$V$8725,MATCH($AN28,'Player Pool'!$Z$2:$Z$8725,0)),Rosters!$W$2:$W$516,0)),""),INDEX('Player Pool'!$H$2:$H$8725,MATCH($AN28,'Player Pool'!$Z$2:$Z$8725,0)))),"") | AR28: =IFERROR(IF(INDEX('Player Pool'!$I$2:$I$8725,MATCH($AN28,'Player Pool'!$Z$2:$Z$8725,0))="","",INDEX('Player Pool'!$I$2:$I$8725,MATCH($AN28,'Player Pool'!$Z$2:$Z$8725,0))),"") | AS28: =IFERROR(IF(INDEX('Player Pool'!$P$2:$P$8725,MATCH($AN28,'Player Pool'!$Z$2:$Z$8725,0))="","",INDEX('Player Pool'!$P$2:$P$8725,MATCH($AN28,'Player Pool'!$Z$2:$Z$8725,0))),"") | AT28: =IFERROR(IF(INDEX('Player Pool'!$R$2:$R$8725,MATCH($AN28,'Player Pool'!$Z$2:$Z$8725,0))="","",INDEX('Player Pool'!$R$2:$R$8725,MATCH($AN28,'Player Pool'!$Z$2:$Z$8725,0))),"") | AU28: =IFERROR(IF(INDEX('Player Pool'!$U$2:$U$8725,MATCH($AN28,'Player Pool'!$Z$2:$Z$8725,0))="","",INDEX('Player Pool'!$U$2:$U$8725,MATCH($AN28,'Player Pool'!$Z$2:$Z$8725,0))),"") | AV28: =IFERROR(IF($AN28="","",IF(INDEX('Player Pool'!$G$2:$G$8725,MATCH($AN28,'Player Pool'!$Z$2:$Z$8725,0))="FA","FA",IF(INDEX('Player Pool'!$G$2:$G$8725,MATCH($AN28,'Player Pool'!$Z$2:$Z$8725,0))='League Settings'!$B$2,"MINE","TAKEN"))),"")
A29: =IFERROR(IF(INDEX(Rosters!$B$2:$B$516,$S29)="","",INDEX(Rosters!$B$2:$B$516,$S29)),"") | B29: =IFERROR(IF(INDEX(Rosters!$C$2:$C$516,$S29)="","",INDEX(Rosters!$C$2:$C$516,$S29)),"") | C29: =IFERROR(IF(INDEX(Rosters!$D$2:$D$516,$S29)="","",INDEX(Rosters!$D$2:$D$516,$S29)),"") | D29: =IFERROR(IF(INDEX(Rosters!$E$2:$E$516,$S29)="","",INDEX(Rosters!$E$2:$E$516,$S29)),"") | E29: =IFERROR(IF(INDEX(Rosters!$F$2:$F$516,$S29)="","",INDEX(Rosters!$F$2:$F$516,$S29)),"") | F29: =IFERROR(IF(INDEX(Rosters!$G$2:$G$516,$S29)="","",INDEX(Rosters!$G$2:$G$516,$S29)),"") | G29: =IFERROR(IF(INDEX(Rosters!$H$2:$H$516,$S29)="","",INDEX(Rosters!$H$2:$H$516,$S29)),"") | H29: =IFERROR(IF(INDEX(Rosters!$I$2:$I$516,$S29)="","",INDEX(Rosters!$I$2:$I$516,$S29)),"") | I29: =IFERROR(IF(INDEX(Rosters!$J$2:$J$516,$S29)="","",INDEX(Rosters!$J$2:$J$516,$S29)),"") | J29: =IFERROR(IF(INDEX(Rosters!$S$2:$S$516,$S29)="","",INDEX(Rosters!$S$2:$S$516,$S29)),"") | K29: =IFERROR(IF(INDEX(Rosters!$K$2:$K$516,$S29)="","",INDEX(Rosters!$K$2:$K$516,$S29)),"") | L29: =IFERROR(IF(INDEX(Rosters!$T$2:$T$516,$S29)="","",INDEX(Rosters!$T$2:$T$516,$S29)),"") | M29: =IFERROR(IF(INDEX(Rosters!$L$2:$L$516,$S29)="","",INDEX(Rosters!$L$2:$L$516,$S29)),"") | N29: =IFERROR(IF(INDEX(Rosters!$Q$2:$Q$516,$S29)="","",INDEX(Rosters!$Q$2:$Q$516,$S29)),"") | O29: =IFERROR(IF(INDEX(Rosters!$R$2:$R$516,$S29)="","",INDEX(Rosters!$R$2:$R$516,$S29)),"") | P29: =IFERROR(IF(INDEX(Rosters!$N$2:$N$516,$S29)="","",INDEX(Rosters!$N$2:$N$516,$S29)),"") | Q29: =IFERROR(IF(INDEX(Rosters!$O$2:$O$516,$S29)="","",INDEX(Rosters!$O$2:$O$516,$S29)),"") | R29: =IFERROR(IF(INDEX(Rosters!$P$2:$P$516,$S29)="","",INDEX(Rosters!$P$2:$P$516,$S29)),"") | S29: =IFERROR(MATCH('League Settings'!$B$2&"|RESERVE|"&3,Rosters!$AD$2:$AD$516,0),"") | U29: =IFERROR(IF(INDEX('Player Pool'!$D$2:$D$8725,MATCH($T29,'Player Pool'!$Z$2:$Z$8725,0))="","",INDEX('Player Pool'!$D$2:$D$8725,MATCH($T29,'Player Pool'!$Z$2:$Z$8725,0))),"") | V29: =IFERROR(IF(INDEX('Player Pool'!$E$2:$E$8725,MATCH($T29,'Player Pool'!$Z$2:$Z$8725,0))="","",INDEX('Player Pool'!$E$2:$E$8725,MATCH($T29,'Player Pool'!$Z$2:$Z$8725,0))),"") | W29: =IFERROR(IF($T29="","",IF(ISNUMBER(IFERROR(INDEX(Rosters!$I$2:$I$516,MATCH(INDEX('Player Pool'!$V$2:$V$8725,MATCH($T29,'Player Pool'!$Z$2:$Z$8725,0)),Rosters!$W$2:$W$516,0)),"")),IFERROR(INDEX(Rosters!$I$2:$I$516,MATCH(INDEX('Player Pool'!$V$2:$V$8725,MATCH($T29,'Player Pool'!$Z$2:$Z$8725,0)),Rosters!$W$2:$W$516,0)),""),INDEX('Player Pool'!$H$2:$H$8725,MATCH($T29,'Player Pool'!$Z$2:$Z$8725,0)))),"") | X29: =IFERROR(IF(INDEX('Player Pool'!$I$2:$I$8725,MATCH($T29,'Player Pool'!$Z$2:$Z$8725,0))="","",INDEX('Player Pool'!$I$2:$I$8725,MATCH($T29,'Player Pool'!$Z$2:$Z$8725,0))),"") | Y29: =IFERROR(IF(INDEX('Player Pool'!$P$2:$P$8725,MATCH($T29,'Player Pool'!$Z$2:$Z$8725,0))="","",INDEX('Player Pool'!$P$2:$P$8725,MATCH($T29,'Player Pool'!$Z$2:$Z$8725,0))),"") | Z29: =IFERROR(IF(INDEX('Player Pool'!$R$2:$R$8725,MATCH($T29,'Player Pool'!$Z$2:$Z$8725,0))="","",INDEX('Player Pool'!$R$2:$R$8725,MATCH($T29,'Player Pool'!$Z$2:$Z$8725,0))),"") | AA29: =IFERROR(IF(INDEX('Player Pool'!$U$2:$U$8725,MATCH($T29,'Player Pool'!$Z$2:$Z$8725,0))="","",INDEX('Player Pool'!$U$2:$U$8725,MATCH($T29,'Player Pool'!$Z$2:$Z$8725,0))),"") | AB29: =IFERROR(IF($T29="","",IF(INDEX('Player Pool'!$G$2:$G$8725,MATCH($T29,'Player Pool'!$Z$2:$Z$8725,0))="FA","FA",IF(INDEX('Player Pool'!$G$2:$G$8725,MATCH($T29,'Player Pool'!$Z$2:$Z$8725,0))='League Settings'!$B$2,"MINE","TAKEN"))),"") | AE29: =IFERROR(IF(INDEX('Player Pool'!$D$2:$D$8725,MATCH($AD29,'Player Pool'!$Z$2:$Z$8725,0))="","",INDEX('Player Pool'!$D$2:$D$8725,MATCH($AD29,'Player Pool'!$Z$2:$Z$8725,0))),"") | AF29: =IFERROR(IF(INDEX('Player Pool'!$E$2:$E$8725,MATCH($AD29,'Player Pool'!$Z$2:$Z$8725,0))="","",INDEX('Player Pool'!$E$2:$E$8725,MATCH($AD29,'Player Pool'!$Z$2:$Z$8725,0))),"") | AG29: =IFERROR(IF($AD29="","",IF(ISNUMBER(IFERROR(INDEX(Rosters!$I$2:$I$516,MATCH(INDEX('Player Pool'!$V$2:$V$8725,MATCH($AD29,'Player Pool'!$Z$2:$Z$8725,0)),Rosters!$W$2:$W$516,0)),"")),IFERROR(INDEX(Rosters!$I$2:$I$516,MATCH(INDEX('Player Pool'!$V$2:$V$8725,MATCH($AD29,'Player Pool'!$Z$2:$Z$8725,0)),Rosters!$W$2:$W$516,0)),""),INDEX('Player Pool'!$H$2:$H$8725,MATCH($AD29,'Player Pool'!$Z$2:$Z$8725,0)))),"") | AH29: =IFERROR(IF(INDEX('Player Pool'!$I$2:$I$8725,MATCH($AD29,'Player Pool'!$Z$2:$Z$8725,0))="","",INDEX('Player Pool'!$I$2:$I$8725,MATCH($AD29,'Player Pool'!$Z$2:$Z$8725,0))),"") | AI29: =IFERROR(IF(INDEX('Player Pool'!$P$2:$P$8725,MATCH($AD29,'Player Pool'!$Z$2:$Z$8725,0))="","",INDEX('Player Pool'!$P$2:$P$8725,MATCH($AD29,'Player Pool'!$Z$2:$Z$8725,0))),"") | AJ29: =IFERROR(IF(INDEX('Player Pool'!$R$2:$R$8725,MATCH($AD29,'Player Pool'!$Z$2:$Z$8725,0))="","",INDEX('Player Pool'!$R$2:$R$8725,MATCH($AD29,'Player Pool'!$Z$2:$Z$8725,0))),"") | AK29: =IFERROR(IF(INDEX('Player Pool'!$U$2:$U$8725,MATCH($AD29,'Player Pool'!$Z$2:$Z$8725,0))="","",INDEX('Player Pool'!$U$2:$U$8725,MATCH($AD29,'Player Pool'!$Z$2:$Z$8725,0))),"") | AL29: =IFERROR(IF($AD29="","",IF(INDEX('Player Pool'!$G$2:$G$8725,MATCH($AD29,'Player Pool'!$Z$2:$Z$8725,0))="FA","FA",IF(INDEX('Player Pool'!$G$2:$G$8725,MATCH($AD29,'Player Pool'!$Z$2:$Z$8725,0))='League Settings'!$B$2,"MINE","TAKEN"))),"") | AO29: =IFERROR(IF(INDEX('Player Pool'!$D$2:$D$8725,MATCH($AN29,'Player Pool'!$Z$2:$Z$8725,0))="","",INDEX('Player Pool'!$D$2:$D$8725,MATCH($AN29,'Player Pool'!$Z$2:$Z$8725,0))),"") | AP29: =IFERROR(IF(INDEX('Player Pool'!$E$2:$E$8725,MATCH($AN29,'Player Pool'!$Z$2:$Z$8725,0))="","",INDEX('Player Pool'!$E$2:$E$8725,MATCH($AN29,'Player Pool'!$Z$2:$Z$8725,0))),"") | AQ29: =IFERROR(IF($AN29="","",IF(ISNUMBER(IFERROR(INDEX(Rosters!$I$2:$I$516,MATCH(INDEX('Player Pool'!$V$2:$V$8725,MATCH($AN29,'Player Pool'!$Z$2:$Z$8725,0)),Rosters!$W$2:$W$516,0)),"")),IFERROR(INDEX(Rosters!$I$2:$I$516,MATCH(INDEX('Player Pool'!$V$2:$V$8725,MATCH($AN29,'Player Pool'!$Z$2:$Z$8725,0)),Rosters!$W$2:$W$516,0)),""),INDEX('Player Pool'!$H$2:$H$8725,MATCH($AN29,'Player Pool'!$Z$2:$Z$8725,0)))),"") | AR29: =IFERROR(IF(INDEX('Player Pool'!$I$2:$I$8725,MATCH($AN29,'Player Pool'!$Z$2:$Z$8725,0))="","",INDEX('Player Pool'!$I$2:$I$8725,MATCH($AN29,'Player Pool'!$Z$2:$Z$8725,0))),"") | AS29: =IFERROR(IF(INDEX('Player Pool'!$P$2:$P$8725,MATCH($AN29,'Player Pool'!$Z$2:$Z$8725,0))="","",INDEX('Player Pool'!$P$2:$P$8725,MATCH($AN29,'Player Pool'!$Z$2:$Z$8725,0))),"") | AT29: =IFERROR(IF(INDEX('Player Pool'!$R$2:$R$8725,MATCH($AN29,'Player Pool'!$Z$2:$Z$8725,0))="","",INDEX('Player Pool'!$R$2:$R$8725,MATCH($AN29,'Player Pool'!$Z$2:$Z$8725,0))),"") | AU29: =IFERROR(IF(INDEX('Player Pool'!$U$2:$U$8725,MATCH($AN29,'Player Pool'!$Z$2:$Z$8725,0))="","",INDEX('Player Pool'!$U$2:$U$8725,MATCH($AN29,'Player Pool'!$Z$2:$Z$8725,0))),"") | AV29: =IFERROR(IF($AN29="","",IF(INDEX('Player Pool'!$G$2:$G$8725,MATCH($AN29,'Player Pool'!$Z$2:$Z$8725,0))="FA","FA",IF(INDEX('Player Pool'!$G$2:$G$8725,MATCH($AN29,'Player Pool'!$Z$2:$Z$8725,0))='League Settings'!$B$2,"MINE","TAKEN"))),"")
A30: ="RESERVE subtotal ("&COUNTIF(A27:A29,"?*")&")" | H30: =SUM(H27:H29) | T30: ="RESERVE ("&COUNTIF(T27:T29,"?*")&")" | W30: =SUM(W27:W29) | X30: =SUM(X27:X29) | Y30: =SUM(Y27:Y29) | AD30: ="RESERVE ("&COUNTIF(AD27:AD29,"?*")&")" | AG30: =SUM(AG27:AG29) | AH30: =SUM(AH27:AH29) | AI30: =SUM(AI27:AI29) | AN30: ="RESERVE ("&COUNTIF(AN27:AN29,"?*")&")" | AQ30: =SUM(AQ27:AQ29) | AR30: =SUM(AR27:AR29) | AS30: =SUM(AS27:AS29)
A32: IR - outside the cap, does NOT score | T32: IR - outside the cap, does NOT score | AD32: IR - outside the cap, does NOT score | AN32: IR - outside the cap, does NOT score
A33: =IFERROR(IF(INDEX(Rosters!$B$2:$B$516,$S33)="","",INDEX(Rosters!$B$2:$B$516,$S33)),"") | B33: =IFERROR(IF(INDEX(Rosters!$C$2:$C$516,$S33)="","",INDEX(Rosters!$C$2:$C$516,$S33)),"") | C33: =IFERROR(IF(INDEX(Rosters!$D$2:$D$516,$S33)="","",INDEX(Rosters!$D$2:$D$516,$S33)),"") | D33: =IFERROR(IF(INDEX(Rosters!$E$2:$E$516,$S33)="","",INDEX(Rosters!$E$2:$E$516,$S33)),"") | E33: =IFERROR(IF(INDEX(Rosters!$F$2:$F$516,$S33)="","",INDEX(Rosters!$F$2:$F$516,$S33)),"") | F33: =IFERROR(IF(INDEX(Rosters!$G$2:$G$516,$S33)="","",INDEX(Rosters!$G$2:$G$516,$S33)),"") | G33: =IFERROR(IF(INDEX(Rosters!$H$2:$H$516,$S33)="","",INDEX(Rosters!$H$2:$H$516,$S33)),"") | H33: =IFERROR(IF(INDEX(Rosters!$I$2:$I$516,$S33)="","",INDEX(Rosters!$I$2:$I$516,$S33)),"") | I33: =IFERROR(IF(INDEX(Rosters!$J$2:$J$516,$S33)="","",INDEX(Rosters!$J$2:$J$516,$S33)),"") | J33: =IFERROR(IF(INDEX(Rosters!$S$2:$S$516,$S33)="","",INDEX(Rosters!$S$2:$S$516,$S33)),"") | K33: =IFERROR(IF(INDEX(Rosters!$K$2:$K$516,$S33)="","",INDEX(Rosters!$K$2:$K$516,$S33)),"") | L33: =IFERROR(IF(INDEX(Rosters!$T$2:$T$516,$S33)="","",INDEX(Rosters!$T$2:$T$516,$S33)),"") | M33: =IFERROR(IF(INDEX(Rosters!$L$2:$L$516,$S33)="","",INDEX(Rosters!$L$2:$L$516,$S33)),"") | N33: =IFERROR(IF(INDEX(Rosters!$Q$2:$Q$516,$S33)="","",INDEX(Rosters!$Q$2:$Q$516,$S33)),"") | O33: =IFERROR(IF(INDEX(Rosters!$R$2:$R$516,$S33)="","",INDEX(Rosters!$R$2:$R$516,$S33)),"") | P33: =IFERROR(IF(INDEX(Rosters!$N$2:$N$516,$S33)="","",INDEX(Rosters!$N$2:$N$516,$S33)),"") | Q33: =IFERROR(IF(INDEX(Rosters!$O$2:$O$516,$S33)="","",INDEX(Rosters!$O$2:$O$516,$S33)),"") | R33: =IFERROR(IF(INDEX(Rosters!$P$2:$P$516,$S33)="","",INDEX(Rosters!$P$2:$P$516,$S33)),"") | S33: =IFERROR(MATCH('League Settings'!$B$2&"|INJURED_RESERVE|"&1,Rosters!$AD$2:$AD$516,0),"") | U33: =IFERROR(IF(INDEX('Player Pool'!$D$2:$D$8725,MATCH($T33,'Player Pool'!$Z$2:$Z$8725,0))="","",INDEX('Player Pool'!$D$2:$D$8725,MATCH($T33,'Player Pool'!$Z$2:$Z$8725,0))),"") | V33: =IFERROR(IF(INDEX('Player Pool'!$E$2:$E$8725,MATCH($T33,'Player Pool'!$Z$2:$Z$8725,0))="","",INDEX('Player Pool'!$E$2:$E$8725,MATCH($T33,'Player Pool'!$Z$2:$Z$8725,0))),"") | W33: =IFERROR(IF($T33="","",IF(ISNUMBER(IFERROR(INDEX(Rosters!$I$2:$I$516,MATCH(INDEX('Player Pool'!$V$2:$V$8725,MATCH($T33,'Player Pool'!$Z$2:$Z$8725,0)),Rosters!$W$2:$W$516,0)),"")),IFERROR(INDEX(Rosters!$I$2:$I$516,MATCH(INDEX('Player Pool'!$V$2:$V$8725,MATCH($T33,'Player Pool'!$Z$2:$Z$8725,0)),Rosters!$W$2:$W$516,0)),""),INDEX('Player Pool'!$H$2:$H$8725,MATCH($T33,'Player Pool'!$Z$2:$Z$8725,0)))),"") | X33: =IFERROR(IF(INDEX('Player Pool'!$I$2:$I$8725,MATCH($T33,'Player Pool'!$Z$2:$Z$8725,0))="","",INDEX('Player Pool'!$I$2:$I$8725,MATCH($T33,'Player Pool'!$Z$2:$Z$8725,0))),"") | Y33: =IFERROR(IF(INDEX('Player Pool'!$P$2:$P$8725,MATCH($T33,'Player Pool'!$Z$2:$Z$8725,0))="","",INDEX('Player Pool'!$P$2:$P$8725,MATCH($T33,'Player Pool'!$Z$2:$Z$8725,0))),"") | Z33: =IFERROR(IF(INDEX('Player Pool'!$R$2:$R$8725,MATCH($T33,'Player Pool'!$Z$2:$Z$8725,0))="","",INDEX('Player Pool'!$R$2:$R$8725,MATCH($T33,'Player Pool'!$Z$2:$Z$8725,0))),"") | AA33: =IFERROR(IF(INDEX('Player Pool'!$U$2:$U$8725,MATCH($T33,'Player Pool'!$Z$2:$Z$8725,0))="","",INDEX('Player Pool'!$U$2:$U$8725,MATCH($T33,'Player Pool'!$Z$2:$Z$8725,0))),"") | AB33: =IFERROR(IF($T33="","",IF(INDEX('Player Pool'!$G$2:$G$8725,MATCH($T33,'Player Pool'!$Z$2:$Z$8725,0))="FA","FA",IF(INDEX('Player Pool'!$G$2:$G$8725,MATCH($T33,'Player Pool'!$Z$2:$Z$8725,0))='League Settings'!$B$2,"MINE","TAKEN"))),"") | AE33: =IFERROR(IF(INDEX('Player Pool'!$D$2:$D$8725,MATCH($AD33,'Player Pool'!$Z$2:$Z$8725,0))="","",INDEX('Player Pool'!$D$2:$D$8725,MATCH($AD33,'Player Pool'!$Z$2:$Z$8725,0))),"") | AF33: =IFERROR(IF(INDEX('Player Pool'!$E$2:$E$8725,MATCH($AD33,'Player Pool'!$Z$2:$Z$8725,0))="","",INDEX('Player Pool'!$E$2:$E$8725,MATCH($AD33,'Player Pool'!$Z$2:$Z$8725,0))),"") | AG33: =IFERROR(IF($AD33="","",IF(ISNUMBER(IFERROR(INDEX(Rosters!$I$2:$I$516,MATCH(INDEX('Player Pool'!$V$2:$V$8725,MATCH($AD33,'Player Pool'!$Z$2:$Z$8725,0)),Rosters!$W$2:$W$516,0)),"")),IFERROR(INDEX(Rosters!$I$2:$I$516,MATCH(INDEX('Player Pool'!$V$2:$V$8725,MATCH($AD33,'Player Pool'!$Z$2:$Z$8725,0)),Rosters!$W$2:$W$516,0)),""),INDEX('Player Pool'!$H$2:$H$8725,MATCH($AD33,'Player Pool'!$Z$2:$Z$8725,0)))),"") | AH33: =IFERROR(IF(INDEX('Player Pool'!$I$2:$I$8725,MATCH($AD33,'Player Pool'!$Z$2:$Z$8725,0))="","",INDEX('Player Pool'!$I$2:$I$8725,MATCH($AD33,'Player Pool'!$Z$2:$Z$8725,0))),"") | AI33: =IFERROR(IF(INDEX('Player Pool'!$P$2:$P$8725,MATCH($AD33,'Player Pool'!$Z$2:$Z$8725,0))="","",INDEX('Player Pool'!$P$2:$P$8725,MATCH($AD33,'Player Pool'!$Z$2:$Z$8725,0))),"") | AJ33: =IFERROR(IF(INDEX('Player Pool'!$R$2:$R$8725,MATCH($AD33,'Player Pool'!$Z$2:$Z$8725,0))="","",INDEX('Player Pool'!$R$2:$R$8725,MATCH($AD33,'Player Pool'!$Z$2:$Z$8725,0))),"") | AK33: =IFERROR(IF(INDEX('Player Pool'!$U$2:$U$8725,MATCH($AD33,'Player Pool'!$Z$2:$Z$8725,0))="","",INDEX('Player Pool'!$U$2:$U$8725,MATCH($AD33,'Player Pool'!$Z$2:$Z$8725,0))),"") | AL33: =IFERROR(IF($AD33="","",IF(INDEX('Player Pool'!$G$2:$G$8725,MATCH($AD33,'Player Pool'!$Z$2:$Z$8725,0))="FA","FA",IF(INDEX('Player Pool'!$G$2:$G$8725,MATCH($AD33,'Player Pool'!$Z$2:$Z$8725,0))='League Settings'!$B$2,"MINE","TAKEN"))),"") | AO33: =IFERROR(IF(INDEX('Player Pool'!$D$2:$D$8725,MATCH($AN33,'Player Pool'!$Z$2:$Z$8725,0))="","",INDEX('Player Pool'!$D$2:$D$8725,MATCH($AN33,'Player Pool'!$Z$2:$Z$8725,0))),"") | AP33: =IFERROR(IF(INDEX('Player Pool'!$E$2:$E$8725,MATCH($AN33,'Player Pool'!$Z$2:$Z$8725,0))="","",INDEX('Player Pool'!$E$2:$E$8725,MATCH($AN33,'Player Pool'!$Z$2:$Z$8725,0))),"") | AQ33: =IFERROR(IF($AN33="","",IF(ISNUMBER(IFERROR(INDEX(Rosters!$I$2:$I$516,MATCH(INDEX('Player Pool'!$V$2:$V$8725,MATCH($AN33,'Player Pool'!$Z$2:$Z$8725,0)),Rosters!$W$2:$W$516,0)),"")),IFERROR(INDEX(Rosters!$I$2:$I$516,MATCH(INDEX('Player Pool'!$V$2:$V$8725,MATCH($AN33,'Player Pool'!$Z$2:$Z$8725,0)),Rosters!$W$2:$W$516,0)),""),INDEX('Player Pool'!$H$2:$H$8725,MATCH($AN33,'Player Pool'!$Z$2:$Z$8725,0)))),"") | AR33: =IFERROR(IF(INDEX('Player Pool'!$I$2:$I$8725,MATCH($AN33,'Player Pool'!$Z$2:$Z$8725,0))="","",INDEX('Player Pool'!$I$2:$I$8725,MATCH($AN33,'Player Pool'!$Z$2:$Z$8725,0))),"") | AS33: =IFERROR(IF(INDEX('Player Pool'!$P$2:$P$8725,MATCH($AN33,'Player Pool'!$Z$2:$Z$8725,0))="","",INDEX('Player Pool'!$P$2:$P$8725,MATCH($AN33,'Player Pool'!$Z$2:$Z$8725,0))),"") | AT33: =IFERROR(IF(INDEX('Player Pool'!$R$2:$R$8725,MATCH($AN33,'Player Pool'!$Z$2:$Z$8725,0))="","",INDEX('Player Pool'!$R$2:$R$8725,MATCH($AN33,'Player Pool'!$Z$2:$Z$8725,0))),"") | AU33: =IFERROR(IF(INDEX('Player Pool'!$U$2:$U$8725,MATCH($AN33,'Player Pool'!$Z$2:$Z$8725,0))="","",INDEX('Player Pool'!$U$2:$U$8725,MATCH($AN33,'Player Pool'!$Z$2:$Z$8725,0))),"") | AV33: =IFERROR(IF($AN33="","",IF(INDEX('Player Pool'!$G$2:$G$8725,MATCH($AN33,'Player Pool'!$Z$2:$Z$8725,0))="FA","FA",IF(INDEX('Player Pool'!$G$2:$G$8725,MATCH($AN33,'Player Pool'!$Z$2:$Z$8725,0))='League Settings'!$B$2,"MINE","TAKEN"))),"")
A34: =IFERROR(IF(INDEX(Rosters!$B$2:$B$516,$S34)="","",INDEX(Rosters!$B$2:$B$516,$S34)),"") | B34: =IFERROR(IF(INDEX(Rosters!$C$2:$C$516,$S34)="","",INDEX(Rosters!$C$2:$C$516,$S34)),"") | C34: =IFERROR(IF(INDEX(Rosters!$D$2:$D$516,$S34)="","",INDEX(Rosters!$D$2:$D$516,$S34)),"") | D34: =IFERROR(IF(INDEX(Rosters!$E$2:$E$516,$S34)="","",INDEX(Rosters!$E$2:$E$516,$S34)),"") | E34: =IFERROR(IF(INDEX(Rosters!$F$2:$F$516,$S34)="","",INDEX(Rosters!$F$2:$F$516,$S34)),"") | F34: =IFERROR(IF(INDEX(Rosters!$G$2:$G$516,$S34)="","",INDEX(Rosters!$G$2:$G$516,$S34)),"") | G34: =IFERROR(IF(INDEX(Rosters!$H$2:$H$516,$S34)="","",INDEX(Rosters!$H$2:$H$516,$S34)),"") | H34: =IFERROR(IF(INDEX(Rosters!$I$2:$I$516,$S34)="","",INDEX(Rosters!$I$2:$I$516,$S34)),"") | I34: =IFERROR(IF(INDEX(Rosters!$J$2:$J$516,$S34)="","",INDEX(Rosters!$J$2:$J$516,$S34)),"") | J34: =IFERROR(IF(INDEX(Rosters!$S$2:$S$516,$S34)="","",INDEX(Rosters!$S$2:$S$516,$S34)),"") | K34: =IFERROR(IF(INDEX(Rosters!$K$2:$K$516,$S34)="","",INDEX(Rosters!$K$2:$K$516,$S34)),"") | L34: =IFERROR(IF(INDEX(Rosters!$T$2:$T$516,$S34)="","",INDEX(Rosters!$T$2:$T$516,$S34)),"") | M34: =IFERROR(IF(INDEX(Rosters!$L$2:$L$516,$S34)="","",INDEX(Rosters!$L$2:$L$516,$S34)),"") | N34: =IFERROR(IF(INDEX(Rosters!$Q$2:$Q$516,$S34)="","",INDEX(Rosters!$Q$2:$Q$516,$S34)),"") | O34: =IFERROR(IF(INDEX(Rosters!$R$2:$R$516,$S34)="","",INDEX(Rosters!$R$2:$R$516,$S34)),"") | P34: =IFERROR(IF(INDEX(Rosters!$N$2:$N$516,$S34)="","",INDEX(Rosters!$N$2:$N$516,$S34)),"") | Q34: =IFERROR(IF(INDEX(Rosters!$O$2:$O$516,$S34)="","",INDEX(Rosters!$O$2:$O$516,$S34)),"") | R34: =IFERROR(IF(INDEX(Rosters!$P$2:$P$516,$S34)="","",INDEX(Rosters!$P$2:$P$516,$S34)),"") | S34: =IFERROR(MATCH('League Settings'!$B$2&"|INJURED_RESERVE|"&2,Rosters!$AD$2:$AD$516,0),"") | U34: =IFERROR(IF(INDEX('Player Pool'!$D$2:$D$8725,MATCH($T34,'Player Pool'!$Z$2:$Z$8725,0))="","",INDEX('Player Pool'!$D$2:$D$8725,MATCH($T34,'Player Pool'!$Z$2:$Z$8725,0))),"") | V34: =IFERROR(IF(INDEX('Player Pool'!$E$2:$E$8725,MATCH($T34,'Player Pool'!$Z$2:$Z$8725,0))="","",INDEX('Player Pool'!$E$2:$E$8725,MATCH($T34,'Player Pool'!$Z$2:$Z$8725,0))),"") | W34: =IFERROR(IF($T34="","",IF(ISNUMBER(IFERROR(INDEX(Rosters!$I$2:$I$516,MATCH(INDEX('Player Pool'!$V$2:$V$8725,MATCH($T34,'Player Pool'!$Z$2:$Z$8725,0)),Rosters!$W$2:$W$516,0)),"")),IFERROR(INDEX(Rosters!$I$2:$I$516,MATCH(INDEX('Player Pool'!$V$2:$V$8725,MATCH($T34,'Player Pool'!$Z$2:$Z$8725,0)),Rosters!$W$2:$W$516,0)),""),INDEX('Player Pool'!$H$2:$H$8725,MATCH($T34,'Player Pool'!$Z$2:$Z$8725,0)))),"") | X34: =IFERROR(IF(INDEX('Player Pool'!$I$2:$I$8725,MATCH($T34,'Player Pool'!$Z$2:$Z$8725,0))="","",INDEX('Player Pool'!$I$2:$I$8725,MATCH($T34,'Player Pool'!$Z$2:$Z$8725,0))),"") | Y34: =IFERROR(IF(INDEX('Player Pool'!$P$2:$P$8725,MATCH($T34,'Player Pool'!$Z$2:$Z$8725,0))="","",INDEX('Player Pool'!$P$2:$P$8725,MATCH($T34,'Player Pool'!$Z$2:$Z$8725,0))),"") | Z34: =IFERROR(IF(INDEX('Player Pool'!$R$2:$R$8725,MATCH($T34,'Player Pool'!$Z$2:$Z$8725,0))="","",INDEX('Player Pool'!$R$2:$R$8725,MATCH($T34,'Player Pool'!$Z$2:$Z$8725,0))),"") | AA34: =IFERROR(IF(INDEX('Player Pool'!$U$2:$U$8725,MATCH($T34,'Player Pool'!$Z$2:$Z$8725,0))="","",INDEX('Player Pool'!$U$2:$U$8725,MATCH($T34,'Player Pool'!$Z$2:$Z$8725,0))),"") | AB34: =IFERROR(IF($T34="","",IF(INDEX('Player Pool'!$G$2:$G$8725,MATCH($T34,'Player Pool'!$Z$2:$Z$8725,0))="FA","FA",IF(INDEX('Player Pool'!$G$2:$G$8725,MATCH($T34,'Player Pool'!$Z$2:$Z$8725,0))='League Settings'!$B$2,"MINE","TAKEN"))),"") | AE34: =IFERROR(IF(INDEX('Player Pool'!$D$2:$D$8725,MATCH($AD34,'Player Pool'!$Z$2:$Z$8725,0))="","",INDEX('Player Pool'!$D$2:$D$8725,MATCH($AD34,'Player Pool'!$Z$2:$Z$8725,0))),"") | AF34: =IFERROR(IF(INDEX('Player Pool'!$E$2:$E$8725,MATCH($AD34,'Player Pool'!$Z$2:$Z$8725,0))="","",INDEX('Player Pool'!$E$2:$E$8725,MATCH($AD34,'Player Pool'!$Z$2:$Z$8725,0))),"") | AG34: =IFERROR(IF($AD34="","",IF(ISNUMBER(IFERROR(INDEX(Rosters!$I$2:$I$516,MATCH(INDEX('Player Pool'!$V$2:$V$8725,MATCH($AD34,'Player Pool'!$Z$2:$Z$8725,0)),Rosters!$W$2:$W$516,0)),"")),IFERROR(INDEX(Rosters!$I$2:$I$516,MATCH(INDEX('Player Pool'!$V$2:$V$8725,MATCH($AD34,'Player Pool'!$Z$2:$Z$8725,0)),Rosters!$W$2:$W$516,0)),""),INDEX('Player Pool'!$H$2:$H$8725,MATCH($AD34,'Player Pool'!$Z$2:$Z$8725,0)))),"") | AH34: =IFERROR(IF(INDEX('Player Pool'!$I$2:$I$8725,MATCH($AD34,'Player Pool'!$Z$2:$Z$8725,0))="","",INDEX('Player Pool'!$I$2:$I$8725,MATCH($AD34,'Player Pool'!$Z$2:$Z$8725,0))),"") | AI34: =IFERROR(IF(INDEX('Player Pool'!$P$2:$P$8725,MATCH($AD34,'Player Pool'!$Z$2:$Z$8725,0))="","",INDEX('Player Pool'!$P$2:$P$8725,MATCH($AD34,'Player Pool'!$Z$2:$Z$8725,0))),"") | AJ34: =IFERROR(IF(INDEX('Player Pool'!$R$2:$R$8725,MATCH($AD34,'Player Pool'!$Z$2:$Z$8725,0))="","",INDEX('Player Pool'!$R$2:$R$8725,MATCH($AD34,'Player Pool'!$Z$2:$Z$8725,0))),"") | AK34: =IFERROR(IF(INDEX('Player Pool'!$U$2:$U$8725,MATCH($AD34,'Player Pool'!$Z$2:$Z$8725,0))="","",INDEX('Player Pool'!$U$2:$U$8725,MATCH($AD34,'Player Pool'!$Z$2:$Z$8725,0))),"") | AL34: =IFERROR(IF($AD34="","",IF(INDEX('Player Pool'!$G$2:$G$8725,MATCH($AD34,'Player Pool'!$Z$2:$Z$8725,0))="FA","FA",IF(INDEX('Player Pool'!$G$2:$G$8725,MATCH($AD34,'Player Pool'!$Z$2:$Z$8725,0))='League Settings'!$B$2,"MINE","TAKEN"))),"") | AO34: =IFERROR(IF(INDEX('Player Pool'!$D$2:$D$8725,MATCH($AN34,'Player Pool'!$Z$2:$Z$8725,0))="","",INDEX('Player Pool'!$D$2:$D$8725,MATCH($AN34,'Player Pool'!$Z$2:$Z$8725,0))),"") | AP34: =IFERROR(IF(INDEX('Player Pool'!$E$2:$E$8725,MATCH($AN34,'Player Pool'!$Z$2:$Z$8725,0))="","",INDEX('Player Pool'!$E$2:$E$8725,MATCH($AN34,'Player Pool'!$Z$2:$Z$8725,0))),"") | AQ34: =IFERROR(IF($AN34="","",IF(ISNUMBER(IFERROR(INDEX(Rosters!$I$2:$I$516,MATCH(INDEX('Player Pool'!$V$2:$V$8725,MATCH($AN34,'Player Pool'!$Z$2:$Z$8725,0)),Rosters!$W$2:$W$516,0)),"")),IFERROR(INDEX(Rosters!$I$2:$I$516,MATCH(INDEX('Player Pool'!$V$2:$V$8725,MATCH($AN34,'Player Pool'!$Z$2:$Z$8725,0)),Rosters!$W$2:$W$516,0)),""),INDEX('Player Pool'!$H$2:$H$8725,MATCH($AN34,'Player Pool'!$Z$2:$Z$8725,0)))),"") | AR34: =IFERROR(IF(INDEX('Player Pool'!$I$2:$I$8725,MATCH($AN34,'Player Pool'!$Z$2:$Z$8725,0))="","",INDEX('Player Pool'!$I$2:$I$8725,MATCH($AN34,'Player Pool'!$Z$2:$Z$8725,0))),"") | AS34: =IFERROR(IF(INDEX('Player Pool'!$P$2:$P$8725,MATCH($AN34,'Player Pool'!$Z$2:$Z$8725,0))="","",INDEX('Player Pool'!$P$2:$P$8725,MATCH($AN34,'Player Pool'!$Z$2:$Z$8725,0))),"") | AT34: =IFERROR(IF(INDEX('Player Pool'!$R$2:$R$8725,MATCH($AN34,'Player Pool'!$Z$2:$Z$8725,0))="","",INDEX('Player Pool'!$R$2:$R$8725,MATCH($AN34,'Player Pool'!$Z$2:$Z$8725,0))),"") | AU34: =IFERROR(IF(INDEX('Player Pool'!$U$2:$U$8725,MATCH($AN34,'Player Pool'!$Z$2:$Z$8725,0))="","",INDEX('Player Pool'!$U$2:$U$8725,MATCH($AN34,'Player Pool'!$Z$2:$Z$8725,0))),"") | AV34: =IFERROR(IF($AN34="","",IF(INDEX('Player Pool'!$G$2:$G$8725,MATCH($AN34,'Player Pool'!$Z$2:$Z$8725,0))="FA","FA",IF(INDEX('Player Pool'!$G$2:$G$8725,MATCH($AN34,'Player Pool'!$Z$2:$Z$8725,0))='League Settings'!$B$2,"MINE","TAKEN"))),"")
A35: ="IR subtotal ("&COUNTIF(A33:A34,"?*")&")" | T35: ="IR ("&COUNTIF(T33:T34,"?*")&")" | W35: =SUM(W33:W34) | X35: =SUM(X33:X34) | Y35: =SUM(Y33:Y34) | AD35: ="IR ("&COUNTIF(AD33:AD34,"?*")&")" | AG35: =SUM(AG33:AG34) | AH35: =SUM(AH33:AH34) | AI35: =SUM(AI33:AI34) | AN35: ="IR ("&COUNTIF(AN33:AN34,"?*")&")" | AQ35: =SUM(AQ33:AQ34) | AR35: =SUM(AR33:AR34) | AS35: =SUM(AS33:AS34)
A37: MINORS - outside the cap, does NOT score | T37: MINORS - outside the cap, does NOT score | AD37: MINORS - outside the cap, does NOT score | AN37: MINORS - outside the cap, does NOT score
A38: =IFERROR(IF(INDEX(Rosters!$B$2:$B$516,$S38)="","",INDEX(Rosters!$B$2:$B$516,$S38)),"") | B38: =IFERROR(IF(INDEX(Rosters!$C$2:$C$516,$S38)="","",INDEX(Rosters!$C$2:$C$516,$S38)),"") | C38: =IFERROR(IF(INDEX(Rosters!$D$2:$D$516,$S38)="","",INDEX(Rosters!$D$2:$D$516,$S38)),"") | D38: =IFERROR(IF(INDEX(Rosters!$E$2:$E$516,$S38)="","",INDEX(Rosters!$E$2:$E$516,$S38)),"") | E38: =IFERROR(IF(INDEX(Rosters!$F$2:$F$516,$S38)="","",INDEX(Rosters!$F$2:$F$516,$S38)),"") | F38: =IFERROR(IF(INDEX(Rosters!$G$2:$G$516,$S38)="","",INDEX(Rosters!$G$2:$G$516,$S38)),"") | G38: =IFERROR(IF(INDEX(Rosters!$H$2:$H$516,$S38)="","",INDEX(Rosters!$H$2:$H$516,$S38)),"") | H38: =IFERROR(IF(INDEX(Rosters!$I$2:$I$516,$S38)="","",INDEX(Rosters!$I$2:$I$516,$S38)),"") | I38: =IFERROR(IF(INDEX(Rosters!$J$2:$J$516,$S38)="","",INDEX(Rosters!$J$2:$J$516,$S38)),"") | J38: =IFERROR(IF(INDEX(Rosters!$S$2:$S$516,$S38)="","",INDEX(Rosters!$S$2:$S$516,$S38)),"") | K38: =IFERROR(IF(INDEX(Rosters!$K$2:$K$516,$S38)="","",INDEX(Rosters!$K$2:$K$516,$S38)),"") | L38: =IFERROR(IF(INDEX(Rosters!$T$2:$T$516,$S38)="","",INDEX(Rosters!$T$2:$T$516,$S38)),"") | M38: =IFERROR(IF(INDEX(Rosters!$L$2:$L$516,$S38)="","",INDEX(Rosters!$L$2:$L$516,$S38)),"") | N38: =IFERROR(IF(INDEX(Rosters!$Q$2:$Q$516,$S38)="","",INDEX(Rosters!$Q$2:$Q$516,$S38)),"") | O38: =IFERROR(IF(INDEX(Rosters!$R$2:$R$516,$S38)="","",INDEX(Rosters!$R$2:$R$516,$S38)),"") | P38: =IFERROR(IF(INDEX(Rosters!$N$2:$N$516,$S38)="","",INDEX(Rosters!$N$2:$N$516,$S38)),"") | Q38: =IFERROR(IF(INDEX(Rosters!$O$2:$O$516,$S38)="","",INDEX(Rosters!$O$2:$O$516,$S38)),"") | R38: =IFERROR(IF(INDEX(Rosters!$P$2:$P$516,$S38)="","",INDEX(Rosters!$P$2:$P$516,$S38)),"") | S38: =IFERROR(MATCH('League Settings'!$B$2&"|MINORS|"&1,Rosters!$AD$2:$AD$516,0),"") | T38: Sergei Murashov (PIT G) | U38: =IFERROR(IF(INDEX('Player Pool'!$D$2:$D$8725,MATCH($T38,'Player Pool'!$Z$2:$Z$8725,0))="","",INDEX('Player Pool'!$D$2:$D$8725,MATCH($T38,'Player Pool'!$Z$2:$Z$8725,0))),"") | V38: =IFERROR(IF(INDEX('Player Pool'!$E$2:$E$8725,MATCH($T38,'Player Pool'!$Z$2:$Z$8725,0))="","",INDEX('Player Pool'!$E$2:$E$8725,MATCH($T38,'Player Pool'!$Z$2:$Z$8725,0))),"") | W38: =IFERROR(IF($T38="","",IF(ISNUMBER(IFERROR(INDEX(Rosters!$I$2:$I$516,MATCH(INDEX('Player Pool'!$V$2:$V$8725,MATCH($T38,'Player Pool'!$Z$2:$Z$8725,0)),Rosters!$W$2:$W$516,0)),"")),IFERROR(INDEX(Rosters!$I$2:$I$516,MATCH(INDEX('Player Pool'!$V$2:$V$8725,MATCH($T38,'Player Pool'!$Z$2:$Z$8725,0)),Rosters!$W$2:$W$516,0)),""),INDEX('Player Pool'!$H$2:$H$8725,MATCH($T38,'Player Pool'!$Z$2:$Z$8725,0)))),"") | X38: =IFERROR(IF(INDEX('Player Pool'!$I$2:$I$8725,MATCH($T38,'Player Pool'!$Z$2:$Z$8725,0))="","",INDEX('Player Pool'!$I$2:$I$8725,MATCH($T38,'Player Pool'!$Z$2:$Z$8725,0))),"") | Y38: =IFERROR(IF(INDEX('Player Pool'!$P$2:$P$8725,MATCH($T38,'Player Pool'!$Z$2:$Z$8725,0))="","",INDEX('Player Pool'!$P$2:$P$8725,MATCH($T38,'Player Pool'!$Z$2:$Z$8725,0))),"") | Z38: =IFERROR(IF(INDEX('Player Pool'!$R$2:$R$8725,MATCH($T38,'Player Pool'!$Z$2:$Z$8725,0))="","",INDEX('Player Pool'!$R$2:$R$8725,MATCH($T38,'Player Pool'!$Z$2:$Z$8725,0))),"") | AA38: =IFERROR(IF(INDEX('Player Pool'!$U$2:$U$8725,MATCH($T38,'Player Pool'!$Z$2:$Z$8725,0))="","",INDEX('Player Pool'!$U$2:$U$8725,MATCH($T38,'Player Pool'!$Z$2:$Z$8725,0))),"") | AB38: =IFERROR(IF($T38="","",IF(INDEX('Player Pool'!$G$2:$G$8725,MATCH($T38,'Player Pool'!$Z$2:$Z$8725,0))="FA","FA",IF(INDEX('Player Pool'!$G$2:$G$8725,MATCH($T38,'Player Pool'!$Z$2:$Z$8725,0))='League Settings'!$B$2,"MINE","TAKEN"))),"") | AD38: Sergei Murashov (PIT G) | AE38: =IFERROR(IF(INDEX('Player Pool'!$D$2:$D$8725,MATCH($AD38,'Player Pool'!$Z$2:$Z$8725,0))="","",INDEX('Player Pool'!$D$2:$D$8725,MATCH($AD38,'Player Pool'!$Z$2:$Z$8725,0))),"") | AF38: =IFERROR(IF(INDEX('Player Pool'!$E$2:$E$8725,MATCH($AD38,'Player Pool'!$Z$2:$Z$8725,0))="","",INDEX('Player Pool'!$E$2:$E$8725,MATCH($AD38,'Player Pool'!$Z$2:$Z$8725,0))),"") | AG38: =IFERROR(IF($AD38="","",IF(ISNUMBER(IFERROR(INDEX(Rosters!$I$2:$I$516,MATCH(INDEX('Player Pool'!$V$2:$V$8725,MATCH($AD38,'Player Pool'!$Z$2:$Z$8725,0)),Rosters!$W$2:$W$516,0)),"")),IFERROR(INDEX(Rosters!$I$2:$I$516,MATCH(INDEX('Player Pool'!$V$2:$V$8725,MATCH($AD38,'Player Pool'!$Z$2:$Z$8725,0)),Rosters!$W$2:$W$516,0)),""),INDEX('Player Pool'!$H$2:$H$8725,MATCH($AD38,'Player Pool'!$Z$2:$Z$8725,0)))),"") | AH38: =IFERROR(IF(INDEX('Player Pool'!$I$2:$I$8725,MATCH($AD38,'Player Pool'!$Z$2:$Z$8725,0))="","",INDEX('Player Pool'!$I$2:$I$8725,MATCH($AD38,'Player Pool'!$Z$2:$Z$8725,0))),"") | AI38: =IFERROR(IF(INDEX('Player Pool'!$P$2:$P$8725,MATCH($AD38,'Player Pool'!$Z$2:$Z$8725,0))="","",INDEX('Player Pool'!$P$2:$P$8725,MATCH($AD38,'Player Pool'!$Z$2:$Z$8725,0))),"") | AJ38: =IFERROR(IF(INDEX('Player Pool'!$R$2:$R$8725,MATCH($AD38,'Player Pool'!$Z$2:$Z$8725,0))="","",INDEX('Player Pool'!$R$2:$R$8725,MATCH($AD38,'Player Pool'!$Z$2:$Z$8725,0))),"") | AK38: =IFERROR(IF(INDEX('Player Pool'!$U$2:$U$8725,MATCH($AD38,'Player Pool'!$Z$2:$Z$8725,0))="","",INDEX('Player Pool'!$U$2:$U$8725,MATCH($AD38,'Player Pool'!$Z$2:$Z$8725,0))),"") | AL38: =IFERROR(IF($AD38="","",IF(INDEX('Player Pool'!$G$2:$G$8725,MATCH($AD38,'Player Pool'!$Z$2:$Z$8725,0))="FA","FA",IF(INDEX('Player Pool'!$G$2:$G$8725,MATCH($AD38,'Player Pool'!$Z$2:$Z$8725,0))='League Settings'!$B$2,"MINE","TAKEN"))),"") | AN38: Sergei Murashov (PIT G) | AO38: =IFERROR(IF(INDEX('Player Pool'!$D$2:$D$8725,MATCH($AN38,'Player Pool'!$Z$2:$Z$8725,0))="","",INDEX('Player Pool'!$D$2:$D$8725,MATCH($AN38,'Player Pool'!$Z$2:$Z$8725,0))),"") | AP38: =IFERROR(IF(INDEX('Player Pool'!$E$2:$E$8725,MATCH($AN38,'Player Pool'!$Z$2:$Z$8725,0))="","",INDEX('Player Pool'!$E$2:$E$8725,MATCH($AN38,'Player Pool'!$Z$2:$Z$8725,0))),"") | AQ38: =IFERROR(IF($AN38="","",IF(ISNUMBER(IFERROR(INDEX(Rosters!$I$2:$I$516,MATCH(INDEX('Player Pool'!$V$2:$V$8725,MATCH($AN38,'Player Pool'!$Z$2:$Z$8725,0)),Rosters!$W$2:$W$516,0)),"")),IFERROR(INDEX(Rosters!$I$2:$I$516,MATCH(INDEX('Player Pool'!$V$2:$V$8725,MATCH($AN38,'Player Pool'!$Z$2:$Z$8725,0)),Rosters!$W$2:$W$516,0)),""),INDEX('Player Pool'!$H$2:$H$8725,MATCH($AN38,'Player Pool'!$Z$2:$Z$8725,0)))),"") | AR38: =IFERROR(IF(INDEX('Player Pool'!$I$2:$I$8725,MATCH($AN38,'Player Pool'!$Z$2:$Z$8725,0))="","",INDEX('Player Pool'!$I$2:$I$8725,MATCH($AN38,'Player Pool'!$Z$2:$Z$8725,0))),"") | AS38: =IFERROR(IF(INDEX('Player Pool'!$P$2:$P$8725,MATCH($AN38,'Player Pool'!$Z$2:$Z$8725,0))="","",INDEX('Player Pool'!$P$2:$P$8725,MATCH($AN38,'Player Pool'!$Z$2:$Z$8725,0))),"") | AT38: =IFERROR(IF(INDEX('Player Pool'!$R$2:$R$8725,MATCH($AN38,'Player Pool'!$Z$2:$Z$8725,0))="","",INDEX('Player Pool'!$R$2:$R$8725,MATCH($AN38,'Player Pool'!$Z$2:$Z$8725,0))),"") | AU38: =IFERROR(IF(INDEX('Player Pool'!$U$2:$U$8725,MATCH($AN38,'Player Pool'!$Z$2:$Z$8725,0))="","",INDEX('Player Pool'!$U$2:$U$8725,MATCH($AN38,'Player Pool'!$Z$2:$Z$8725,0))),"") | AV38: =IFERROR(IF($AN38="","",IF(INDEX('Player Pool'!$G$2:$G$8725,MATCH($AN38,'Player Pool'!$Z$2:$Z$8725,0))="FA","FA",IF(INDEX('Player Pool'!$G$2:$G$8725,MATCH($AN38,'Player Pool'!$Z$2:$Z$8725,0))='League Settings'!$B$2,"MINE","TAKEN"))),"")
A39: =IFERROR(IF(INDEX(Rosters!$B$2:$B$516,$S39)="","",INDEX(Rosters!$B$2:$B$516,$S39)),"") | B39: =IFERROR(IF(INDEX(Rosters!$C$2:$C$516,$S39)="","",INDEX(Rosters!$C$2:$C$516,$S39)),"") | C39: =IFERROR(IF(INDEX(Rosters!$D$2:$D$516,$S39)="","",INDEX(Rosters!$D$2:$D$516,$S39)),"") | D39: =IFERROR(IF(INDEX(Rosters!$E$2:$E$516,$S39)="","",INDEX(Rosters!$E$2:$E$516,$S39)),"") | E39: =IFERROR(IF(INDEX(Rosters!$F$2:$F$516,$S39)="","",INDEX(Rosters!$F$2:$F$516,$S39)),"") | F39: =IFERROR(IF(INDEX(Rosters!$G$2:$G$516,$S39)="","",INDEX(Rosters!$G$2:$G$516,$S39)),"") | G39: =IFERROR(IF(INDEX(Rosters!$H$2:$H$516,$S39)="","",INDEX(Rosters!$H$2:$H$516,$S39)),"") | H39: =IFERROR(IF(INDEX(Rosters!$I$2:$I$516,$S39)="","",INDEX(Rosters!$I$2:$I$516,$S39)),"") | I39: =IFERROR(IF(INDEX(Rosters!$J$2:$J$516,$S39)="","",INDEX(Rosters!$J$2:$J$516,$S39)),"") | J39: =IFERROR(IF(INDEX(Rosters!$S$2:$S$516,$S39)="","",INDEX(Rosters!$S$2:$S$516,$S39)),"") | K39: =IFERROR(IF(INDEX(Rosters!$K$2:$K$516,$S39)="","",INDEX(Rosters!$K$2:$K$516,$S39)),"") | L39: =IFERROR(IF(INDEX(Rosters!$T$2:$T$516,$S39)="","",INDEX(Rosters!$T$2:$T$516,$S39)),"") | M39: =IFERROR(IF(INDEX(Rosters!$L$2:$L$516,$S39)="","",INDEX(Rosters!$L$2:$L$516,$S39)),"") | N39: =IFERROR(IF(INDEX(Rosters!$Q$2:$Q$516,$S39)="","",INDEX(Rosters!$Q$2:$Q$516,$S39)),"") | O39: =IFERROR(IF(INDEX(Rosters!$R$2:$R$516,$S39)="","",INDEX(Rosters!$R$2:$R$516,$S39)),"") | P39: =IFERROR(IF(INDEX(Rosters!$N$2:$N$516,$S39)="","",INDEX(Rosters!$N$2:$N$516,$S39)),"") | Q39: =IFERROR(IF(INDEX(Rosters!$O$2:$O$516,$S39)="","",INDEX(Rosters!$O$2:$O$516,$S39)),"") | R39: =IFERROR(IF(INDEX(Rosters!$P$2:$P$516,$S39)="","",INDEX(Rosters!$P$2:$P$516,$S39)),"") | S39: =IFERROR(MATCH('League Settings'!$B$2&"|MINORS|"&2,Rosters!$AD$2:$AD$516,0),"") | T39: Carter Yakemchuk (OTT D) | U39: =IFERROR(IF(INDEX('Player Pool'!$D$2:$D$8725,MATCH($T39,'Player Pool'!$Z$2:$Z$8725,0))="","",INDEX('Player Pool'!$D$2:$D$8725,MATCH($T39,'Player Pool'!$Z$2:$Z$8725,0))),"") | V39: =IFERROR(IF(INDEX('Player Pool'!$E$2:$E$8725,MATCH($T39,'Player Pool'!$Z$2:$Z$8725,0))="","",INDEX('Player Pool'!$E$2:$E$8725,MATCH($T39,'Player Pool'!$Z$2:$Z$8725,0))),"") | W39: =IFERROR(IF($T39="","",IF(ISNUMBER(IFERROR(INDEX(Rosters!$I$2:$I$516,MATCH(INDEX('Player Pool'!$V$2:$V$8725,MATCH($T39,'Player Pool'!$Z$2:$Z$8725,0)),Rosters!$W$2:$W$516,0)),"")),IFERROR(INDEX(Rosters!$I$2:$I$516,MATCH(INDEX('Player Pool'!$V$2:$V$8725,MATCH($T39,'Player Pool'!$Z$2:$Z$8725,0)),Rosters!$W$2:$W$516,0)),""),INDEX('Player Pool'!$H$2:$H$8725,MATCH($T39,'Player Pool'!$Z$2:$Z$8725,0)))),"") | X39: =IFERROR(IF(INDEX('Player Pool'!$I$2:$I$8725,MATCH($T39,'Player Pool'!$Z$2:$Z$8725,0))="","",INDEX('Player Pool'!$I$2:$I$8725,MATCH($T39,'Player Pool'!$Z$2:$Z$8725,0))),"") | Y39: =IFERROR(IF(INDEX('Player Pool'!$P$2:$P$8725,MATCH($T39,'Player Pool'!$Z$2:$Z$8725,0))="","",INDEX('Player Pool'!$P$2:$P$8725,MATCH($T39,'Player Pool'!$Z$2:$Z$8725,0))),"") | Z39: =IFERROR(IF(INDEX('Player Pool'!$R$2:$R$8725,MATCH($T39,'Player Pool'!$Z$2:$Z$8725,0))="","",INDEX('Player Pool'!$R$2:$R$8725,MATCH($T39,'Player Pool'!$Z$2:$Z$8725,0))),"") | AA39: =IFERROR(IF(INDEX('Player Pool'!$U$2:$U$8725,MATCH($T39,'Player Pool'!$Z$2:$Z$8725,0))="","",INDEX('Player Pool'!$U$2:$U$8725,MATCH($T39,'Player Pool'!$Z$2:$Z$8725,0))),"") | AB39: =IFERROR(IF($T39="","",IF(INDEX('Player Pool'!$G$2:$G$8725,MATCH($T39,'Player Pool'!$Z$2:$Z$8725,0))="FA","FA",IF(INDEX('Player Pool'!$G$2:$G$8725,MATCH($T39,'Player Pool'!$Z$2:$Z$8725,0))='League Settings'!$B$2,"MINE","TAKEN"))),"") | AD39: Carter Yakemchuk (OTT D) | AE39: =IFERROR(IF(INDEX('Player Pool'!$D$2:$D$8725,MATCH($AD39,'Player Pool'!$Z$2:$Z$8725,0))="","",INDEX('Player Pool'!$D$2:$D$8725,MATCH($AD39,'Player Pool'!$Z$2:$Z$8725,0))),"") | AF39: =IFERROR(IF(INDEX('Player Pool'!$E$2:$E$8725,MATCH($AD39,'Player Pool'!$Z$2:$Z$8725,0))="","",INDEX('Player Pool'!$E$2:$E$8725,MATCH($AD39,'Player Pool'!$Z$2:$Z$8725,0))),"") | AG39: =IFERROR(IF($AD39="","",IF(ISNUMBER(IFERROR(INDEX(Rosters!$I$2:$I$516,MATCH(INDEX('Player Pool'!$V$2:$V$8725,MATCH($AD39,'Player Pool'!$Z$2:$Z$8725,0)),Rosters!$W$2:$W$516,0)),"")),IFERROR(INDEX(Rosters!$I$2:$I$516,MATCH(INDEX('Player Pool'!$V$2:$V$8725,MATCH($AD39,'Player Pool'!$Z$2:$Z$8725,0)),Rosters!$W$2:$W$516,0)),""),INDEX('Player Pool'!$H$2:$H$8725,MATCH($AD39,'Player Pool'!$Z$2:$Z$8725,0)))),"") | AH39: =IFERROR(IF(INDEX('Player Pool'!$I$2:$I$8725,MATCH($AD39,'Player Pool'!$Z$2:$Z$8725,0))="","",INDEX('Player Pool'!$I$2:$I$8725,MATCH($AD39,'Player Pool'!$Z$2:$Z$8725,0))),"") | AI39: =IFERROR(IF(INDEX('Player Pool'!$P$2:$P$8725,MATCH($AD39,'Player Pool'!$Z$2:$Z$8725,0))="","",INDEX('Player Pool'!$P$2:$P$8725,MATCH($AD39,'Player Pool'!$Z$2:$Z$8725,0))),"") | AJ39: =IFERROR(IF(INDEX('Player Pool'!$R$2:$R$8725,MATCH($AD39,'Player Pool'!$Z$2:$Z$8725,0))="","",INDEX('Player Pool'!$R$2:$R$8725,MATCH($AD39,'Player Pool'!$Z$2:$Z$8725,0))),"") | AK39: =IFERROR(IF(INDEX('Player Pool'!$U$2:$U$8725,MATCH($AD39,'Player Pool'!$Z$2:$Z$8725,0))="","",INDEX('Player Pool'!$U$2:$U$8725,MATCH($AD39,'Player Pool'!$Z$2:$Z$8725,0))),"") | AL39: =IFERROR(IF($AD39="","",IF(INDEX('Player Pool'!$G$2:$G$8725,MATCH($AD39,'Player Pool'!$Z$2:$Z$8725,0))="FA","FA",IF(INDEX('Player Pool'!$G$2:$G$8725,MATCH($AD39,'Player Pool'!$Z$2:$Z$8725,0))='League Settings'!$B$2,"MINE","TAKEN"))),"") | AN39: Carter Yakemchuk (OTT D) | AO39: =IFERROR(IF(INDEX('Player Pool'!$D$2:$D$8725,MATCH($AN39,'Player Pool'!$Z$2:$Z$8725,0))="","",INDEX('Player Pool'!$D$2:$D$8725,MATCH($AN39,'Player Pool'!$Z$2:$Z$8725,0))),"") | AP39: =IFERROR(IF(INDEX('Player Pool'!$E$2:$E$8725,MATCH($AN39,'Player Pool'!$Z$2:$Z$8725,0))="","",INDEX('Player Pool'!$E$2:$E$8725,MATCH($AN39,'Player Pool'!$Z$2:$Z$8725,0))),"") | AQ39: =IFERROR(IF($AN39="","",IF(ISNUMBER(IFERROR(INDEX(Rosters!$I$2:$I$516,MATCH(INDEX('Player Pool'!$V$2:$V$8725,MATCH($AN39,'Player Pool'!$Z$2:$Z$8725,0)),Rosters!$W$2:$W$516,0)),"")),IFERROR(INDEX(Rosters!$I$2:$I$516,MATCH(INDEX('Player Pool'!$V$2:$V$8725,MATCH($AN39,'Player Pool'!$Z$2:$Z$8725,0)),Rosters!$W$2:$W$516,0)),""),INDEX('Player Pool'!$H$2:$H$8725,MATCH($AN39,'Player Pool'!$Z$2:$Z$8725,0)))),"") | AR39: =IFERROR(IF(INDEX('Player Pool'!$I$2:$I$8725,MATCH($AN39,'Player Pool'!$Z$2:$Z$8725,0))="","",INDEX('Player Pool'!$I$2:$I$8725,MATCH($AN39,'Player Pool'!$Z$2:$Z$8725,0))),"") | AS39: =IFERROR(IF(INDEX('Player Pool'!$P$2:$P$8725,MATCH($AN39,'Player Pool'!$Z$2:$Z$8725,0))="","",INDEX('Player Pool'!$P$2:$P$8725,MATCH($AN39,'Player Pool'!$Z$2:$Z$8725,0))),"") | AT39: =IFERROR(IF(INDEX('Player Pool'!$R$2:$R$8725,MATCH($AN39,'Player Pool'!$Z$2:$Z$8725,0))="","",INDEX('Player Pool'!$R$2:$R$8725,MATCH($AN39,'Player Pool'!$Z$2:$Z$8725,0))),"") | AU39: =IFERROR(IF(INDEX('Player Pool'!$U$2:$U$8725,MATCH($AN39,'Player Pool'!$Z$2:$Z$8725,0))="","",INDEX('Player Pool'!$U$2:$U$8725,MATCH($AN39,'Player Pool'!$Z$2:$Z$8725,0))),"") | AV39: =IFERROR(IF($AN39="","",IF(INDEX('Player Pool'!$G$2:$G$8725,MATCH($AN39,'Player Pool'!$Z$2:$Z$8725,0))="FA","FA",IF(INDEX('Player Pool'!$G$2:$G$8725,MATCH($AN39,'Player Pool'!$Z$2:$Z$8725,0))='League Settings'!$B$2,"MINE","TAKEN"))),"")
